Workbook

Sheet Instructions
A1: Cyprus VAT working - instructions
A2: How the working is built, what you do each quarter, and how each part feeds the VAT 4 return.
B4: 1. What this working does
B5: It takes the full general ledger (GL) for the VAT quarter, gives every line a VAT treatment code (through the account mapping, or an override on the line), classifies the counterparty as Cyprus (CY), other EU member state (EU) or third country (3RD) and as inter-company (Y) or third party (N), converts foreign-currency amounts to EUR at the quarterly average ECB rate, and builds the VAT 4 return (Boxes 1-11B), the VIES summary, an inter-company analysis and reconciliations to the VAT control accounts.
B6: All results are Excel formulas. Change a mapping, a country or a rate and every sheet updates.
B8: 2. Sheets
B9: Instructions - this page.
B10: Settings - company details, quarter dates, pro-rata %, VAT control accounts, GL column names for the import script. (Yellow cells = your input.)
B11: GL_Input - the full GL for the quarter. Columns A-L are inputs (paste or import). Columns M-Z are formulas - do not overwrite them.
B12: Account_Mapping - one row per GL account with its default VAT code. Carried forward from quarter to quarter.
B13: Counterparties - one row per customer/supplier: country (ISO code), VAT number and inter-company flag. Drives the EU / 3rd-country / inter-company split.
B14: VAT_Codes - the VAT treatments and which return boxes each one feeds. Totals per code are calculated here.
B15: FX_Rates / FX_Daily - daily ECB euro reference rates for the quarter and the quarterly average used in GL_Input.
B16: VAT_Return - the VAT 4 form with every box, the amount, what the box must include and which codes feed it.
... B59: The VAT codes and box mapping follow the Tax Department's VAT 4 guidance and Big Four / practitioner guides as at October 2026. VAT rules (rates, temporary zero rates, reverse-charge lists) change often - review VAT_Codes and Legal_Notes every quarter. This working is a preparation tool, not tax advice; complex items (property, construction, capital goods adjustments, partial exemption annual adjustments, VAT groups, fixed establishments) need specific review.

Sheet Settings
A1: Settings
A2: Yellow cells are inputs. Dates drive the period checks, VIES months and due date.
B4: Company name | C4: Example Holdings Ltd | D4: Legal name as registered with the Tax Department.
B5: VAT registration number | C5: 10000000X | D5: Cyprus VAT number (8 digits + letter).
B6: Tax Identification Code (TIC) | D6: Optional.
B7: Quarter | C7: Q3 2026 | D7: Label only.
B8: Period start | C8: 46204 | D8: First day of the VAT quarter.
B9: Period end | C9: 46295 | D9: Last day of the VAT quarter.
B10: Input VAT recovery % (pro-rata) for mixed-use costs | C10: 1 | D10: Provisional % = taxable (incl. outside-scope with right) supplies / total supplies of the previous year. 100% if no exempt supplies. Annual adjustment at year end.
B11: Reverse-charge VAT is booked in the GL VAT control accounts? (Y/N) | C11: N | D11: Y if your bookkeeping posts the self-assessed reverse-charge VAT to the output and input VAT accounts. Used by the Reconciliation sheet.
B12: Reconciliation tolerance (EUR) | C12: 5 | D12: Differences above this amount are flagged.
B13: Return and payment due date | C13: =DATE(YEAR(C9),MONTH(C9)+2,10) -> 46336 | D13: 10th day of the second month after the end of the quarter (next working day if a weekend / holiday).
B14: VIES statements due | C14: 15th of each following month | D14: Monthly recapitulative statement for EU supplies of goods and services (TFA portal).
B17: Output VAT control account codes (credit balances)
B18: Output VAT account 1 | C18: 2201
B19: Output VAT account 2
B20: Output VAT account 3
B21: Output VAT account 4
B22: Output VAT account 5
B25: Input VAT control account codes (debit balances) - excl. import VAT account
B26: Input VAT account 1 | C26: 2101
B27: Input VAT account 2
B28: Input VAT account 3
B29: Input VAT account 4
B30: Input VAT account 5
B33: GL column map (for the import-gl command) | D33: Type the header text exactly as it appears in your GL export. Leave blank if the column does not exist. Give either 'Amount' (Dr + / Cr -) or both 'Debit' and 'Credit'.
B34: Working field | C34: Header in your GL export | D34: Notes
B35: date | C35: Date | D35: Posting or document date.
B36: doc | C36: Doc No
B37: account | C37: Account | D37: Account code.
B38: account_name | C38: Account Name
B39: description | C39: Description
B40: cp_code | C40: Counterparty | D40: Customer / supplier code (or name) - the key to Counterparties.
B41: cp_name | C41: Counterparty Name
B42: currency | C42: Currency | D42: ISO currency code. Blank = EUR.
B43: amount_fc | C43: Amount | D43: Signed amount in transaction currency (Dr + / Cr -).
B44: debit_fc | D44: Use instead of 'Amount' when the export has separate debit and credit columns.
B45: credit_fc
B46: amount_eur | D46: Optional: amount already in EUR (Dr + / Cr -). Takes priority over the FX conversion.
B47: vat_code | D47: Optional: VAT/tax code from your accounting system, if it uses the same codes as VAT_Codes.
B48: vat_fc | D48: Optional: VAT amount of the line in transaction currency.

Sheet GL_Input
A1: GL_Input - full general ledger for the VAT quarter
A2: Columns A-L: paste/import your GL (Debit = +, Credit = -). Columns M-Z: formulas, do not overwrite. Filter column Z for exceptions.
A3: INPUT >>> | M3: CALCULATED >>>
A4: Date | B4: Journal / Doc no. | C4: Account code | D4: Account name | E4: Description | F4: Counterparty code | G4: Counterparty name | H4: Currency | I4: Amount in currency (Dr + / Cr -) | J4: Amount EUR if in GL (Dr + / Cr -) | K4: VAT code override (optional) | L4: VAT amount in currency (optional) | M4: Account VAT code | N4: VAT code used | O4: Country | P4: Region (CY/EU/3RD) | Q4: Inter-company (Y/N) | R4: FX rate (ccy per EUR) | S4: Amount EUR (Dr + / Cr -) | T4: Nature | U4: Return value EUR | V4: VAT rate | W4: VAT EUR | X4: VIES type | Y4: Month in quarter | Z4: Check
A5: 46208 | B5: SI-1001 | C5: 4000 | D5: Sales - Cyprus customers | E5: Consulting services July | F5: C-CY01 | G5: Limassol Trading Ltd | H5: EUR | I5: -10000 | M5: =IF($C5="","",IFERROR(INDEX(Account_Mapping!$C:$C,MATCH($C5&"",Account_Mapping!$A:$A,0))&"","")) -> S19 | N5: =IF($K5<>"",$K5,$M5) -> S19 | O5: =IF($F5="","",IFERROR(INDEX(Counterparties!$C:$C,MATCH($F5&"",Counterparties!$A:$A,0))&"","")) -> CY | P5: =IF($O5="","",IF($O5="CY","CY",IF(ISNUMBER(MATCH($O5,Lists!$A:$A,0)),"EU","3RD"))) -> CY | Q5: =IF($F5="","N",IFERROR(IF(INDEX(Counterparties!$E:$E,MATCH($F5&"",Counterparties!$A:$A,0))="Y","Y","N"),"N")) -> N | R5: =IF(OR($H5="",$H5="EUR"),1,IFERROR(INDEX(FX_Rates!$D:$D,MATCH($H5,FX_Rates!$A:$A,0)),"")) -> 1 | S5: =IF(AND($I5="",$J5=""),"",IF($J5<>"",$J5,IF(OR($R5="",$R5=0),"",ROUND($I5/$R5,2)))) -> -10000 | T5: =IF($N5="","",IFERROR(INDEX(VAT_Codes!$C:$C,MATCH($N5,VAT_Codes!$A:$A,0)),"")&"") -> Output | U5: =IF(OR($S5="",$T5="",$T5="None"),0,IF($T5="Output",-$S5,$S5)) -> 10000 | V5: =IF($N5="",0,IFERROR(INDEX(VAT_Codes!$D:$D,MATCH($N5,VAT_Codes!$A:$A,0)),0)) -> 0.19 | W5: =IF($U5=0,0,IF(IFERROR(INDEX(VAT_Codes!$F:$F,MATCH($N5,VAT_Codes!$A:$A,0)),"N")="Y",$U5,IF($L5<>"",ROUND(ABS($L5)/IF(OR($R5="",$R5=0),1,$R5),2)*SIGN($U5),ROUND($U5*$V5,2)))) -> 1900 | X5: =IF($N5="","",IFERROR(INDEX(VAT_Codes!$H:$H,MATCH($N5,VAT_Codes!$A:$A,0)),"")&"") | Y5: =IF($A5="","",(YEAR($A5)-YEAR(Settings!$C$8))*12+MONTH($A5)-MONTH(Settings!$C$8)+1) -> 1 | Z5: =IF(AND($C5="",$I5="",$J5=""),"",IF($N5="","NO VAT CODE",IF($T5="","UNKNOWN VAT CODE",IF($S5="","MISSING FX RATE",IF(OR($A5<Settings!$C$8,$A5>Settings!$C$9),"OUTSIDE PERIOD",IF(AND(IFERROR(INDEX(VAT_Codes!$E:$E,MATCH($N5,VAT_Codes!$A:$A,0)),"ANY")<>"ANY",$P5=""),"MISSING COUNTERPARTY COUNTRY",IF(AND(IFERROR(INDEX(VAT_Codes!$E:$E,MATCH($N5,VAT_Codes!$A:$A,0)),"ANY")<>"ANY",$P5<>IFERROR(INDEX(VAT_Codes!$E:$E,MATCH($N5,VAT_Codes!$A:$A,0)),"ANY")),"REGION MISMATCH","OK"))))))) -> OK
A6: 46208 | B6: SI-1001 | C6: 2201 | D6: Output VAT | E6: VAT on SI-1001 | F6: C-CY01 | G6: Limassol Trading Ltd | H6: EUR | I6: -1900 | M6: =IF($C6="","",IFERROR(INDEX(Account_Mapping!$C:$C,MATCH($C6&"",Account_Mapping!$A:$A,0))&"","")) -> NR | N6: =IF($K6<>"",$K6,$M6) -> NR | O6: =IF($F6="","",IFERROR(INDEX(Counterparties!$C:$C,MATCH($F6&"",Counterparties!$A:$A,0))&"","")) -> CY | P6: =IF($O6="","",IF($O6="CY","CY",IF(ISNUMBER(MATCH($O6,Lists!$A:$A,0)),"EU","3RD"))) -> CY | Q6: =IF($F6="","N",IFERROR(IF(INDEX(Counterparties!$E:$E,MATCH($F6&"",Counterparties!$A:$A,0))="Y","Y","N"),"N")) -> N | R6: =IF(OR($H6="",$H6="EUR"),1,IFERROR(INDEX(FX_Rates!$D:$D,MATCH($H6,FX_Rates!$A:$A,0)),"")) -> 1 | S6: =IF(AND($I6="",$J6=""),"",IF($J6<>"",$J6,IF(OR($R6="",$R6=0),"",ROUND($I6/$R6,2)))) -> -1900 | T6: =IF($N6="","",IFERROR(INDEX(VAT_Codes!$C:$C,MATCH($N6,VAT_Codes!$A:$A,0)),"")&"") -> None | U6: =IF(OR($S6="",$T6="",$T6="None"),0,IF($T6="Output",-$S6,$S6)) -> 0 | V6: =IF($N6="",0,IFERROR(INDEX(VAT_Codes!$D:$D,MATCH($N6,VAT_Codes!$A:$A,0)),0)) -> 0 | W6: =IF($U6=0,0,IF(IFERROR(INDEX(VAT_Codes!$F:$F,MATCH($N6,VAT_Codes!$A:$A,0)),"N")="Y",$U6,IF($L6<>"",ROUND(ABS($L6)/IF(OR($R6="",$R6=0),1,$R6),2)*SIGN($U6),ROUND($U6*$V6,2)))) -> 0 | X6: =IF($N6="","",IFERROR(INDEX(VAT_Codes!$H:$H,MATCH($N6,VAT_Codes!$A:$A,0)),"")&"") | Y6: =IF($A6="","",(YEAR($A6)-YEAR(Settings!$C$8))*12+MONTH($A6)-MONTH(Settings!$C$8)+1) -> 1 | Z6: =IF(AND($C6="",$I6="",$J6=""),"",IF($N6="","NO VAT CODE",IF($T6="","UNKNOWN VAT CODE",IF($S6="","MISSING FX RATE",IF(OR($A6<Settings!$C$8,$A6>Settings!$C$9),"OUTSIDE PERIOD",IF(AND(IFERROR(INDEX(VAT_Codes!$E:$E,MATCH($N6,VAT_Codes!$A:$A,0)),"ANY")<>"ANY",$P6=""),"MISSING COUNTERPARTY COUNTRY",IF(AND(IFERROR(INDEX(VAT_Codes!$E:$E,MATCH($N6,VAT_Codes!$A:$A,0)),"ANY")<>"ANY",$P6<>IFERROR(INDEX(VAT_Codes!$E:$E,MATCH($N6,VAT_Codes!$A:$A,0)),"ANY")),"REGION MISMATCH","OK"))))))) -> OK
A7: 46231 | B7: SI-1002 | C7: 4100 | D7: Management fees - group | E7: Q3 management fee | F7: IC-DE01 | G7: Example GmbH (group) | H7: EUR | I7: -25000 | M7: =IF($C7="","",IFERROR(INDEX(Account_Mapping!$C:$C,MATCH($C7&"",Account_Mapping!$A:$A,0))&"","")) -> EUS | N7: =IF($K7<>"",$K7,$M7) -> EUS | O7: =IF($F7="","",IFERROR(INDEX(Counterparties!$C:$C,MATCH($F7&"",Counterparties!$A:$A,0))&"","")) -> DE | P7: =IF($O7="","",IF($O7="CY","CY",IF(ISNUMBER(MATCH($O7,Lists!$A:$A,0)),"EU","3RD"))) -> EU | Q7: =IF($F7="","N",IFERROR(IF(INDEX(Counterparties!$E:$E,MATCH($F7&"",Counterparties!$A:$A,0))="Y","Y","N"),"N")) -> Y | R7: =IF(OR($H7="",$H7="EUR"),1,IFERROR(INDEX(FX_Rates!$D:$D,MATCH($H7,FX_Rates!$A:$A,0)),"")) -> 1 | S7: =IF(AND($I7="",$J7=""),"",IF($J7<>"",$J7,IF(OR($R7="",$R7=0),"",ROUND($I7/$R7,2)))) -> -25000 | T7: =IF($N7="","",IFERROR(INDEX(VAT_Codes!$C:$C,MATCH($N7,VAT_Codes!$A:$A,0)),"")&"") -> Output | U7: =IF(OR($S7="",$T7="",$T7="None"),0,IF($T7="Output",-$S7,$S7)) -> 25000 | V7: =IF($N7="",0,IFERROR(INDEX(VAT_Codes!$D:$D,MATCH($N7,VAT_Codes!$A:$A,0)),0)) -> 0 | W7: =IF($U7=0,0,IF(IFERROR(INDEX(VAT_Codes!$F:$F,MATCH($N7,VAT_Codes!$A:$A,0)),"N")="Y",$U7,IF($L7<>"",ROUND(ABS($L7)/IF(OR($R7="",$R7=0),1,$R7),2)*SIGN($U7),ROUND($U7*$V7,2)))) -> 0 | X7: =IF($N7="","",IFERROR(INDEX(VAT_Codes!$H:$H,MATCH($N7,VAT_Codes!$A:$A,0)),"")&"") -> S | Y7: =IF($A7="","",(YEAR($A7)-YEAR(Settings!$C$8))*12+MONTH($A7)-MONTH(Settings!$C$8)+1) -> 1 | Z7: =IF(AND($C7="",$I7="",$J7=""),"",IF($N7="","NO VAT CODE",IF($T7="","UNKNOWN VAT CODE",IF($S7="","MISSING FX RATE",IF(OR($A7<Settings!$C$8,$A7>Settings!$C$9),"OUTSIDE PERIOD",IF(AND(IFERROR(INDEX(VAT_Codes!$E:$E,MATCH($N7,VAT_Codes!$A:$A,0)),"ANY")<>"ANY",$P7=""),"MISSING COUNTERPARTY COUNTRY",IF(AND(IFERROR(INDEX(VAT_Codes!$E:$E,MATCH($N7,VAT_Codes!$A:$A,0)),"ANY")<>"ANY",$P7<>IFERROR(INDEX(VAT_Codes!$E:$E,MATCH($N7,VAT_Codes!$A:$A,0)),"ANY")),"REGION MISMATCH","OK"))))))) -> OK
A8: 46262 | B8: SI-1003 | C8: 4100 | D8: Management fees - group | E8: Q3 management fee | F8: IC-AE01 | G8: Example FZE Dubai (group) | H8: USD | I8: -30000 | K8: OS3 | M8: =IF($C8="","",IFERROR(INDEX(Account_Mapping!$C:$C,MATCH($C8&"",Account_Mapping!$A:$A,0))&"","")) -> EUS | N8: =IF($K8<>"",$K8,$M8) -> OS3 | O8: =IF($F8="","",IFERROR(INDEX(Counterparties!$C:$C,MATCH($F8&"",Counterparties!$A:$A,0))&"","")) -> AE | P8: =IF($O8="","",IF($O8="CY","CY",IF(ISNUMBER(MATCH($O8,Lists!$A:$A,0)),"EU","3RD"))) -> 3RD | Q8: =IF($F8="","N",IFERROR(IF(INDEX(Counterparties!$E:$E,MATCH($F8&"",Counterparties!$A:$A,0))="Y","Y","N"),"N")) -> Y | R8: =IF(OR($H8="",$H8="EUR"),1,IFERROR(INDEX(FX_Rates!$D:$D,MATCH($H8,FX_Rates!$A:$A,0)),"")) -> 1.1649 | S8: =IF(AND($I8="",$J8=""),"",IF($J8<>"",$J8,IF(OR($R8="",$R8=0),"",ROUND($I8/$R8,2)))) -> -25753.28 | T8: =IF($N8="","",IFERROR(INDEX(VAT_Codes!$C:$C,MATCH($N8,VAT_Codes!$A:$A,0)),"")&"") -> Output | U8: =IF(OR($S8="",$T8="",$T8="None"),0,IF($T8="Output",-$S8,$S8)) -> 25753.28 | V8: =IF($N8="",0,IFERROR(INDEX(VAT_Codes!$D:$D,MATCH($N8,VAT_Codes!$A:$A,0)),0)) -> 0 | W8: =IF($U8=0,0,IF(IFERROR(INDEX(VAT_Codes!$F:$F,MATCH($N8,VAT_Codes!$A:$A,0)),"N")="Y",$U8,IF($L8<>"",ROUND(ABS($L8)/IF(OR($R8="",$R8=0),1,$R8),2)*SIGN($U8),ROUND($U8*$V8,2)))) -> 0 | X8: =IF($N8="","",IFERROR(INDEX(VAT_Codes!$H:$H,MATCH($N8,VAT_Codes!$A:$A,0)),"")&"") | Y8: =IF($A8="","",(YEAR($A8)-YEAR(Settings!$C$8))*12+MONTH($A8)-MONTH(Settings!$C$8)+1) -> 2 | Z8: =IF(AND($C8="",$I8="",$J8=""),"",IF($N8="","NO VAT CODE",IF($T8="","UNKNOWN VAT CODE",IF($S8="","MISSING FX RATE",IF(OR($A8<Settings!$C$8,$A8>Settings!$C$9),"OUTSIDE PERIOD",IF(AND(IFERROR(INDEX(VAT_Codes!$E:$E,MATCH($N8,VAT_Codes!$A:$A,0)),"ANY")<>"ANY",$P8=""),"MISSING COUNTERPARTY COUNTRY",IF(AND(IFERROR(INDEX(VAT_Codes!$E:$E,MATCH($N8,VAT_Codes!$A:$A,0)),"ANY")<>"ANY",$P8<>IFERROR(INDEX(VAT_Codes!$E:$E,MATCH($N8,VAT_Codes!$A:$A,0)),"ANY")),"REGION MISMATCH","OK"))))))) -> OK
A9: 46246 | B9: SI-1004 | C9: 4300 | D9: Sales of goods - export / EU | E9: Goods to Italy | F9: C-IT01 | G9: Milano Srl | H9: EUR | I9: -8000 | M9: =IF($C9="","",IFERROR(INDEX(Account_Mapping!$C:$C,MATCH($C9&"",Account_Mapping!$A:$A,0))&"","")) -> EUG | N9: =IF($K9<>"",$K9,$M9) -> EUG | O9: =IF($F9="","",IFERROR(INDEX(Counterparties!$C:$C,MATCH($F9&"",Counterparties!$A:$A,0))&"","")) -> IT | P9: =IF($O9="","",IF($O9="CY","CY",IF(ISNUMBER(MATCH($O9,Lists!$A:$A,0)),"EU","3RD"))) -> EU | Q9: =IF($F9="","N",IFERROR(IF(INDEX(Counterparties!$E:$E,MATCH($F9&"",Counterparties!$A:$A,0))="Y","Y","N"),"N")) -> N | R9: =IF(OR($H9="",$H9="EUR"),1,IFERROR(INDEX(FX_Rates!$D:$D,MATCH($H9,FX_Rates!$A:$A,0)),"")) -> 1 | S9: =IF(AND($I9="",$J9=""),"",IF($J9<>"",$J9,IF(OR($R9="",$R9=0),"",ROUND($I9/$R9,2)))) -> -8000 | T9: =IF($N9="","",IFERROR(INDEX(VAT_Codes!$C:$C,MATCH($N9,VAT_Codes!$A:$A,0)),"")&"") -> Output | U9: =IF(OR($S9="",$T9="",$T9="None"),0,IF($T9="Output",-$S9,$S9)) -> 8000 | V9: =IF($N9="",0,IFERROR(INDEX(VAT_Codes!$D:$D,MATCH($N9,VAT_Codes!$A:$A,0)),0)) -> 0 | W9: =IF($U9=0,0,IF(IFERROR(INDEX(VAT_Codes!$F:$F,MATCH($N9,VAT_Codes!$A:$A,0)),"N")="Y",$U9,IF($L9<>"",ROUND(ABS($L9)/IF(OR($R9="",$R9=0),1,$R9),2)*SIGN($U9),ROUND($U9*$V9,2)))) -> 0 | X9: =IF($N9="","",IFERROR(INDEX(VAT_Codes!$H:$H,MATCH($N9,VAT_Codes!$A:$A,0)),"")&"") -> G | Y9: =IF($A9="","",(YEAR($A9)-YEAR(Settings!$C$8))*12+MONTH($A9)-MONTH(Settings!$C$8)+1) -> 2 | Z9: =IF(AND($C9="",$I9="",$J9=""),"",IF($N9="","NO VAT CODE",IF($T9="","UNKNOWN VAT CODE",IF($S9="","MISSING FX RATE",IF(OR($A9<Settings!$C$8,$A9>Settings!$C$9),"OUTSIDE PERIOD",IF(AND(IFERROR(INDEX(VAT_Codes!$E:$E,MATCH($N9,VAT_Codes!$A:$A,0)),"ANY")<>"ANY",$P9=""),"MISSING COUNTERPARTY COUNTRY",IF(AND(IFERROR(INDEX(VAT_Codes!$E:$E,MATCH($N9,VAT_Codes!$A:$A,0)),"ANY")<>"ANY",$P9<>IFERROR(INDEX(VAT_Codes!$E:$E,MATCH($N9,VAT_Codes!$A:$A,0)),"ANY")),"REGION MISMATCH","OK"))))))) -> OK
A10: 46268 | B10: SI-1005 | C10: 4300 | D10: Sales of goods - export / EU | E10: Goods to USA | F10: C-US01 | G10: Boston Inc | H10: USD | I10: -12000 | K10: EXPG | M10: =IF($C10="","",IFERROR(INDEX(Account_Mapping!$C:$C,MATCH($C10&"",Account_Mapping!$A:$A,0))&"","")) -> EUG | N10: =IF($K10<>"",$K10,$M10) -> EXPG | O10: =IF($F10="","",IFERROR(INDEX(Counterparties!$C:$C,MATCH($F10&"",Counterparties!$A:$A,0))&"","")) -> US | P10: =IF($O10="","",IF($O10="CY","CY",IF(ISNUMBER(MATCH($O10,Lists!$A:$A,0)),"EU","3RD"))) -> 3RD | Q10: =IF($F10="","N",IFERROR(IF(INDEX(Counterparties!$E:$E,MATCH($F10&"",Counterparties!$A:$A,0))="Y","Y","N"),"N")) -> N | R10: =IF(OR($H10="",$H10="EUR"),1,IFERROR(INDEX(FX_Rates!$D:$D,MATCH($H10,FX_Rates!$A:$A,0)),"")) -> 1.1649 | S10: =IF(AND($I10="",$J10=""),"",IF($J10<>"",$J10,IF(OR($R10="",$R10=0),"",ROUND($I10/$R10,2)))) -> -10301.31 | T10: =IF($N10="","",IFERROR(INDEX(VAT_Codes!$C:$C,MATCH($N10,VAT_Codes!$A:$A,0)),"")&"") -> Output | U10: =IF(OR($S10="",$T10="",$T10="None"),0,IF($T10="Output",-$S10,$S10)) -> 10301.31 | V10: =IF($N10="",0,IFERROR(INDEX(VAT_Codes!$D:$D,MATCH($N10,VAT_Codes!$A:$A,0)),0)) -> 0 | W10: =IF($U10=0,0,IF(IFERROR(INDEX(VAT_Codes!$F:$F,MATCH($N10,VAT_Codes!$A:$A,0)),"N")="Y",$U10,IF($L10<>"",ROUND(ABS($L10)/IF(OR($R10="",$R10=0),1,$R10),2)*SIGN($U10),ROUND($U10*$V10,2)))) -> 0 | X10: =IF($N10="","",IFERROR(INDEX(VAT_Codes!$H:$H,MATCH($N10,VAT_Codes!$A:$A,0)),"")&"") | Y10: =IF($A10="","",(YEAR($A10)-YEAR(Settings!$C$8))*12+MONTH($A10)-MONTH(Settings!$C$8)+1) -> 3 | Z10: =IF(AND($C10="",$I10="",$J10=""),"",IF($N10="","NO VAT CODE",IF($T10="","UNKNOWN VAT CODE",IF($S10="","MISSING FX RATE",IF(OR($A10<Settings!$C$8,$A10>Settings!$C$9),"OUTSIDE PERIOD",IF(AND(IFERROR(INDEX(VAT_Codes!$E:$E,MATCH($N10,VAT_Codes!$A:$A,0)),"ANY")<>"ANY",$P10=""),"MISSING COUNTERPARTY COUNTRY",IF(AND(IFERROR(INDEX(VAT_Codes!$E:$E,MATCH($N10,VAT_Codes!$A:$A,0)),"ANY")<>"ANY",$P10<>IFERROR(INDEX(VAT_Codes!$E:$E,MATCH($N10,VAT_Codes!$A:$A,0)),"ANY")),"REGION MISMATCH","OK"))))))) -> OK
A11: 46213 | B11: PI-501 | C11: 6000 | D11: Professional fees | E11: Audit fee | F11: S-CY01 | G11: Nicosia Audit Ltd | H11: EUR | I11: 2000 | M11: =IF($C11="","",IFERROR(INDEX(Account_Mapping!$C:$C,MATCH($C11&"",Account_Mapping!$A:$A,0))&"","")) -> P19 | N11: =IF($K11<>"",$K11,$M11) -> P19 | O11: =IF($F11="","",IFERROR(INDEX(Counterparties!$C:$C,MATCH($F11&"",Counterparties!$A:$A,0))&"","")) -> CY | P11: =IF($O11="","",IF($O11="CY","CY",IF(ISNUMBER(MATCH($O11,Lists!$A:$A,0)),"EU","3RD"))) -> CY | Q11: =IF($F11="","N",IFERROR(IF(INDEX(Counterparties!$E:$E,MATCH($F11&"",Counterparties!$A:$A,0))="Y","Y","N"),"N")) -> N | R11: =IF(OR($H11="",$H11="EUR"),1,IFERROR(INDEX(FX_Rates!$D:$D,MATCH($H11,FX_Rates!$A:$A,0)),"")) -> 1 | S11: =IF(AND($I11="",$J11=""),"",IF($J11<>"",$J11,IF(OR($R11="",$R11=0),"",ROUND($I11/$R11,2)))) -> 2000 | T11: =IF($N11="","",IFERROR(INDEX(VAT_Codes!$C:$C,MATCH($N11,VAT_Codes!$A:$A,0)),"")&"") -> Input | U11: =IF(OR($S11="",$T11="",$T11="None"),0,IF($T11="Output",-$S11,$S11)) -> 2000 | V11: =IF($N11="",0,IFERROR(INDEX(VAT_Codes!$D:$D,MATCH($N11,VAT_Codes!$A:$A,0)),0)) -> 0.19 | W11: =IF($U11=0,0,IF(IFERROR(INDEX(VAT_Codes!$F:$F,MATCH($N11,VAT_Codes!$A:$A,0)),"N")="Y",$U11,IF($L11<>"",ROUND(ABS($L11)/IF(OR($R11="",$R11=0),1,$R11),2)*SIGN($U11),ROUND($U11*$V11,2)))) -> 380 | X11: =IF($N11="","",IFERROR(INDEX(VAT_Codes!$H:$H,MATCH($N11,VAT_Codes!$A:$A,0)),"")&"") | Y11: =IF($A11="","",(YEAR($A11)-YEAR(Settings!$C$8))*12+MONTH($A11)-MONTH(Settings!$C$8)+1) -> 1 | Z11: =IF(AND($C11="",$I11="",$J11=""),"",IF($N11="","NO VAT CODE",IF($T11="","UNKNOWN VAT CODE",IF($S11="","MISSING FX RATE",IF(OR($A11<Settings!$C$8,$A11>Settings!$C$9),"OUTSIDE PERIOD",IF(AND(IFERROR(INDEX(VAT_Codes!$E:$E,MATCH($N11,VAT_Codes!$A:$A,0)),"ANY")<>"ANY",$P11=""),"MISSING COUNTERPARTY COUNTRY",IF(AND(IFERROR(INDEX(VAT_Codes!$E:$E,MATCH($N11,VAT_Codes!$A:$A,0)),"ANY")<>"ANY",$P11<>IFERROR(INDEX(VAT_Codes!$E:$E,MATCH($N11,VAT_Codes!$A:$A,0)),"ANY")),"REGION MISMATCH","OK"))))))) -> OK
A12: 46213 | B12: PI-501 | C12: 2101 | D12: Input VAT | E12: VAT on PI-501 | F12: S-CY01 | G12: Nicosia Audit Ltd | H12: EUR | I12: 380 | M12: =IF($C12="","",IFERROR(INDEX(Account_Mapping!$C:$C,MATCH($C12&"",Account_Mapping!$A:$A,0))&"","")) -> NR | N12: =IF($K12<>"",$K12,$M12) -> NR | O12: =IF($F12="","",IFERROR(INDEX(Counterparties!$C:$C,MATCH($F12&"",Counterparties!$A:$A,0))&"","")) -> CY | P12: =IF($O12="","",IF($O12="CY","CY",IF(ISNUMBER(MATCH($O12,Lists!$A:$A,0)),"EU","3RD"))) -> CY | Q12: =IF($F12="","N",IFERROR(IF(INDEX(Counterparties!$E:$E,MATCH($F12&"",Counterparties!$A:$A,0))="Y","Y","N"),"N")) -> N | R12: =IF(OR($H12="",$H12="EUR"),1,IFERROR(INDEX(FX_Rates!$D:$D,MATCH($H12,FX_Rates!$A:$A,0)),"")) -> 1 | S12: =IF(AND($I12="",$J12=""),"",IF($J12<>"",$J12,IF(OR($R12="",$R12=0),"",ROUND($I12/$R12,2)))) -> 380 | T12: =IF($N12="","",IFERROR(INDEX(VAT_Codes!$C:$C,MATCH($N12,VAT_Codes!$A:$A,0)),"")&"") -> None | U12: =IF(OR($S12="",$T12="",$T12="None"),0,IF($T12="Output",-$S12,$S12)) -> 0 | V12: =IF($N12="",0,IFERROR(INDEX(VAT_Codes!$D:$D,MATCH($N12,VAT_Codes!$A:$A,0)),0)) -> 0 | W12: =IF($U12=0,0,IF(IFERROR(INDEX(VAT_Codes!$F:$F,MATCH($N12,VAT_Codes!$A:$A,0)),"N")="Y",$U12,IF($L12<>"",ROUND(ABS($L12)/IF(OR($R12="",$R12=0),1,$R12),2)*SIGN($U12),ROUND($U12*$V12,2)))) -> 0 | X12: =IF($N12="","",IFERROR(INDEX(VAT_Codes!$H:$H,MATCH($N12,VAT_Codes!$A:$A,0)),"")&"") | Y12: =IF($A12="","",(YEAR($A12)-YEAR(Settings!$C$8))*12+MONTH($A12)-MONTH(Settings!$C$8)+1) -> 1 | Z12: =IF(AND($C12="",$I12="",$J12=""),"",IF($N12="","NO VAT CODE",IF($T12="","UNKNOWN VAT CODE",IF($S12="","MISSING FX RATE",IF(OR($A12<Settings!$C$8,$A12>Settings!$C$9),"OUTSIDE PERIOD",IF(AND(IFERROR(INDEX(VAT_Codes!$E:$E,MATCH($N12,VAT_Codes!$A:$A,0)),"ANY")<>"ANY",$P12=""),"MISSING COUNTERPARTY COUNTRY",IF(AND(IFERROR(INDEX(VAT_Codes!$E:$E,MATCH($N12,VAT_Codes!$A:$A,0)),"ANY")<>"ANY",$P12<>IFERROR(INDEX(VAT_Codes!$E:$E,MATCH($N12,VAT_Codes!$A:$A,0)),"ANY")),"REGION MISMATCH","OK"))))))) -> OK
A13: 46254 | B13: PI-502 | C13: 6100 | D13: Group recharges | E13: IT recharge from parent | F13: IC-NL01 | G13: Example BV (parent) | H13: EUR | I13: 15000 | M13: =IF($C13="","",IFERROR(INDEX(Account_Mapping!$C:$C,MATCH($C13&"",Account_Mapping!$A:$A,0))&"","")) -> AES19 | N13: =IF($K13<>"",$K13,$M13) -> AES19 | O13: =IF($F13="","",IFERROR(INDEX(Counterparties!$C:$C,MATCH($F13&"",Counterparties!$A:$A,0))&"","")) -> NL | P13: =IF($O13="","",IF($O13="CY","CY",IF(ISNUMBER(MATCH($O13,Lists!$A:$A,0)),"EU","3RD"))) -> EU | Q13: =IF($F13="","N",IFERROR(IF(INDEX(Counterparties!$E:$E,MATCH($F13&"",Counterparties!$A:$A,0))="Y","Y","N"),"N")) -> Y | R13: =IF(OR($H13="",$H13="EUR"),1,IFERROR(INDEX(FX_Rates!$D:$D,MATCH($H13,FX_Rates!$A:$A,0)),"")) -> 1 | S13: =IF(AND($I13="",$J13=""),"",IF($J13<>"",$J13,IF(OR($R13="",$R13=0),"",ROUND($I13/$R13,2)))) -> 15000 | T13: =IF($N13="","",IFERROR(INDEX(VAT_Codes!$C:$C,MATCH($N13,VAT_Codes!$A:$A,0)),"")&"") -> Input | U13: =IF(OR($S13="",$T13="",$T13="None"),0,IF($T13="Output",-$S13,$S13)) -> 15000 | V13: =IF($N13="",0,IFERROR(INDEX(VAT_Codes!$D:$D,MATCH($N13,VAT_Codes!$A:$A,0)),0)) -> 0.19 | W13: =IF($U13=0,0,IF(IFERROR(INDEX(VAT_Codes!$F:$F,MATCH($N13,VAT_Codes!$A:$A,0)),"N")="Y",$U13,IF($L13<>"",ROUND(ABS($L13)/IF(OR($R13="",$R13=0),1,$R13),2)*SIGN($U13),ROUND($U13*$V13,2)))) -> 2850 | X13: =IF($N13="","",IFERROR(INDEX(VAT_Codes!$H:$H,MATCH($N13,VAT_Codes!$A:$A,0)),"")&"") | Y13: =IF($A13="","",(YEAR($A13)-YEAR(Settings!$C$8))*12+MONTH($A13)-MONTH(Settings!$C$8)+1) -> 2 | Z13: =IF(AND($C13="",$I13="",$J13=""),"",IF($N13="","NO VAT CODE",IF($T13="","UNKNOWN VAT CODE",IF($S13="","MISSING FX RATE",IF(OR($A13<Settings!$C$8,$A13>Settings!$C$9),"OUTSIDE PERIOD",IF(AND(IFERROR(INDEX(VAT_Codes!$E:$E,MATCH($N13,VAT_Codes!$A:$A,0)),"ANY")<>"ANY",$P13=""),"MISSING COUNTERPARTY COUNTRY",IF(AND(IFERROR(INDEX(VAT_Codes!$E:$E,MATCH($N13,VAT_Codes!$A:$A,0)),"ANY")<>"ANY",$P13<>IFERROR(INDEX(VAT_Codes!$E:$E,MATCH($N13,VAT_Codes!$A:$A,0)),"ANY")),"REGION MISMATCH","OK"))))))) -> OK
A14: 46236 | B14: PI-503 | C14: 6000 | D14: Professional fees | E14: Software subscription | F14: S-US01 | G14: Cloudsoft Inc | H14: USD | I14: 1200 | K14: A3S19 | M14: =IF($C14="","",IFERROR(INDEX(Account_Mapping!$C:$C,MATCH($C14&"",Account_Mapping!$A:$A,0))&"","")) -> P19 | N14: =IF($K14<>"",$K14,$M14) -> A3S19 | O14: =IF($F14="","",IFERROR(INDEX(Counterparties!$C:$C,MATCH($F14&"",Counterparties!$A:$A,0))&"","")) -> US | P14: =IF($O14="","",IF($O14="CY","CY",IF(ISNUMBER(MATCH($O14,Lists!$A:$A,0)),"EU","3RD"))) -> 3RD | Q14: =IF($F14="","N",IFERROR(IF(INDEX(Counterparties!$E:$E,MATCH($F14&"",Counterparties!$A:$A,0))="Y","Y","N"),"N")) -> N | R14: =IF(OR($H14="",$H14="EUR"),1,IFERROR(INDEX(FX_Rates!$D:$D,MATCH($H14,FX_Rates!$A:$A,0)),"")) -> 1.1649 | S14: =IF(AND($I14="",$J14=""),"",IF($J14<>"",$J14,IF(OR($R14="",$R14=0),"",ROUND($I14/$R14,2)))) -> 1030.13 | T14: =IF($N14="","",IFERROR(INDEX(VAT_Codes!$C:$C,MATCH($N14,VAT_Codes!$A:$A,0)),"")&"") -> Input | U14: =IF(OR($S14="",$T14="",$T14="None"),0,IF($T14="Output",-$S14,$S14)) -> 1030.13 | V14: =IF($N14="",0,IFERROR(INDEX(VAT_Codes!$D:$D,MATCH($N14,VAT_Codes!$A:$A,0)),0)) -> 0.19 | W14: =IF($U14=0,0,IF(IFERROR(INDEX(VAT_Codes!$F:$F,MATCH($N14,VAT_Codes!$A:$A,0)),"N")="Y",$U14,IF($L14<>"",ROUND(ABS($L14)/IF(OR($R14="",$R14=0),1,$R14),2)*SIGN($U14),ROUND($U14*$V14,2)))) -> 195.72 | X14: =IF($N14="","",IFERROR(INDEX(VAT_Codes!$H:$H,MATCH($N14,VAT_Codes!$A:$A,0)),"")&"") | Y14: =IF($A14="","",(YEAR($A14)-YEAR(Settings!$C$8))*12+MONTH($A14)-MONTH(Settings!$C$8)+1) -> 2 | Z14: =IF(AND($C14="",$I14="",$J14=""),"",IF($N14="","NO VAT CODE",IF($T14="","UNKNOWN VAT CODE",IF($S14="","MISSING FX RATE",IF(OR($A14<Settings!$C$8,$A14>Settings!$C$9),"OUTSIDE PERIOD",IF(AND(IFERROR(INDEX(VAT_Codes!$E:$E,MATCH($N14,VAT_Codes!$A:$A,0)),"ANY")<>"ANY",$P14=""),"MISSING COUNTERPARTY COUNTRY",IF(AND(IFERROR(INDEX(VAT_Codes!$E:$E,MATCH($N14,VAT_Codes!$A:$A,0)),"ANY")<>"ANY",$P14<>IFERROR(INDEX(VAT_Codes!$E:$E,MATCH($N14,VAT_Codes!$A:$A,0)),"ANY")),"REGION MISMATCH","OK"))))))) -> OK
A15: 46273 | B15: PI-504 | C15: 5000 | D15: Purchases of goods | E15: Goods from Germany | F15: S-DE01 | G15: Hamburg Supplies GmbH | H15: EUR | I15: 5000 | M15: =IF($C15="","",IFERROR(INDEX(Account_Mapping!$C:$C,MATCH($C15&"",Account_Mapping!$A:$A,0))&"","")) -> AEG19 | N15: =IF($K15<>"",$K15,$M15) -> AEG19 | O15: =IF($F15="","",IFERROR(INDEX(Counterparties!$C:$C,MATCH($F15&"",Counterparties!$A:$A,0))&"","")) -> DE | P15: =IF($O15="","",IF($O15="CY","CY",IF(ISNUMBER(MATCH($O15,Lists!$A:$A,0)),"EU","3RD"))) -> EU | Q15: =IF($F15="","N",IFERROR(IF(INDEX(Counterparties!$E:$E,MATCH($F15&"",Counterparties!$A:$A,0))="Y","Y","N"),"N")) -> N | R15: =IF(OR($H15="",$H15="EUR"),1,IFERROR(INDEX(FX_Rates!$D:$D,MATCH($H15,FX_Rates!$A:$A,0)),"")) -> 1 | S15: =IF(AND($I15="",$J15=""),"",IF($J15<>"",$J15,IF(OR($R15="",$R15=0),"",ROUND($I15/$R15,2)))) -> 5000 | T15: =IF($N15="","",IFERROR(INDEX(VAT_Codes!$C:$C,MATCH($N15,VAT_Codes!$A:$A,0)),"")&"") -> Input | U15: =IF(OR($S15="",$T15="",$T15="None"),0,IF($T15="Output",-$S15,$S15)) -> 5000 | V15: =IF($N15="",0,IFERROR(INDEX(VAT_Codes!$D:$D,MATCH($N15,VAT_Codes!$A:$A,0)),0)) -> 0.19 | W15: =IF($U15=0,0,IF(IFERROR(INDEX(VAT_Codes!$F:$F,MATCH($N15,VAT_Codes!$A:$A,0)),"N")="Y",$U15,IF($L15<>"",ROUND(ABS($L15)/IF(OR($R15="",$R15=0),1,$R15),2)*SIGN($U15),ROUND($U15*$V15,2)))) -> 950 | X15: =IF($N15="","",IFERROR(INDEX(VAT_Codes!$H:$H,MATCH($N15,VAT_Codes!$A:$A,0)),"")&"") | Y15: =IF($A15="","",(YEAR($A15)-YEAR(Settings!$C$8))*12+MONTH($A15)-MONTH(Settings!$C$8)+1) -> 3 | Z15: =IF(AND($C15="",$I15="",$J15=""),"",IF($N15="","NO VAT CODE",IF($T15="","UNKNOWN VAT CODE",IF($S15="","MISSING FX RATE",IF(OR($A15<Settings!$C$8,$A15>Settings!$C$9),"OUTSIDE PERIOD",IF(AND(IFERROR(INDEX(VAT_Codes!$E:$E,MATCH($N15,VAT_Codes!$A:$A,0)),"ANY")<>"ANY",$P15=""),"MISSING COUNTERPARTY COUNTRY",IF(AND(IFERROR(INDEX(VAT_Codes!$E:$E,MATCH($N15,VAT_Codes!$A:$A,0)),"ANY")<>"ANY",$P15<>IFERROR(INDEX(VAT_Codes!$E:$E,MATCH($N15,VAT_Codes!$A:$A,0)),"ANY")),"REGION MISMATCH","OK"))))))) -> OK
A16: 46280 | B16: PI-505 | C16: 5010 | D16: Imports of goods | E16: Goods from China | F16: S-CN01 | G16: Shenzhen Mfg Co | H16: USD | I16: 4000 | M16: =IF($C16="","",IFERROR(INDEX(Account_Mapping!$C:$C,MATCH($C16&"",Account_Mapping!$A:$A,0))&"","")) -> IMP | N16: =IF($K16<>"",$K16,$M16) -> IMP | O16: =IF($F16="","",IFERROR(INDEX(Counterparties!$C:$C,MATCH($F16&"",Counterparties!$A:$A,0))&"","")) -> CN | P16: =IF($O16="","",IF($O16="CY","CY",IF(ISNUMBER(MATCH($O16,Lists!$A:$A,0)),"EU","3RD"))) -> 3RD | Q16: =IF($F16="","N",IFERROR(IF(INDEX(Counterparties!$E:$E,MATCH($F16&"",Counterparties!$A:$A,0))="Y","Y","N"),"N")) -> N | R16: =IF(OR($H16="",$H16="EUR"),1,IFERROR(INDEX(FX_Rates!$D:$D,MATCH($H16,FX_Rates!$A:$A,0)),"")) -> 1.1649 | S16: =IF(AND($I16="",$J16=""),"",IF($J16<>"",$J16,IF(OR($R16="",$R16=0),"",ROUND($I16/$R16,2)))) -> 3433.77 | T16: =IF($N16="","",IFERROR(INDEX(VAT_Codes!$C:$C,MATCH($N16,VAT_Codes!$A:$A,0)),"")&"") -> Input | U16: =IF(OR($S16="",$T16="",$T16="None"),0,IF($T16="Output",-$S16,$S16)) -> 3433.77 | V16: =IF($N16="",0,IFERROR(INDEX(VAT_Codes!$D:$D,MATCH($N16,VAT_Codes!$A:$A,0)),0)) -> 0 | W16: =IF($U16=0,0,IF(IFERROR(INDEX(VAT_Codes!$F:$F,MATCH($N16,VAT_Codes!$A:$A,0)),"N")="Y",$U16,IF($L16<>"",ROUND(ABS($L16)/IF(OR($R16="",$R16=0),1,$R16),2)*SIGN($U16),ROUND($U16*$V16,2)))) -> 0 | X16: =IF($N16="","",IFERROR(INDEX(VAT_Codes!$H:$H,MATCH($N16,VAT_Codes!$A:$A,0)),"")&"") | Y16: =IF($A16="","",(YEAR($A16)-YEAR(Settings!$C$8))*12+MONTH($A16)-MONTH(Settings!$C$8)+1) -> 3 | Z16: =IF(AND($C16="",$I16="",$J16=""),"",IF($N16="","NO VAT CODE",IF($T16="","UNKNOWN VAT CODE",IF($S16="","MISSING FX RATE",IF(OR($A16<Settings!$C$8,$A16>Settings!$C$9),"OUTSIDE PERIOD",IF(AND(IFERROR(INDEX(VAT_Codes!$E:$E,MATCH($N16,VAT_Codes!$A:$A,0)),"ANY")<>"ANY",$P16=""),"MISSING COUNTERPARTY COUNTRY",IF(AND(IFERROR(INDEX(VAT_Codes!$E:$E,MATCH($N16,VAT_Codes!$A:$A,0)),"ANY")<>"ANY",$P16<>IFERROR(INDEX(VAT_Codes!$E:$E,MATCH($N16,VAT_Codes!$A:$A,0)),"ANY")),"REGION MISMATCH","OK"))))))) -> OK
A17: 46280 | B17: C-77 | C17: 2105 | D17: Import VAT paid to Customs | E17: Import VAT SAD 26CY... | H17: EUR | I17: 700 | M17: =IF($C17="","",IFERROR(INDEX(Account_Mapping!$C:$C,MATCH($C17&"",Account_Mapping!$A:$A,0))&"","")) -> IVAT | N17: =IF($K17<>"",$K17,$M17) -> IVAT | O17: =IF($F17="","",IFERROR(INDEX(Counterparties!$C:$C,MATCH($F17&"",Counterparties!$A:$A,0))&"","")) | P17: =IF($O17="","",IF($O17="CY","CY",IF(ISNUMBER(MATCH($O17,Lists!$A:$A,0)),"EU","3RD"))) | Q17: =IF($F17="","N",IFERROR(IF(INDEX(Counterparties!$E:$E,MATCH($F17&"",Counterparties!$A:$A,0))="Y","Y","N"),"N")) -> N | R17: =IF(OR($H17="",$H17="EUR"),1,IFERROR(INDEX(FX_Rates!$D:$D,MATCH($H17,FX_Rates!$A:$A,0)),"")) -> 1 | S17: =IF(AND($I17="",$J17=""),"",IF($J17<>"",$J17,IF(OR($R17="",$R17=0),"",ROUND($I17/$R17,2)))) -> 700 | T17: =IF($N17="","",IFERROR(INDEX(VAT_Codes!$C:$C,MATCH($N17,VAT_Codes!$A:$A,0)),"")&"") -> Input | U17: =IF(OR($S17="",$T17="",$T17="None"),0,IF($T17="Output",-$S17,$S17)) -> 700 | V17: =IF($N17="",0,IFERROR(INDEX(VAT_Codes!$D:$D,MATCH($N17,VAT_Codes!$A:$A,0)),0)) -> 0 | W17: =IF($U17=0,0,IF(IFERROR(INDEX(VAT_Codes!$F:$F,MATCH($N17,VAT_Codes!$A:$A,0)),"N")="Y",$U17,IF($L17<>"",ROUND(ABS($L17)/IF(OR($R17="",$R17=0),1,$R17),2)*SIGN($U17),ROUND($U17*$V17,2)))) -> 700 | X17: =IF($N17="","",IFERROR(INDEX(VAT_Codes!$H:$H,MATCH($N17,VAT_Codes!$A:$A,0)),"")&"") | Y17: =IF($A17="","",(YEAR($A17)-YEAR(Settings!$C$8))*12+MONTH($A17)-MONTH(Settings!$C$8)+1) -> 3 | Z17: =IF(AND($C17="",$I17="",$J17=""),"",IF($N17="","NO VAT CODE",IF($T17="","UNKNOWN VAT CODE",IF($S17="","MISSING FX RATE",IF(OR($A17<Settings!$C$8,$A17>Settings!$C$9),"OUTSIDE PERIOD",IF(AND(IFERROR(INDEX(VAT_Codes!$E:$E,MATCH($N17,VAT_Codes!$A:$A,0)),"ANY")<>"ANY",$P17=""),"MISSING COUNTERPARTY COUNTRY",IF(AND(IFERROR(INDEX(VAT_Codes!$E:$E,MATCH($N17,VAT_Codes!$A:$A,0)),"ANY")<>"ANY",$P17<>IFERROR(INDEX(VAT_Codes!$E:$E,MATCH($N17,VAT_Codes!$A:$A,0)),"ANY")),"REGION MISMATCH","OK"))))))) -> OK
A18: 46259 | B18: PI-506 | C18: 6500 | D18: Entertainment | E18: Client dinner | F18: S-CY02 | G18: Paphos Restaurant Ltd | H18: EUR | I18: 300 | L18: 57 | M18: =IF($C18="","",IFERROR(INDEX(Account_Mapping!$C:$C,MATCH($C18&"",Account_Mapping!$A:$A,0))&"","")) -> PB19 | N18: =IF($K18<>"",$K18,$M18) -> PB19 | O18: =IF($F18="","",IFERROR(INDEX(Counterparties!$C:$C,MATCH($F18&"",Counterparties!$A:$A,0))&"","")) -> CY | P18: =IF($O18="","",IF($O18="CY","CY",IF(ISNUMBER(MATCH($O18,Lists!$A:$A,0)),"EU","3RD"))) -> CY | Q18: =IF($F18="","N",IFERROR(IF(INDEX(Counterparties!$E:$E,MATCH($F18&"",Counterparties!$A:$A,0))="Y","Y","N"),"N")) -> N | R18: =IF(OR($H18="",$H18="EUR"),1,IFERROR(INDEX(FX_Rates!$D:$D,MATCH($H18,FX_Rates!$A:$A,0)),"")) -> 1 | S18: =IF(AND($I18="",$J18=""),"",IF($J18<>"",$J18,IF(OR($R18="",$R18=0),"",ROUND($I18/$R18,2)))) -> 300 | T18: =IF($N18="","",IFERROR(INDEX(VAT_Codes!$C:$C,MATCH($N18,VAT_Codes!$A:$A,0)),"")&"") -> Input | U18: =IF(OR($S18="",$T18="",$T18="None"),0,IF($T18="Output",-$S18,$S18)) -> 300 | V18: =IF($N18="",0,IFERROR(INDEX(VAT_Codes!$D:$D,MATCH($N18,VAT_Codes!$A:$A,0)),0)) -> 0.19 | W18: =IF($U18=0,0,IF(IFERROR(INDEX(VAT_Codes!$F:$F,MATCH($N18,VAT_Codes!$A:$A,0)),"N")="Y",$U18,IF($L18<>"",ROUND(ABS($L18)/IF(OR($R18="",$R18=0),1,$R18),2)*SIGN($U18),ROUND($U18*$V18,2)))) -> 57 | X18: =IF($N18="","",IFERROR(INDEX(VAT_Codes!$H:$H,MATCH($N18,VAT_Codes!$A:$A,0)),"")&"") | Y18: =IF($A18="","",(YEAR($A18)-YEAR(Settings!$C$8))*12+MONTH($A18)-MONTH(Settings!$C$8)+1) -> 2 | Z18: =IF(AND($C18="",$I18="",$J18=""),"",IF($N18="","NO VAT CODE",IF($T18="","UNKNOWN VAT CODE",IF($S18="","MISSING FX RATE",IF(OR($A18<Settings!$C$8,$A18>Settings!$C$9),"OUTSIDE PERIOD",IF(AND(IFERROR(INDEX(VAT_Codes!$E:$E,MATCH($N18,VAT_Codes!$A:$A,0)),"ANY")<>"ANY",$P18=""),"MISSING COUNTERPARTY COUNTRY",IF(AND(IFERROR(INDEX(VAT_Codes!$E:$E,MATCH($N18,VAT_Codes!$A:$A,0)),"ANY")<>"ANY",$P18<>IFERROR(INDEX(VAT_Codes!$E:$E,MATCH($N18,VAT_Codes!$A:$A,0)),"ANY")),"REGION MISMATCH","OK"))))))) -> OK
A19: 46231 | B19: PAY-07 | C19: 7000 | D19: Salaries | E19: July payroll | H19: EUR | I19: 20000 | M19: =IF($C19="","",IFERROR(INDEX(Account_Mapping!$C:$C,MATCH($C19&"",Account_Mapping!$A:$A,0))&"","")) -> NR | N19: =IF($K19<>"",$K19,$M19) -> NR | O19: =IF($F19="","",IFERROR(INDEX(Counterparties!$C:$C,MATCH($F19&"",Counterparties!$A:$A,0))&"","")) | P19: =IF($O19="","",IF($O19="CY","CY",IF(ISNUMBER(MATCH($O19,Lists!$A:$A,0)),"EU","3RD"))) | Q19: =IF($F19="","N",IFERROR(IF(INDEX(Counterparties!$E:$E,MATCH($F19&"",Counterparties!$A:$A,0))="Y","Y","N"),"N")) -> N | R19: =IF(OR($H19="",$H19="EUR"),1,IFERROR(INDEX(FX_Rates!$D:$D,MATCH($H19,FX_Rates!$A:$A,0)),"")) -> 1 | S19: =IF(AND($I19="",$J19=""),"",IF($J19<>"",$J19,IF(OR($R19="",$R19=0),"",ROUND($I19/$R19,2)))) -> 20000 | T19: =IF($N19="","",IFERROR(INDEX(VAT_Codes!$C:$C,MATCH($N19,VAT_Codes!$A:$A,0)),"")&"") -> None | U19: =IF(OR($S19="",$T19="",$T19="None"),0,IF($T19="Output",-$S19,$S19)) -> 0 | V19: =IF($N19="",0,IFERROR(INDEX(VAT_Codes!$D:$D,MATCH($N19,VAT_Codes!$A:$A,0)),0)) -> 0 | W19: =IF($U19=0,0,IF(IFERROR(INDEX(VAT_Codes!$F:$F,MATCH($N19,VAT_Codes!$A:$A,0)),"N")="Y",$U19,IF($L19<>"",ROUND(ABS($L19)/IF(OR($R19="",$R19=0),1,$R19),2)*SIGN($U19),ROUND($U19*$V19,2)))) -> 0 | X19: =IF($N19="","",IFERROR(INDEX(VAT_Codes!$H:$H,MATCH($N19,VAT_Codes!$A:$A,0)),"")&"") | Y19: =IF($A19="","",(YEAR($A19)-YEAR(Settings!$C$8))*12+MONTH($A19)-MONTH(Settings!$C$8)+1) -> 1 | Z19: =IF(AND($C19="",$I19="",$J19=""),"",IF($N19="","NO VAT CODE",IF($T19="","UNKNOWN VAT CODE",IF($S19="","MISSING FX RATE",IF(OR($A19<Settings!$C$8,$A19>Settings!$C$9),"OUTSIDE PERIOD",IF(AND(IFERROR(INDEX(VAT_Codes!$E:$E,MATCH($N19,VAT_Codes!$A:$A,0)),"ANY")<>"ANY",$P19=""),"MISSING COUNTERPARTY COUNTRY",IF(AND(IFERROR(INDEX(VAT_Codes!$E:$E,MATCH($N19,VAT_Codes!$A:$A,0)),"ANY")<>"ANY",$P19<>IFERROR(INDEX(VAT_Codes!$E:$E,MATCH($N19,VAT_Codes!$A:$A,0)),"ANY")),"REGION MISMATCH","OK"))))))) -> OK
A20: 46231 | B20: PAY-07 | C20: 1200 | D20: Bank - EUR | E20: July payroll | H20: EUR | I20: -20000 | M20: =IF($C20="","",IFERROR(INDEX(Account_Mapping!$C:$C,MATCH($C20&"",Account_Mapping!$A:$A,0))&"","")) -> NR | N20: =IF($K20<>"",$K20,$M20) -> NR | O20: =IF($F20="","",IFERROR(INDEX(Counterparties!$C:$C,MATCH($F20&"",Counterparties!$A:$A,0))&"","")) | P20: =IF($O20="","",IF($O20="CY","CY",IF(ISNUMBER(MATCH($O20,Lists!$A:$A,0)),"EU","3RD"))) | Q20: =IF($F20="","N",IFERROR(IF(INDEX(Counterparties!$E:$E,MATCH($F20&"",Counterparties!$A:$A,0))="Y","Y","N"),"N")) -> N | R20: =IF(OR($H20="",$H20="EUR"),1,IFERROR(INDEX(FX_Rates!$D:$D,MATCH($H20,FX_Rates!$A:$A,0)),"")) -> 1 | S20: =IF(AND($I20="",$J20=""),"",IF($J20<>"",$J20,IF(OR($R20="",$R20=0),"",ROUND($I20/$R20,2)))) -> -20000 | T20: =IF($N20="","",IFERROR(INDEX(VAT_Codes!$C:$C,MATCH($N20,VAT_Codes!$A:$A,0)),"")&"") -> None | U20: =IF(OR($S20="",$T20="",$T20="None"),0,IF($T20="Output",-$S20,$S20)) -> 0 | V20: =IF($N20="",0,IFERROR(INDEX(VAT_Codes!$D:$D,MATCH($N20,VAT_Codes!$A:$A,0)),0)) -> 0 | W20: =IF($U20=0,0,IF(IFERROR(INDEX(VAT_Codes!$F:$F,MATCH($N20,VAT_Codes!$A:$A,0)),"N")="Y",$U20,IF($L20<>"",ROUND(ABS($L20)/IF(OR($R20="",$R20=0),1,$R20),2)*SIGN($U20),ROUND($U20*$V20,2)))) -> 0 | X20: =IF($N20="","",IFERROR(INDEX(VAT_Codes!$H:$H,MATCH($N20,VAT_Codes!$A:$A,0)),"")&"") | Y20: =IF($A20="","",(YEAR($A20)-YEAR(Settings!$C$8))*12+MONTH($A20)-MONTH(Settings!$C$8)+1) -> 1 | Z20: =IF(AND($C20="",$I20="",$J20=""),"",IF($N20="","NO VAT CODE",IF($T20="","UNKNOWN VAT CODE",IF($S20="","MISSING FX RATE",IF(OR($A20<Settings!$C$8,$A20>Settings!$C$9),"OUTSIDE PERIOD",IF(AND(IFERROR(INDEX(VAT_Codes!$E:$E,MATCH($N20,VAT_Codes!$A:$A,0)),"ANY")<>"ANY",$P20=""),"MISSING COUNTERPARTY COUNTRY",IF(AND(IFERROR(INDEX(VAT_Codes!$E:$E,MATCH($N20,VAT_Codes!$A:$A,0)),"ANY")<>"ANY",$P20<>IFERROR(INDEX(VAT_Codes!$E:$E,MATCH($N20,VAT_Codes!$A:$A,0)),"ANY")),"REGION MISMATCH","OK"))))))) -> OK
M21: =IF($C21="","",IFERROR(INDEX(Account_Mapping!$C:$C,MATCH($C21&"",Account_Mapping!$A:$A,0))&"","")) | N21: =IF($K21<>"",$K21,$M21) | O21: =IF($F21="","",IFERROR(INDEX(Counterparties!$C:$C,MATCH($F21&"",Counterparties!$A:$A,0))&"","")) | P21: =IF($O21="","",IF($O21="CY","CY",IF(ISNUMBER(MATCH($O21,Lists!$A:$A,0)),"EU","3RD"))) | Q21: =IF($F21="","N",IFERROR(IF(INDEX(Counterparties!$E:$E,MATCH($F21&"",Counterparties!$A:$A,0))="Y","Y","N"),"N")) -> N | R21: =IF(OR($H21="",$H21="EUR"),1,IFERROR(INDEX(FX_Rates!$D:$D,MATCH($H21,FX_Rates!$A:$A,0)),"")) -> 1 | S21: =IF(AND($I21="",$J21=""),"",IF($J21<>"",$J21,IF(OR($R21="",$R21=0),"",ROUND($I21/$R21,2)))) | T21: =IF($N21="","",IFERROR(INDEX(VAT_Codes!$C:$C,MATCH($N21,VAT_Codes!$A:$A,0)),"")&"") | U21: =IF(OR($S21="",$T21="",$T21="None"),0,IF($T21="Output",-$S21,$S21)) -> 0 | V21: =IF($N21="",0,IFERROR(INDEX(VAT_Codes!$D:$D,MATCH($N21,VAT_Codes!$A:$A,0)),0)) -> 0 | W21: =IF($U21=0,0,IF(IFERROR(INDEX(VAT_Codes!$F:$F,MATCH($N21,VAT_Codes!$A:$A,0)),"N")="Y",$U21,IF($L21<>"",ROUND(ABS($L21)/IF(OR($R21="",$R21=0),1,$R21),2)*SIGN($U21),ROUND($U21*$V21,2)))) -> 0 | X21: =IF($N21="","",IFERROR(INDEX(VAT_Codes!$H:$H,MATCH($N21,VAT_Codes!$A:$A,0)),"")&"") | Y21: =IF($A21="","",(YEAR($A21)-YEAR(Settings!$C$8))*12+MONTH($A21)-MONTH(Settings!$C$8)+1) | Z21: =IF(AND($C21="",$I21="",$J21=""),"",IF($N21="","NO VAT CODE",IF($T21="","UNKNOWN VAT CODE",IF($S21="","MISSING FX RATE",IF(OR($A21<Settings!$C$8,$A21>Settings!$C$9),"OUTSIDE PERIOD",IF(AND(IFERROR(INDEX(VAT_Codes!$E:$E,MATCH($N21,VAT_Codes!$A:$A,0)),"ANY")<>"ANY",$P21=""),"MISSING COUNTERPARTY COUNTRY",IF(AND(IFERROR(INDEX(VAT_Codes!$E:$E,MATCH($N21,VAT_Codes!$A:$A,0)),"ANY")<>"ANY",$P21<>IFERROR(INDEX(VAT_Codes!$E:$E,MATCH($N21,VAT_Codes!$A:$A,0)),"ANY")),"REGION MISMATCH","OK")))))))
M22: =IF($C22="","",IFERROR(INDEX(Account_Mapping!$C:$C,MATCH($C22&"",Account_Mapping!$A:$A,0))&"","")) | N22: =IF($K22<>"",$K22,$M22) | O22: =IF($F22="","",IFERROR(INDEX(Counterparties!$C:$C,MATCH($F22&"",Counterparties!$A:$A,0))&"","")) | P22: =IF($O22="","",IF($O22="CY","CY",IF(ISNUMBER(MATCH($O22,Lists!$A:$A,0)),"EU","3RD"))) | Q22: =IF($F22="","N",IFERROR(IF(INDEX(Counterparties!$E:$E,MATCH($F22&"",Counterparties!$A:$A,0))="Y","Y","N"),"N")) -> N | R22: =IF(OR($H22="",$H22="EUR"),1,IFERROR(INDEX(FX_Rates!$D:$D,MATCH($H22,FX_Rates!$A:$A,0)),"")) -> 1 | S22: =IF(AND($I22="",$J22=""),"",IF($J22<>"",$J22,IF(OR($R22="",$R22=0),"",ROUND($I22/$R22,2)))) | T22: =IF($N22="","",IFERROR(INDEX(VAT_Codes!$C:$C,MATCH($N22,VAT_Codes!$A:$A,0)),"")&"") | U22: =IF(OR($S22="",$T22="",$T22="None"),0,IF($T22="Output",-$S22,$S22)) -> 0 | V22: =IF($N22="",0,IFERROR(INDEX(VAT_Codes!$D:$D,MATCH($N22,VAT_Codes!$A:$A,0)),0)) -> 0 | W22: =IF($U22=0,0,IF(IFERROR(INDEX(VAT_Codes!$F:$F,MATCH($N22,VAT_Codes!$A:$A,0)),"N")="Y",$U22,IF($L22<>"",ROUND(ABS($L22)/IF(OR($R22="",$R22=0),1,$R22),2)*SIGN($U22),ROUND($U22*$V22,2)))) -> 0 | X22: =IF($N22="","",IFERROR(INDEX(VAT_Codes!$H:$H,MATCH($N22,VAT_Codes!$A:$A,0)),"")&"") | Y22: =IF($A22="","",(YEAR($A22)-YEAR(Settings!$C$8))*12+MONTH($A22)-MONTH(Settings!$C$8)+1) | Z22: =IF(AND($C22="",$I22="",$J22=""),"",IF($N22="","NO VAT CODE",IF($T22="","UNKNOWN VAT CODE",IF($S22="","MISSING FX RATE",IF(OR($A22<Settings!$C$8,$A22>Settings!$C$9),"OUTSIDE PERIOD",IF(AND(IFERROR(INDEX(VAT_Codes!$E:$E,MATCH($N22,VAT_Codes!$A:$A,0)),"ANY")<>"ANY",$P22=""),"MISSING COUNTERPARTY COUNTRY",IF(AND(IFERROR(INDEX(VAT_Codes!$E:$E,MATCH($N22,VAT_Codes!$A:$A,0)),"ANY")<>"ANY",$P22<>IFERROR(INDEX(VAT_Codes!$E:$E,MATCH($N22,VAT_Codes!$A:$A,0)),"ANY")),"REGION MISMATCH","OK")))))))
M23: =IF($C23="","",IFERROR(INDEX(Account_Mapping!$C:$C,MATCH($C23&"",Account_Mapping!$A:$A,0))&"","")) | N23: =IF($K23<>"",$K23,$M23) | O23: =IF($F23="","",IFERROR(INDEX(Counterparties!$C:$C,MATCH($F23&"",Counterparties!$A:$A,0))&"","")) | P23: =IF($O23="","",IF($O23="CY","CY",IF(ISNUMBER(MATCH($O23,Lists!$A:$A,0)),"EU","3RD"))) | Q23: =IF($F23="","N",IFERROR(IF(INDEX(Counterparties!$E:$E,MATCH($F23&"",Counterparties!$A:$A,0))="Y","Y","N"),"N")) -> N | R23: =IF(OR($H23="",$H23="EUR"),1,IFERROR(INDEX(FX_Rates!$D:$D,MATCH($H23,FX_Rates!$A:$A,0)),"")) -> 1 | S23: =IF(AND($I23="",$J23=""),"",IF($J23<>"",$J23,IF(OR($R23="",$R23=0),"",ROUND($I23/$R23,2)))) | T23: =IF($N23="","",IFERROR(INDEX(VAT_Codes!$C:$C,MATCH($N23,VAT_Codes!$A:$A,0)),"")&"") | U23: =IF(OR($S23="",$T23="",$T23="None"),0,IF($T23="Output",-$S23,$S23)) -> 0 | V23: =IF($N23="",0,IFERROR(INDEX(VAT_Codes!$D:$D,MATCH($N23,VAT_Codes!$A:$A,0)),0)) -> 0 | W23: =IF($U23=0,0,IF(IFERROR(INDEX(VAT_Codes!$F:$F,MATCH($N23,VAT_Codes!$A:$A,0)),"N")="Y",$U23,IF($L23<>"",ROUND(ABS($L23)/IF(OR($R23="",$R23=0),1,$R23),2)*SIGN($U23),ROUND($U23*$V23,2)))) -> 0 | X23: =IF($N23="","",IFERROR(INDEX(VAT_Codes!$H:$H,MATCH($N23,VAT_Codes!$A:$A,0)),"")&"") | Y23: =IF($A23="","",(YEAR($A23)-YEAR(Settings!$C$8))*12+MONTH($A23)-MONTH(Settings!$C$8)+1) | Z23: =IF(AND($C23="",$I23="",$J23=""),"",IF($N23="","NO VAT CODE",IF($T23="","UNKNOWN VAT CODE",IF($S23="","MISSING FX RATE",IF(OR($A23<Settings!$C$8,$A23>Settings!$C$9),"OUTSIDE PERIOD",IF(AND(IFERROR(INDEX(VAT_Codes!$E:$E,MATCH($N23,VAT_Codes!$A:$A,0)),"ANY")<>"ANY",$P23=""),"MISSING COUNTERPARTY COUNTRY",IF(AND(IFERROR(INDEX(VAT_Codes!$E:$E,MATCH($N23,VAT_Codes!$A:$A,0)),"ANY")<>"ANY",$P23<>IFERROR(INDEX(VAT_Codes!$E:$E,MATCH($N23,VAT_Codes!$A:$A,0)),"ANY")),"REGION MISMATCH","OK")))))))
M24: =IF($C24="","",IFERROR(INDEX(Account_Mapping!$C:$C,MATCH($C24&"",Account_Mapping!$A:$A,0))&"","")) | N24: =IF($K24<>"",$K24,$M24) | O24: =IF($F24="","",IFERROR(INDEX(Counterparties!$C:$C,MATCH($F24&"",Counterparties!$A:$A,0))&"","")) | P24: =IF($O24="","",IF($O24="CY","CY",IF(ISNUMBER(MATCH($O24,Lists!$A:$A,0)),"EU","3RD"))) | Q24: =IF($F24="","N",IFERROR(IF(INDEX(Counterparties!$E:$E,MATCH($F24&"",Counterparties!$A:$A,0))="Y","Y","N"),"N")) -> N | R24: =IF(OR($H24="",$H24="EUR"),1,IFERROR(INDEX(FX_Rates!$D:$D,MATCH($H24,FX_Rates!$A:$A,0)),"")) -> 1 | S24: =IF(AND($I24="",$J24=""),"",IF($J24<>"",$J24,IF(OR($R24="",$R24=0),"",ROUND($I24/$R24,2)))) | T24: =IF($N24="","",IFERROR(INDEX(VAT_Codes!$C:$C,MATCH($N24,VAT_Codes!$A:$A,0)),"")&"") | U24: =IF(OR($S24="",$T24="",$T24="None"),0,IF($T24="Output",-$S24,$S24)) -> 0 | V24: =IF($N24="",0,IFERROR(INDEX(VAT_Codes!$D:$D,MATCH($N24,VAT_Codes!$A:$A,0)),0)) -> 0 | W24: =IF($U24=0,0,IF(IFERROR(INDEX(VAT_Codes!$F:$F,MATCH($N24,VAT_Codes!$A:$A,0)),"N")="Y",$U24,IF($L24<>"",ROUND(ABS($L24)/IF(OR($R24="",$R24=0),1,$R24),2)*SIGN($U24),ROUND($U24*$V24,2)))) -> 0 | X24: =IF($N24="","",IFERROR(INDEX(VAT_Codes!$H:$H,MATCH($N24,VAT_Codes!$A:$A,0)),"")&"") | Y24: =IF($A24="","",(YEAR($A24)-YEAR(Settings!$C$8))*12+MONTH($A24)-MONTH(Settings!$C$8)+1) | Z24: =IF(AND($C24="",$I24="",$J24=""),"",IF($N24="","NO VAT CODE",IF($T24="","UNKNOWN VAT CODE",IF($S24="","MISSING FX RATE",IF(OR($A24<Settings!$C$8,$A24>Settings!$C$9),"OUTSIDE PERIOD",IF(AND(IFERROR(INDEX(VAT_Codes!$E:$E,MATCH($N24,VAT_Codes!$A:$A,0)),"ANY")<>"ANY",$P24=""),"MISSING COUNTERPARTY COUNTRY",IF(AND(IFERROR(INDEX(VAT_Codes!$E:$E,MATCH($N24,VAT_Codes!$A:$A,0)),"ANY")<>"ANY",$P24<>IFERROR(INDEX(VAT_Codes!$E:$E,MATCH($N24,VAT_Codes!$A:$A,0)),"ANY")),"REGION MISMATCH","OK")))))))
M25: =IF($C25="","",IFERROR(INDEX(Account_Mapping!$C:$C,MATCH($C25&"",Account_Mapping!$A:$A,0))&"","")) | N25: =IF($K25<>"",$K25,$M25) | O25: =IF($F25="","",IFERROR(INDEX(Counterparties!$C:$C,MATCH($F25&"",Counterparties!$A:$A,0))&"","")) | P25: =IF($O25="","",IF($O25="CY","CY",IF(ISNUMBER(MATCH($O25,Lists!$A:$A,0)),"EU","3RD"))) | Q25: =IF($F25="","N",IFERROR(IF(INDEX(Counterparties!$E:$E,MATCH($F25&"",Counterparties!$A:$A,0))="Y","Y","N"),"N")) -> N | R25: =IF(OR($H25="",$H25="EUR"),1,IFERROR(INDEX(FX_Rates!$D:$D,MATCH($H25,FX_Rates!$A:$A,0)),"")) -> 1 | S25: =IF(AND($I25="",$J25=""),"",IF($J25<>"",$J25,IF(OR($R25="",$R25=0),"",ROUND($I25/$R25,2)))) | T25: =IF($N25="","",IFERROR(INDEX(VAT_Codes!$C:$C,MATCH($N25,VAT_Codes!$A:$A,0)),"")&"") | U25: =IF(OR($S25="",$T25="",$T25="None"),0,IF($T25="Output",-$S25,$S25)) -> 0 | V25: =IF($N25="",0,IFERROR(INDEX(VAT_Codes!$D:$D,MATCH($N25,VAT_Codes!$A:$A,0)),0)) -> 0 | W25: =IF($U25=0,0,IF(IFERROR(INDEX(VAT_Codes!$F:$F,MATCH($N25,VAT_Codes!$A:$A,0)),"N")="Y",$U25,IF($L25<>"",ROUND(ABS($L25)/IF(OR($R25="",$R25=0),1,$R25),2)*SIGN($U25),ROUND($U25*$V25,2)))) -> 0 | X25: =IF($N25="","",IFERROR(INDEX(VAT_Codes!$H:$H,MATCH($N25,VAT_Codes!$A:$A,0)),"")&"") | Y25: =IF($A25="","",(YEAR($A25)-YEAR(Settings!$C$8))*12+MONTH($A25)-MONTH(Settings!$C$8)+1) | Z25: =IF(AND($C25="",$I25="",$J25=""),"",IF($N25="","NO VAT CODE",IF($T25="","UNKNOWN VAT CODE",IF($S25="","MISSING FX RATE",IF(OR($A25<Settings!$C$8,$A25>Settings!$C$9),"OUTSIDE PERIOD",IF(AND(IFERROR(INDEX(VAT_Codes!$E:$E,MATCH($N25,VAT_Codes!$A:$A,0)),"ANY")<>"ANY",$P25=""),"MISSING COUNTERPARTY COUNTRY",IF(AND(IFERROR(INDEX(VAT_Codes!$E:$E,MATCH($N25,VAT_Codes!$A:$A,0)),"ANY")<>"ANY",$P25<>IFERROR(INDEX(VAT_Codes!$E:$E,MATCH($N25,VAT_Codes!$A:$A,0)),"ANY")),"REGION MISMATCH","OK")))))))
M26: =IF($C26="","",IFERROR(INDEX(Account_Mapping!$C:$C,MATCH($C26&"",Account_Mapping!$A:$A,0))&"","")) | N26: =IF($K26<>"",$K26,$M26) | O26: =IF($F26="","",IFERROR(INDEX(Counterparties!$C:$C,MATCH($F26&"",Counterparties!$A:$A,0))&"","")) | P26: =IF($O26="","",IF($O26="CY","CY",IF(ISNUMBER(MATCH($O26,Lists!$A:$A,0)),"EU","3RD"))) | Q26: =IF($F26="","N",IFERROR(IF(INDEX(Counterparties!$E:$E,MATCH($F26&"",Counterparties!$A:$A,0))="Y","Y","N"),"N")) -> N | R26: =IF(OR($H26="",$H26="EUR"),1,IFERROR(INDEX(FX_Rates!$D:$D,MATCH($H26,FX_Rates!$A:$A,0)),"")) -> 1 | S26: =IF(AND($I26="",$J26=""),"",IF($J26<>"",$J26,IF(OR($R26="",$R26=0),"",ROUND($I26/$R26,2)))) | T26: =IF($N26="","",IFERROR(INDEX(VAT_Codes!$C:$C,MATCH($N26,VAT_Codes!$A:$A,0)),"")&"") | U26: =IF(OR($S26="",$T26="",$T26="None"),0,IF($T26="Output",-$S26,$S26)) -> 0 | V26: =IF($N26="",0,IFERROR(INDEX(VAT_Codes!$D:$D,MATCH($N26,VAT_Codes!$A:$A,0)),0)) -> 0 | W26: =IF($U26=0,0,IF(IFERROR(INDEX(VAT_Codes!$F:$F,MATCH($N26,VAT_Codes!$A:$A,0)),"N")="Y",$U26,IF($L26<>"",ROUND(ABS($L26)/IF(OR($R26="",$R26=0),1,$R26),2)*SIGN($U26),ROUND($U26*$V26,2)))) -> 0 | X26: =IF($N26="","",IFERROR(INDEX(VAT_Codes!$H:$H,MATCH($N26,VAT_Codes!$A:$A,0)),"")&"") | Y26: =IF($A26="","",(YEAR($A26)-YEAR(Settings!$C$8))*12+MONTH($A26)-MONTH(Settings!$C$8)+1) | Z26: =IF(AND($C26="",$I26="",$J26=""),"",IF($N26="","NO VAT CODE",IF($T26="","UNKNOWN VAT CODE",IF($S26="","MISSING FX RATE",IF(OR($A26<Settings!$C$8,$A26>Settings!$C$9),"OUTSIDE PERIOD",IF(AND(IFERROR(INDEX(VAT_Codes!$E:$E,MATCH($N26,VAT_Codes!$A:$A,0)),"ANY")<>"ANY",$P26=""),"MISSING COUNTERPARTY COUNTRY",IF(AND(IFERROR(INDEX(VAT_Codes!$E:$E,MATCH($N26,VAT_Codes!$A:$A,0)),"ANY")<>"ANY",$P26<>IFERROR(INDEX(VAT_Codes!$E:$E,MATCH($N26,VAT_Codes!$A:$A,0)),"ANY")),"REGION MISMATCH","OK")))))))
M27: =IF($C27="","",IFERROR(INDEX(Account_Mapping!$C:$C,MATCH($C27&"",Account_Mapping!$A:$A,0))&"","")) | N27: =IF($K27<>"",$K27,$M27) | O27: =IF($F27="","",IFERROR(INDEX(Counterparties!$C:$C,MATCH($F27&"",Counterparties!$A:$A,0))&"","")) | P27: =IF($O27="","",IF($O27="CY","CY",IF(ISNUMBER(MATCH($O27,Lists!$A:$A,0)),"EU","3RD"))) | Q27: =IF($F27="","N",IFERROR(IF(INDEX(Counterparties!$E:$E,MATCH($F27&"",Counterparties!$A:$A,0))="Y","Y","N"),"N")) -> N | R27: =IF(OR($H27="",$H27="EUR"),1,IFERROR(INDEX(FX_Rates!$D:$D,MATCH($H27,FX_Rates!$A:$A,0)),"")) -> 1 | S27: =IF(AND($I27="",$J27=""),"",IF($J27<>"",$J27,IF(OR($R27="",$R27=0),"",ROUND($I27/$R27,2)))) | T27: =IF($N27="","",IFERROR(INDEX(VAT_Codes!$C:$C,MATCH($N27,VAT_Codes!$A:$A,0)),"")&"") | U27: =IF(OR($S27="",$T27="",$T27="None"),0,IF($T27="Output",-$S27,$S27)) -> 0 | V27: =IF($N27="",0,IFERROR(INDEX(VAT_Codes!$D:$D,MATCH($N27,VAT_Codes!$A:$A,0)),0)) -> 0 | W27: =IF($U27=0,0,IF(IFERROR(INDEX(VAT_Codes!$F:$F,MATCH($N27,VAT_Codes!$A:$A,0)),"N")="Y",$U27,IF($L27<>"",ROUND(ABS($L27)/IF(OR($R27="",$R27=0),1,$R27),2)*SIGN($U27),ROUND($U27*$V27,2)))) -> 0 | X27: =IF($N27="","",IFERROR(INDEX(VAT_Codes!$H:$H,MATCH($N27,VAT_Codes!$A:$A,0)),"")&"") | Y27: =IF($A27="","",(YEAR($A27)-YEAR(Settings!$C$8))*12+MONTH($A27)-MONTH(Settings!$C$8)+1) | Z27: =IF(AND($C27="",$I27="",$J27=""),"",IF($N27="","NO VAT CODE",IF($T27="","UNKNOWN VAT CODE",IF($S27="","MISSING FX RATE",IF(OR($A27<Settings!$C$8,$A27>Settings!$C$9),"OUTSIDE PERIOD",IF(AND(IFERROR(INDEX(VAT_Codes!$E:$E,MATCH($N27,VAT_Codes!$A:$A,0)),"ANY")<>"ANY",$P27=""),"MISSING COUNTERPARTY COUNTRY",IF(AND(IFERROR(INDEX(VAT_Codes!$E:$E,MATCH($N27,VAT_Codes!$A:$A,0)),"ANY")<>"ANY",$P27<>IFERROR(INDEX(VAT_Codes!$E:$E,MATCH($N27,VAT_Codes!$A:$A,0)),"ANY")),"REGION MISMATCH","OK")))))))
M28: =IF($C28="","",IFERROR(INDEX(Account_Mapping!$C:$C,MATCH($C28&"",Account_Mapping!$A:$A,0))&"","")) | N28: =IF($K28<>"",$K28,$M28) | O28: =IF($F28="","",IFERROR(INDEX(Counterparties!$C:$C,MATCH($F28&"",Counterparties!$A:$A,0))&"","")) | P28: =IF($O28="","",IF($O28="CY","CY",IF(ISNUMBER(MATCH($O28,Lists!$A:$A,0)),"EU","3RD"))) | Q28: =IF($F28="","N",IFERROR(IF(INDEX(Counterparties!$E:$E,MATCH($F28&"",Counterparties!$A:$A,0))="Y","Y","N"),"N")) -> N | R28: =IF(OR($H28="",$H28="EUR"),1,IFERROR(INDEX(FX_Rates!$D:$D,MATCH($H28,FX_Rates!$A:$A,0)),"")) -> 1 | S28: =IF(AND($I28="",$J28=""),"",IF($J28<>"",$J28,IF(OR($R28="",$R28=0),"",ROUND($I28/$R28,2)))) | T28: =IF($N28="","",IFERROR(INDEX(VAT_Codes!$C:$C,MATCH($N28,VAT_Codes!$A:$A,0)),"")&"") | U28: =IF(OR($S28="",$T28="",$T28="None"),0,IF($T28="Output",-$S28,$S28)) -> 0 | V28: =IF($N28="",0,IFERROR(INDEX(VAT_Codes!$D:$D,MATCH($N28,VAT_Codes!$A:$A,0)),0)) -> 0 | W28: =IF($U28=0,0,IF(IFERROR(INDEX(VAT_Codes!$F:$F,MATCH($N28,VAT_Codes!$A:$A,0)),"N")="Y",$U28,IF($L28<>"",ROUND(ABS($L28)/IF(OR($R28="",$R28=0),1,$R28),2)*SIGN($U28),ROUND($U28*$V28,2)))) -> 0 | X28: =IF($N28="","",IFERROR(INDEX(VAT_Codes!$H:$H,MATCH($N28,VAT_Codes!$A:$A,0)),"")&"") | Y28: =IF($A28="","",(YEAR($A28)-YEAR(Settings!$C$8))*12+MONTH($A28)-MONTH(Settings!$C$8)+1) | Z28: =IF(AND($C28="",$I28="",$J28=""),"",IF($N28="","NO VAT CODE",IF($T28="","UNKNOWN VAT CODE",IF($S28="","MISSING FX RATE",IF(OR($A28<Settings!$C$8,$A28>Settings!$C$9),"OUTSIDE PERIOD",IF(AND(IFERROR(INDEX(VAT_Codes!$E:$E,MATCH($N28,VAT_Codes!$A:$A,0)),"ANY")<>"ANY",$P28=""),"MISSING COUNTERPARTY COUNTRY",IF(AND(IFERROR(INDEX(VAT_Codes!$E:$E,MATCH($N28,VAT_Codes!$A:$A,0)),"ANY")<>"ANY",$P28<>IFERROR(INDEX(VAT_Codes!$E:$E,MATCH($N28,VAT_Codes!$A:$A,0)),"ANY")),"REGION MISMATCH","OK")))))))
M29: =IF($C29="","",IFERROR(INDEX(Account_Mapping!$C:$C,MATCH($C29&"",Account_Mapping!$A:$A,0))&"","")) | N29: =IF($K29<>"",$K29,$M29) | O29: =IF($F29="","",IFERROR(INDEX(Counterparties!$C:$C,MATCH($F29&"",Counterparties!$A:$A,0))&"","")) | P29: =IF($O29="","",IF($O29="CY","CY",IF(ISNUMBER(MATCH($O29,Lists!$A:$A,0)),"EU","3RD"))) | Q29: =IF($F29="","N",IFERROR(IF(INDEX(Counterparties!$E:$E,MATCH($F29&"",Counterparties!$A:$A,0))="Y","Y","N"),"N")) -> N | R29: =IF(OR($H29="",$H29="EUR"),1,IFERROR(INDEX(FX_Rates!$D:$D,MATCH($H29,FX_Rates!$A:$A,0)),"")) -> 1 | S29: =IF(AND($I29="",$J29=""),"",IF($J29<>"",$J29,IF(OR($R29="",$R29=0),"",ROUND($I29/$R29,2)))) | T29: =IF($N29="","",IFERROR(INDEX(VAT_Codes!$C:$C,MATCH($N29,VAT_Codes!$A:$A,0)),"")&"") | U29: =IF(OR($S29="",$T29="",$T29="None"),0,IF($T29="Output",-$S29,$S29)) -> 0 | V29: =IF($N29="",0,IFERROR(INDEX(VAT_Codes!$D:$D,MATCH($N29,VAT_Codes!$A:$A,0)),0)) -> 0 | W29: =IF($U29=0,0,IF(IFERROR(INDEX(VAT_Codes!$F:$F,MATCH($N29,VAT_Codes!$A:$A,0)),"N")="Y",$U29,IF($L29<>"",ROUND(ABS($L29)/IF(OR($R29="",$R29=0),1,$R29),2)*SIGN($U29),ROUND($U29*$V29,2)))) -> 0 | X29: =IF($N29="","",IFERROR(INDEX(VAT_Codes!$H:$H,MATCH($N29,VAT_Codes!$A:$A,0)),"")&"") | Y29: =IF($A29="","",(YEAR($A29)-YEAR(Settings!$C$8))*12+MONTH($A29)-MONTH(Settings!$C$8)+1) | Z29: =IF(AND($C29="",$I29="",$J29=""),"",IF($N29="","NO VAT CODE",IF($T29="","UNKNOWN VAT CODE",IF($S29="","MISSING FX RATE",IF(OR($A29<Settings!$C$8,$A29>Settings!$C$9),"OUTSIDE PERIOD",IF(AND(IFERROR(INDEX(VAT_Codes!$E:$E,MATCH($N29,VAT_Codes!$A:$A,0)),"ANY")<>"ANY",$P29=""),"MISSING COUNTERPARTY COUNTRY",IF(AND(IFERROR(INDEX(VAT_Codes!$E:$E,MATCH($N29,VAT_Codes!$A:$A,0)),"ANY")<>"ANY",$P29<>IFERROR(INDEX(VAT_Codes!$E:$E,MATCH($N29,VAT_Codes!$A:$A,0)),"ANY")),"REGION MISMATCH","OK")))))))
M30: =IF($C30="","",IFERROR(INDEX(Account_Mapping!$C:$C,MATCH($C30&"",Account_Mapping!$A:$A,0))&"","")) | N30: =IF($K30<>"",$K30,$M30) | O30: =IF($F30="","",IFERROR(INDEX(Counterparties!$C:$C,MATCH($F30&"",Counterparties!$A:$A,0))&"","")) | P30: =IF($O30="","",IF($O30="CY","CY",IF(ISNUMBER(MATCH($O30,Lists!$A:$A,0)),"EU","3RD"))) | Q30: =IF($F30="","N",IFERROR(IF(INDEX(Counterparties!$E:$E,MATCH($F30&"",Counterparties!$A:$A,0))="Y","Y","N"),"N")) -> N | R30: =IF(OR($H30="",$H30="EUR"),1,IFERROR(INDEX(FX_Rates!$D:$D,MATCH($H30,FX_Rates!$A:$A,0)),"")) -> 1 | S30: =IF(AND($I30="",$J30=""),"",IF($J30<>"",$J30,IF(OR($R30="",$R30=0),"",ROUND($I30/$R30,2)))) | T30: =IF($N30="","",IFERROR(INDEX(VAT_Codes!$C:$C,MATCH($N30,VAT_Codes!$A:$A,0)),"")&"") | U30: =IF(OR($S30="",$T30="",$T30="None"),0,IF($T30="Output",-$S30,$S30)) -> 0 | V30: =IF($N30="",0,IFERROR(INDEX(VAT_Codes!$D:$D,MATCH($N30,VAT_Codes!$A:$A,0)),0)) -> 0 | W30: =IF($U30=0,0,IF(IFERROR(INDEX(VAT_Codes!$F:$F,MATCH($N30,VAT_Codes!$A:$A,0)),"N")="Y",$U30,IF($L30<>"",ROUND(ABS($L30)/IF(OR($R30="",$R30=0),1,$R30),2)*SIGN($U30),ROUND($U30*$V30,2)))) -> 0 | X30: =IF($N30="","",IFERROR(INDEX(VAT_Codes!$H:$H,MATCH($N30,VAT_Codes!$A:$A,0)),"")&"") | Y30: =IF($A30="","",(YEAR($A30)-YEAR(Settings!$C$8))*12+MONTH($A30)-MONTH(Settings!$C$8)+1) | Z30: =IF(AND($C30="",$I30="",$J30=""),"",IF($N30="","NO VAT CODE",IF($T30="","UNKNOWN VAT CODE",IF($S30="","MISSING FX RATE",IF(OR($A30<Settings!$C$8,$A30>Settings!$C$9),"OUTSIDE PERIOD",IF(AND(IFERROR(INDEX(VAT_Codes!$E:$E,MATCH($N30,VAT_Codes!$A:$A,0)),"ANY")<>"ANY",$P30=""),"MISSING COUNTERPARTY COUNTRY",IF(AND(IFERROR(INDEX(VAT_Codes!$E:$E,MATCH($N30,VAT_Codes!$A:$A,0)),"ANY")<>"ANY",$P30<>IFERROR(INDEX(VAT_Codes!$E:$E,MATCH($N30,VAT_Codes!$A:$A,0)),"ANY")),"REGION MISMATCH","OK")))))))
M31: =IF($C31="","",IFERROR(INDEX(Account_Mapping!$C:$C,MATCH($C31&"",Account_Mapping!$A:$A,0))&"","")) | N31: =IF($K31<>"",$K31,$M31) | O31: =IF($F31="","",IFERROR(INDEX(Counterparties!$C:$C,MATCH($F31&"",Counterparties!$A:$A,0))&"","")) | P31: =IF($O31="","",IF($O31="CY","CY",IF(ISNUMBER(MATCH($O31,Lists!$A:$A,0)),"EU","3RD"))) | Q31: =IF($F31="","N",IFERROR(IF(INDEX(Counterparties!$E:$E,MATCH($F31&"",Counterparties!$A:$A,0))="Y","Y","N"),"N")) -> N | R31: =IF(OR($H31="",$H31="EUR"),1,IFERROR(INDEX(FX_Rates!$D:$D,MATCH($H31,FX_Rates!$A:$A,0)),"")) -> 1 | S31: =IF(AND($I31="",$J31=""),"",IF($J31<>"",$J31,IF(OR($R31="",$R31=0),"",ROUND($I31/$R31,2)))) | T31: =IF($N31="","",IFERROR(INDEX(VAT_Codes!$C:$C,MATCH($N31,VAT_Codes!$A:$A,0)),"")&"") | U31: =IF(OR($S31="",$T31="",$T31="None"),0,IF($T31="Output",-$S31,$S31)) -> 0 | V31: =IF($N31="",0,IFERROR(INDEX(VAT_Codes!$D:$D,MATCH($N31,VAT_Codes!$A:$A,0)),0)) -> 0 | W31: =IF($U31=0,0,IF(IFERROR(INDEX(VAT_Codes!$F:$F,MATCH($N31,VAT_Codes!$A:$A,0)),"N")="Y",$U31,IF($L31<>"",ROUND(ABS($L31)/IF(OR($R31="",$R31=0),1,$R31),2)*SIGN($U31),ROUND($U31*$V31,2)))) -> 0 | X31: =IF($N31="","",IFERROR(INDEX(VAT_Codes!$H:$H,MATCH($N31,VAT_Codes!$A:$A,0)),"")&"") | Y31: =IF($A31="","",(YEAR($A31)-YEAR(Settings!$C$8))*12+MONTH($A31)-MONTH(Settings!$C$8)+1) | Z31: =IF(AND($C31="",$I31="",$J31=""),"",IF($N31="","NO VAT CODE",IF($T31="","UNKNOWN VAT CODE",IF($S31="","MISSING FX RATE",IF(OR($A31<Settings!$C$8,$A31>Settings!$C$9),"OUTSIDE PERIOD",IF(AND(IFERROR(INDEX(VAT_Codes!$E:$E,MATCH($N31,VAT_Codes!$A:$A,0)),"ANY")<>"ANY",$P31=""),"MISSING COUNTERPARTY COUNTRY",IF(AND(IFERROR(INDEX(VAT_Codes!$E:$E,MATCH($N31,VAT_Codes!$A:$A,0)),"ANY")<>"ANY",$P31<>IFERROR(INDEX(VAT_Codes!$E:$E,MATCH($N31,VAT_Codes!$A:$A,0)),"ANY")),"REGION MISMATCH","OK")))))))
M32: =IF($C32="","",IFERROR(INDEX(Account_Mapping!$C:$C,MATCH($C32&"",Account_Mapping!$A:$A,0))&"","")) | N32: =IF($K32<>"",$K32,$M32) | O32: =IF($F32="","",IFERROR(INDEX(Counterparties!$C:$C,MATCH($F32&"",Counterparties!$A:$A,0))&"","")) | P32: =IF($O32="","",IF($O32="CY","CY",IF(ISNUMBER(MATCH($O32,Lists!$A:$A,0)),"EU","3RD"))) | Q32: =IF($F32="","N",IFERROR(IF(INDEX(Counterparties!$E:$E,MATCH($F32&"",Counterparties!$A:$A,0))="Y","Y","N"),"N")) -> N | R32: =IF(OR($H32="",$H32="EUR"),1,IFERROR(INDEX(FX_Rates!$D:$D,MATCH($H32,FX_Rates!$A:$A,0)),"")) -> 1 | S32: =IF(AND($I32="",$J32=""),"",IF($J32<>"",$J32,IF(OR($R32="",$R32=0),"",ROUND($I32/$R32,2)))) | T32: =IF($N32="","",IFERROR(INDEX(VAT_Codes!$C:$C,MATCH($N32,VAT_Codes!$A:$A,0)),"")&"") | U32: =IF(OR($S32="",$T32="",$T32="None"),0,IF($T32="Output",-$S32,$S32)) -> 0 | V32: =IF($N32="",0,IFERROR(INDEX(VAT_Codes!$D:$D,MATCH($N32,VAT_Codes!$A:$A,0)),0)) -> 0 | W32: =IF($U32=0,0,IF(IFERROR(INDEX(VAT_Codes!$F:$F,MATCH($N32,VAT_Codes!$A:$A,0)),"N")="Y",$U32,IF($L32<>"",ROUND(ABS($L32)/IF(OR($R32="",$R32=0),1,$R32),2)*SIGN($U32),ROUND($U32*$V32,2)))) -> 0 | X32: =IF($N32="","",IFERROR(INDEX(VAT_Codes!$H:$H,MATCH($N32,VAT_Codes!$A:$A,0)),"")&"") | Y32: =IF($A32="","",(YEAR($A32)-YEAR(Settings!$C$8))*12+MONTH($A32)-MONTH(Settings!$C$8)+1) | Z32: =IF(AND($C32="",$I32="",$J32=""),"",IF($N32="","NO VAT CODE",IF($T32="","UNKNOWN VAT CODE",IF($S32="","MISSING FX RATE",IF(OR($A32<Settings!$C$8,$A32>Settings!$C$9),"OUTSIDE PERIOD",IF(AND(IFERROR(INDEX(VAT_Codes!$E:$E,MATCH($N32,VAT_Codes!$A:$A,0)),"ANY")<>"ANY",$P32=""),"MISSING COUNTERPARTY COUNTRY",IF(AND(IFERROR(INDEX(VAT_Codes!$E:$E,MATCH($N32,VAT_Codes!$A:$A,0)),"ANY")<>"ANY",$P32<>IFERROR(INDEX(VAT_Codes!$E:$E,MATCH($N32,VAT_Codes!$A:$A,0)),"ANY")),"REGION MISMATCH","OK")))))))
... M2004: =IF($C2004="","",IFERROR(INDEX(Account_Mapping!$C:$C,MATCH($C2004&"",Account_Mapping!$A:$A,0))&"","")) | N2004: =IF($K2004<>"",$K2004,$M2004) | O2004: =IF($F2004="","",IFERROR(INDEX(Counterparties!$C:$C,MATCH($F2004&"",Counterparties!$A:$A,0))&"","")) | P2004: =IF($O2004="","",IF($O2004="CY","CY",IF(ISNUMBER(MATCH($O2004,Lists!$A:$A,0)),"EU","3RD"))) | Q2004: =IF($F2004="","N",IFERROR(IF(INDEX(Counterparties!$E:$E,MATCH($F2004&"",Counterparties!$A:$A,0))="Y","Y","N"),"N")) -> N | R2004: =IF(OR($H2004="",$H2004="EUR"),1,IFERROR(INDEX(FX_Rates!$D:$D,MATCH($H2004,FX_Rates!$A:$A,0)),"")) -> 1 | S2004: =IF(AND($I2004="",$J2004=""),"",IF($J2004<>"",$J2004,IF(OR($R2004="",$R2004=0),"",ROUND($I2004/$R2004,2)))) | T2004: =IF($N2004="","",IFERROR(INDEX(VAT_Codes!$C:$C,MATCH($N2004,VAT_Codes!$A:$A,0)),"")&"") | U2004: =IF(OR($S2004="",$T2004="",$T2004="None"),0,IF($T2004="Output",-$S2004,$S2004)) -> 0 | V2004: =IF($N2004="",0,IFERROR(INDEX(VAT_Codes!$D:$D,MATCH($N2004,VAT_Codes!$A:$A,0)),0)) -> 0 | W2004: =IF($U2004=0,0,IF(IFERROR(INDEX(VAT_Codes!$F:$F,MATCH($N2004,VAT_Codes!$A:$A,0)),"N")="Y",$U2004,IF($L2004<>"",ROUND(ABS($L2004)/IF(OR($R2004="",$R2004=0),1,$R2004),2)*SIGN($U2004),ROUND($U2004*$V2004,2)))) -> 0 | X2004: =IF($N2004="","",IFERROR(INDEX(VAT_Codes!$H:$H,MATCH($N2004,VAT_Codes!$A:$A,0)),"")&"") | Y2004: =IF($A2004="","",(YEAR($A2004)-YEAR(Settings!$C$8))*12+MONTH($A2004)-MONTH(Settings!$C$8)+1) | Z2004: =IF(AND($C2004="",$I2004="",$J2004=""),"",IF($N2004="","NO VAT CODE",IF($T2004="","UNKNOWN VAT CODE",IF($S2004="","MISSING FX RATE",IF(OR($A2004<Settings!$C$8,$A2004>Settings!$C$9),"OUTSIDE PERIOD",IF(AND(IFERROR(INDEX(VAT_Codes!$E:$E,MATCH($N2004,VAT_Codes!$A:$A,0)),"ANY")<>"ANY",$P2004=""),"MISSING COUNTERPARTY COUNTRY",IF(AND(IFERROR(INDEX(VAT_Codes!$E:$E,MATCH($N2004,VAT_Codes!$A:$A,0)),"ANY")<>"ANY",$P2004<>IFERROR(INDEX(VAT_Codes!$E:$E,MATCH($N2004,VAT_Codes!$A:$A,0)),"ANY")),"REGION MISMATCH","OK")))))))

Sheet Account_Mapping
A1: Account_Mapping - default VAT code per GL account
A2: Give every account a code from VAT_Codes. Non-VAT accounts (balance sheet, payroll, depreciation, VAT control) = NR. Override single lines in GL_Input column K.
A4: Account code | B4: Account name | C4: VAT code | D4: Notes / reasoning | E4: GL movement EUR (Dr+/Cr-) | F4: No. of GL lines | G4: Lines with exceptions
A5: 1200 | B5: Bank - EUR | C5: NR | D5: EXAMPLE | E5: =IF($A5="","",SUMIFS(GL_Input!$S:$S,GL_Input!$C:$C,$A5)) -> -20000 | F5: =IF($A5="","",COUNTIFS(GL_Input!$C:$C,$A5)) -> 1 | G5: =IF($A5="","",COUNTIFS(GL_Input!$C:$C,$A5,GL_Input!$Z:$Z,"<>OK")) -> 0
A6: 2101 | B6: Input VAT | C6: NR | D6: EXAMPLE VAT control account | E6: =IF($A6="","",SUMIFS(GL_Input!$S:$S,GL_Input!$C:$C,$A6)) -> 380 | F6: =IF($A6="","",COUNTIFS(GL_Input!$C:$C,$A6)) -> 1 | G6: =IF($A6="","",COUNTIFS(GL_Input!$C:$C,$A6,GL_Input!$Z:$Z,"<>OK")) -> 0
A7: 2105 | B7: Import VAT paid to Customs | C7: IVAT | D7: EXAMPLE Line amount = import VAT | E7: =IF($A7="","",SUMIFS(GL_Input!$S:$S,GL_Input!$C:$C,$A7)) -> 700 | F7: =IF($A7="","",COUNTIFS(GL_Input!$C:$C,$A7)) -> 1 | G7: =IF($A7="","",COUNTIFS(GL_Input!$C:$C,$A7,GL_Input!$Z:$Z,"<>OK")) -> 0
A8: 2201 | B8: Output VAT | C8: NR | D8: EXAMPLE VAT control account | E8: =IF($A8="","",SUMIFS(GL_Input!$S:$S,GL_Input!$C:$C,$A8)) -> -1900 | F8: =IF($A8="","",COUNTIFS(GL_Input!$C:$C,$A8)) -> 1 | G8: =IF($A8="","",COUNTIFS(GL_Input!$C:$C,$A8,GL_Input!$Z:$Z,"<>OK")) -> 0
A9: 4000 | B9: Sales - Cyprus customers | C9: S19 | D9: EXAMPLE | E9: =IF($A9="","",SUMIFS(GL_Input!$S:$S,GL_Input!$C:$C,$A9)) -> -10000 | F9: =IF($A9="","",COUNTIFS(GL_Input!$C:$C,$A9)) -> 1 | G9: =IF($A9="","",COUNTIFS(GL_Input!$C:$C,$A9,GL_Input!$Z:$Z,"<>OK")) -> 0
A10: 4100 | B10: Management fees - group | C10: EUS | D10: EXAMPLE EU group = EUS; override non-EU lines? | E10: =IF($A10="","",SUMIFS(GL_Input!$S:$S,GL_Input!$C:$C,$A10)) -> -50753.28 | F10: =IF($A10="","",COUNTIFS(GL_Input!$C:$C,$A10)) -> 2 | G10: =IF($A10="","",COUNTIFS(GL_Input!$C:$C,$A10,GL_Input!$Z:$Z,"<>OK")) -> 0
A11: 4300 | B11: Sales of goods - export / EU | C11: EUG | D11: EXAMPLE | E11: =IF($A11="","",SUMIFS(GL_Input!$S:$S,GL_Input!$C:$C,$A11)) -> -18301.31 | F11: =IF($A11="","",COUNTIFS(GL_Input!$C:$C,$A11)) -> 2 | G11: =IF($A11="","",COUNTIFS(GL_Input!$C:$C,$A11,GL_Input!$Z:$Z,"<>OK")) -> 0
A12: 5000 | B12: Purchases of goods | C12: AEG19 | D12: EXAMPLE | E12: =IF($A12="","",SUMIFS(GL_Input!$S:$S,GL_Input!$C:$C,$A12)) -> 5000 | F12: =IF($A12="","",COUNTIFS(GL_Input!$C:$C,$A12)) -> 1 | G12: =IF($A12="","",COUNTIFS(GL_Input!$C:$C,$A12,GL_Input!$Z:$Z,"<>OK")) -> 0
A13: 5010 | B13: Imports of goods | C13: IMP | D13: EXAMPLE | E13: =IF($A13="","",SUMIFS(GL_Input!$S:$S,GL_Input!$C:$C,$A13)) -> 3433.77 | F13: =IF($A13="","",COUNTIFS(GL_Input!$C:$C,$A13)) -> 1 | G13: =IF($A13="","",COUNTIFS(GL_Input!$C:$C,$A13,GL_Input!$Z:$Z,"<>OK")) -> 0
A14: 6000 | B14: Professional fees | C14: P19 | D14: EXAMPLE | E14: =IF($A14="","",SUMIFS(GL_Input!$S:$S,GL_Input!$C:$C,$A14)) -> 3030.13 | F14: =IF($A14="","",COUNTIFS(GL_Input!$C:$C,$A14)) -> 2 | G14: =IF($A14="","",COUNTIFS(GL_Input!$C:$C,$A14,GL_Input!$Z:$Z,"<>OK")) -> 0
A15: 6100 | B15: Group recharges | C15: AES19 | D15: EXAMPLE | E15: =IF($A15="","",SUMIFS(GL_Input!$S:$S,GL_Input!$C:$C,$A15)) -> 15000 | F15: =IF($A15="","",COUNTIFS(GL_Input!$C:$C,$A15)) -> 1 | G15: =IF($A15="","",COUNTIFS(GL_Input!$C:$C,$A15,GL_Input!$Z:$Z,"<>OK")) -> 0
A16: 6500 | B16: Entertainment | C16: PB19 | D16: EXAMPLE Blocked input VAT | E16: =IF($A16="","",SUMIFS(GL_Input!$S:$S,GL_Input!$C:$C,$A16)) -> 300 | F16: =IF($A16="","",COUNTIFS(GL_Input!$C:$C,$A16)) -> 1 | G16: =IF($A16="","",COUNTIFS(GL_Input!$C:$C,$A16,GL_Input!$Z:$Z,"<>OK")) -> 0
A17: 7000 | B17: Salaries | C17: NR | D17: EXAMPLE | E17: =IF($A17="","",SUMIFS(GL_Input!$S:$S,GL_Input!$C:$C,$A17)) -> 20000 | F17: =IF($A17="","",COUNTIFS(GL_Input!$C:$C,$A17)) -> 1 | G17: =IF($A17="","",COUNTIFS(GL_Input!$C:$C,$A17,GL_Input!$Z:$Z,"<>OK")) -> 0

Sheet Counterparties
A1: Counterparties - country, VAT number and inter-company flag
A2: Country = ISO 2-letter code (CY, GR, DE, GB, US, AE...). Inter-company = Y for all group companies. The code must match GL_Input column F.
A4: Counterparty code | B4: Name | C4: Country (ISO) | D4: VAT number (with prefix) | E4: Inter-company (Y/N) | F4: Relationship / notes | G4: Region | H4: Lines in GL | I4: Sales value EUR | J4: Purchase value EUR
A5: C-CY01 | B5: Limassol Trading Ltd | C5: CY | D5: CY10111111A | E5: N | F5: EXAMPLE | G5: =IF($C5="","",IF($C5="CY","CY",IF(ISNUMBER(MATCH($C5,Lists!$A:$A,0)),"EU","3RD"))) -> CY | H5: =IF($A5="","",COUNTIFS(GL_Input!$F:$F,$A5)) -> 2 | I5: =IF($A5="","",SUMIFS(GL_Input!$U:$U,GL_Input!$F:$F,$A5,GL_Input!$T:$T,"Output")) -> 10000 | J5: =IF($A5="","",SUMIFS(GL_Input!$U:$U,GL_Input!$F:$F,$A5,GL_Input!$T:$T,"Input")) -> 0
A6: IC-DE01 | B6: Example GmbH (group) | C6: DE | D6: DE123456789 | E6: Y | F6: EXAMPLE Sister company | G6: =IF($C6="","",IF($C6="CY","CY",IF(ISNUMBER(MATCH($C6,Lists!$A:$A,0)),"EU","3RD"))) -> EU | H6: =IF($A6="","",COUNTIFS(GL_Input!$F:$F,$A6)) -> 1 | I6: =IF($A6="","",SUMIFS(GL_Input!$U:$U,GL_Input!$F:$F,$A6,GL_Input!$T:$T,"Output")) -> 25000 | J6: =IF($A6="","",SUMIFS(GL_Input!$U:$U,GL_Input!$F:$F,$A6,GL_Input!$T:$T,"Input")) -> 0
A7: IC-AE01 | B7: Example FZE Dubai (group) | C7: AE | E7: Y | F7: EXAMPLE Sister company | G7: =IF($C7="","",IF($C7="CY","CY",IF(ISNUMBER(MATCH($C7,Lists!$A:$A,0)),"EU","3RD"))) -> 3RD | H7: =IF($A7="","",COUNTIFS(GL_Input!$F:$F,$A7)) -> 1 | I7: =IF($A7="","",SUMIFS(GL_Input!$U:$U,GL_Input!$F:$F,$A7,GL_Input!$T:$T,"Output")) -> 25753.28 | J7: =IF($A7="","",SUMIFS(GL_Input!$U:$U,GL_Input!$F:$F,$A7,GL_Input!$T:$T,"Input")) -> 0
A8: C-IT01 | B8: Milano Srl | C8: IT | D8: IT01234567890 | E8: N | F8: EXAMPLE | G8: =IF($C8="","",IF($C8="CY","CY",IF(ISNUMBER(MATCH($C8,Lists!$A:$A,0)),"EU","3RD"))) -> EU | H8: =IF($A8="","",COUNTIFS(GL_Input!$F:$F,$A8)) -> 1 | I8: =IF($A8="","",SUMIFS(GL_Input!$U:$U,GL_Input!$F:$F,$A8,GL_Input!$T:$T,"Output")) -> 8000 | J8: =IF($A8="","",SUMIFS(GL_Input!$U:$U,GL_Input!$F:$F,$A8,GL_Input!$T:$T,"Input")) -> 0
A9: C-US01 | B9: Boston Inc | C9: US | E9: N | F9: EXAMPLE | G9: =IF($C9="","",IF($C9="CY","CY",IF(ISNUMBER(MATCH($C9,Lists!$A:$A,0)),"EU","3RD"))) -> 3RD | H9: =IF($A9="","",COUNTIFS(GL_Input!$F:$F,$A9)) -> 1 | I9: =IF($A9="","",SUMIFS(GL_Input!$U:$U,GL_Input!$F:$F,$A9,GL_Input!$T:$T,"Output")) -> 10301.31 | J9: =IF($A9="","",SUMIFS(GL_Input!$U:$U,GL_Input!$F:$F,$A9,GL_Input!$T:$T,"Input")) -> 0
A10: S-CY01 | B10: Nicosia Audit Ltd | C10: CY | D10: CY10222222B | E10: N | F10: EXAMPLE | G10: =IF($C10="","",IF($C10="CY","CY",IF(ISNUMBER(MATCH($C10,Lists!$A:$A,0)),"EU","3RD"))) -> CY | H10: =IF($A10="","",COUNTIFS(GL_Input!$F:$F,$A10)) -> 2 | I10: =IF($A10="","",SUMIFS(GL_Input!$U:$U,GL_Input!$F:$F,$A10,GL_Input!$T:$T,"Output")) -> 0 | J10: =IF($A10="","",SUMIFS(GL_Input!$U:$U,GL_Input!$F:$F,$A10,GL_Input!$T:$T,"Input")) -> 2000
A11: IC-NL01 | B11: Example BV (parent) | C11: NL | D11: NL123456789B01 | E11: Y | F11: EXAMPLE Parent company | G11: =IF($C11="","",IF($C11="CY","CY",IF(ISNUMBER(MATCH($C11,Lists!$A:$A,0)),"EU","3RD"))) -> EU | H11: =IF($A11="","",COUNTIFS(GL_Input!$F:$F,$A11)) -> 1 | I11: =IF($A11="","",SUMIFS(GL_Input!$U:$U,GL_Input!$F:$F,$A11,GL_Input!$T:$T,"Output")) -> 0 | J11: =IF($A11="","",SUMIFS(GL_Input!$U:$U,GL_Input!$F:$F,$A11,GL_Input!$T:$T,"Input")) -> 15000
A12: S-US01 | B12: Cloudsoft Inc | C12: US | E12: N | F12: EXAMPLE | G12: =IF($C12="","",IF($C12="CY","CY",IF(ISNUMBER(MATCH($C12,Lists!$A:$A,0)),"EU","3RD"))) -> 3RD | H12: =IF($A12="","",COUNTIFS(GL_Input!$F:$F,$A12)) -> 1 | I12: =IF($A12="","",SUMIFS(GL_Input!$U:$U,GL_Input!$F:$F,$A12,GL_Input!$T:$T,"Output")) -> 0 | J12: =IF($A12="","",SUMIFS(GL_Input!$U:$U,GL_Input!$F:$F,$A12,GL_Input!$T:$T,"Input")) -> 1030.13
A13: S-DE01 | B13: Hamburg Supplies GmbH | C13: DE | D13: DE987654321 | E13: N | F13: EXAMPLE | G13: =IF($C13="","",IF($C13="CY","CY",IF(ISNUMBER(MATCH($C13,Lists!$A:$A,0)),"EU","3RD"))) -> EU | H13: =IF($A13="","",COUNTIFS(GL_Input!$F:$F,$A13)) -> 1 | I13: =IF($A13="","",SUMIFS(GL_Input!$U:$U,GL_Input!$F:$F,$A13,GL_Input!$T:$T,"Output")) -> 0 | J13: =IF($A13="","",SUMIFS(GL_Input!$U:$U,GL_Input!$F:$F,$A13,GL_Input!$T:$T,"Input")) -> 5000
A14: S-CN01 | B14: Shenzhen Mfg Co | C14: CN | E14: N | F14: EXAMPLE | G14: =IF($C14="","",IF($C14="CY","CY",IF(ISNUMBER(MATCH($C14,Lists!$A:$A,0)),"EU","3RD"))) -> 3RD | H14: =IF($A14="","",COUNTIFS(GL_Input!$F:$F,$A14)) -> 1 | I14: =IF($A14="","",SUMIFS(GL_Input!$U:$U,GL_Input!$F:$F,$A14,GL_Input!$T:$T,"Output")) -> 0 | J14: =IF($A14="","",SUMIFS(GL_Input!$U:$U,GL_Input!$F:$F,$A14,GL_Input!$T:$T,"Input")) -> 3433.77
A15: S-CY02 | B15: Paphos Restaurant Ltd | C15: CY | D15: CY10333333C | E15: N | F15: EXAMPLE | G15: =IF($C15="","",IF($C15="CY","CY",IF(ISNUMBER(MATCH($C15,Lists!$A:$A,0)),"EU","3RD"))) -> CY | H15: =IF($A15="","",COUNTIFS(GL_Input!$F:$F,$A15)) -> 1 | I15: =IF($A15="","",SUMIFS(GL_Input!$U:$U,GL_Input!$F:$F,$A15,GL_Input!$T:$T,"Output")) -> 0 | J15: =IF($A15="","",SUMIFS(GL_Input!$U:$U,GL_Input!$F:$F,$A15,GL_Input!$T:$T,"Input")) -> 300

Sheet VAT_Codes
A1: VAT_Codes - VAT treatments and the return boxes they feed
A2: Y = the code feeds that box. Add your own codes in the blank rows (keep the columns). Recovery: 100% / 0% / pro-rata from Settings.
A4: Code | B4: Description | C4: Nature | D4: VAT rate | E4: Expected region | F4: Line is VAT (Y/N) | G4: Input recovery % | H4: VIES type | I4: Box 1 | J4: Box 2 | K4: Box 4 | L4: Box 6 | M4: Box 7 | N4: Box 8A | O4: Box 8B | P4: Box 9 | Q4: Box 10 | R4: Box 11A | S4: Box 11B | T4: Net value EUR | U4: VAT EUR | V4: VAT reclaimable EUR | W4: No. of lines | X4: Guidance / legal basis
A5: S19 | B5: Domestic sales - standard rate 19% | C5: Output | D5: 0.19 | E5: CY | F5: N | G5: 1 | I5: Y | L5: Y | T5: =IF($A5="",0,SUMIFS(GL_Input!$U:$U,GL_Input!$N:$N,$A5)) -> 10000 | U5: =IF($A5="",0,SUMIFS(GL_Input!$W:$W,GL_Input!$N:$N,$A5)) -> 1900 | V5: =ROUND(U5*N(G5),2) -> 1900 | W5: =IF($A5="",0,COUNTIFS(GL_Input!$N:$N,$A5)) -> 1 | X5: Supplies taxable in Cyprus at 19%. Includes inter-company supplies to Cyprus group companies (unless in a VAT group).
A6: S9 | B6: Domestic sales - reduced rate 9% | C6: Output | D6: 0.09 | E6: CY | F6: N | G6: 1 | I6: Y | L6: Y | T6: =IF($A6="",0,SUMIFS(GL_Input!$U:$U,GL_Input!$N:$N,$A6)) -> 0 | U6: =IF($A6="",0,SUMIFS(GL_Input!$W:$W,GL_Input!$N:$N,$A6)) -> 0 | V6: =ROUND(U6*N(G6),2) -> 0 | W6: =IF($A6="",0,COUNTIFS(GL_Input!$N:$N,$A6)) -> 0 | X6: e.g. hotel accommodation, restaurant/catering services - check the reduced-rate schedule.
A7: S5 | B7: Domestic sales - reduced rate 5% | C7: Output | D7: 0.05 | E7: CY | F7: N | G7: 1 | I7: Y | L7: Y | T7: =IF($A7="",0,SUMIFS(GL_Input!$U:$U,GL_Input!$N:$N,$A7)) -> 0 | U7: =IF($A7="",0,SUMIFS(GL_Input!$W:$W,GL_Input!$N:$N,$A7)) -> 0 | V7: =ROUND(U7*N(G7),2) -> 0 | W7: =IF($A7="",0,COUNTIFS(GL_Input!$N:$N,$A7)) -> 0 | X7: e.g. foodstuffs, pharmaceuticals, qualifying residential property - check the reduced-rate schedule.
A8: S3 | B8: Domestic sales - super-reduced rate 3% | C8: Output | D8: 0.03 | E8: CY | F8: N | G8: 1 | I8: Y | L8: Y | T8: =IF($A8="",0,SUMIFS(GL_Input!$U:$U,GL_Input!$N:$N,$A8)) -> 0 | U8: =IF($A8="",0,SUMIFS(GL_Input!$W:$W,GL_Input!$N:$N,$A8)) -> 0 | V8: =ROUND(U8*N(G8),2) -> 0 | W8: =IF($A8="",0,COUNTIFS(GL_Input!$N:$N,$A8)) -> 0 | X8: e.g. books, newspapers, periodicals - check the reduced-rate schedule.
A9: Z0 | B9: Domestic zero-rated supplies (not exports) | C9: Output | D9: 0 | E9: ANY | F9: N | G9: 1 | L9: Y | P9: Y | T9: =IF($A9="",0,SUMIFS(GL_Input!$U:$U,GL_Input!$N:$N,$A9)) -> 0 | U9: =IF($A9="",0,SUMIFS(GL_Input!$W:$W,GL_Input!$N:$N,$A9)) -> 0 | V9: =ROUND(U9*N(G9),2) -> 0 | W9: =IF($A9="",0,COUNTIFS(GL_Input!$N:$N,$A9)) -> 0 | X9: 0% supplies in Cyprus (e.g. items temporarily zero-rated, qualifying ships/aircraft supplies).
A10: EXPG | B10: Exports of goods to third countries | C10: Output | D10: 0 | E10: 3RD | F10: N | G10: 1 | L10: Y | P10: Y | T10: =IF($A10="",0,SUMIFS(GL_Input!$U:$U,GL_Input!$N:$N,$A10)) -> 10301.31 | U10: =IF($A10="",0,SUMIFS(GL_Input!$W:$W,GL_Input!$N:$N,$A10)) -> 0 | V10: =ROUND(U10*N(G10),2) -> 0 | W10: =IF($A10="",0,COUNTIFS(GL_Input!$N:$N,$A10)) -> 1 | X10: Goods dispatched outside the EU. Keep customs export evidence (SAD / ECS exit message).
A11: EUG | B11: Intra-EU supplies of goods (B2B) | C11: Output | D11: 0 | E11: EU | F11: N | G11: 1 | H11: G | L11: Y | N11: Y | T11: =IF($A11="",0,SUMIFS(GL_Input!$U:$U,GL_Input!$N:$N,$A11)) -> 8000 | U11: =IF($A11="",0,SUMIFS(GL_Input!$W:$W,GL_Input!$N:$N,$A11)) -> 0 | V11: =ROUND(U11*N(G11),2) -> 0 | W11: =IF($A11="",0,COUNTIFS(GL_Input!$N:$N,$A11)) -> 1 | X11: Goods dispatched to a VAT-registered customer in another member state. Customer VAT no. must be valid on VIES. Reported in VIES.
A12: EUS | B12: Services to EU taxable persons (general rule - reverse charge by customer) | C12: Output | D12: 0 | E12: EU | F12: N | G12: 1 | H12: S | L12: Y | O12: Y | T12: =IF($A12="",0,SUMIFS(GL_Input!$U:$U,GL_Input!$N:$N,$A12)) -> 25000 | U12: =IF($A12="",0,SUMIFS(GL_Input!$W:$W,GL_Input!$N:$N,$A12)) -> 0 | V12: =ROUND(U12*N(G12),2) -> 0 | W12: =IF($A12="",0,COUNTIFS(GL_Input!$N:$N,$A12)) -> 1 | X12: B2B services where the place of supply is the customer's member state (s.14 / Art. 44). Includes inter-company management fees, recharges, IT, consultancy to EU group companies. Invoice must say 'Reverse charge'. Reported in VIES.
A13: TRI | B13: Triangular transactions (Cyprus as intermediary) | C13: Output | D13: 0 | E13: EU | F13: N | G13: 1 | H13: T | L13: Y | Q13: Y | T13: =IF($A13="",0,SUMIFS(GL_Input!$U:$U,GL_Input!$N:$N,$A13)) -> 0 | U13: =IF($A13="",0,SUMIFS(GL_Input!$W:$W,GL_Input!$N:$N,$A13)) -> 0 | V13: =ROUND(U13*N(G13),2) -> 0 | W13: =IF($A13="",0,COUNTIFS(GL_Input!$N:$N,$A13)) -> 0 | X13: Simplified triangulation - goods go directly from the first to the third member state. Reported in VIES with the triangulation indicator.
A14: OS3 | B14: Services to customers outside the EU (outside scope, with right to deduct) | C14: Output | D14: 0 | E14: 3RD | F14: N | G14: 1 | L14: Y | Q14: Y | T14: =IF($A14="",0,SUMIFS(GL_Input!$U:$U,GL_Input!$N:$N,$A14)) -> 25753.28 | U14: =IF($A14="",0,SUMIFS(GL_Input!$W:$W,GL_Input!$N:$N,$A14)) -> 0 | V14: =ROUND(U14*N(G14),2) -> 0 | W14: =IF($A14="",0,COUNTIFS(GL_Input!$N:$N,$A14)) -> 1 | X14: B2B services to third-country customers, including inter-company services to non-EU group companies. Not in VIES.
A15: OSS | B15: Distance sales / B2C services declared through OSS | C15: Output | D15: 0 | E15: EU | F15: N | G15: 1 | L15: Y | Q15: Y | T15: =IF($A15="",0,SUMIFS(GL_Input!$U:$U,GL_Input!$N:$N,$A15)) -> 0 | U15: =IF($A15="",0,SUMIFS(GL_Input!$W:$W,GL_Input!$N:$N,$A15)) -> 0 | V15: =ROUND(U15*N(G15),2) -> 0 | W15: =IF($A15="",0,COUNTIFS(GL_Input!$N:$N,$A15)) -> 0 | X15: Sales taxed in another member state and declared in the OSS return. The value only goes in Boxes 6 and 10.
A16: FIN3 | B16: Financial / insurance services to recipients outside the EU | C16: Output | D16: 0 | E16: 3RD | F16: N | G16: 1 | L16: Y | Q16: Y | T16: =IF($A16="",0,SUMIFS(GL_Input!$U:$U,GL_Input!$N:$N,$A16)) -> 0 | U16: =IF($A16="",0,SUMIFS(GL_Input!$W:$W,GL_Input!$N:$N,$A16)) -> 0 | V16: =ROUND(U16*N(G16),2) -> 0 | W16: =IF($A16="",0,COUNTIFS(GL_Input!$N:$N,$A16)) -> 0 | X16: Financial and insurance services (e.g. inter-company loan interest) to non-EU recipients give a right to deduct input VAT.
A17: FINEU | B17: Financial / insurance services to EU recipients (exempt, no right to deduct) | C17: Output | D17: 0 | E17: EU | F17: N | G17: 1 | L17: Y | T17: =IF($A17="",0,SUMIFS(GL_Input!$U:$U,GL_Input!$N:$N,$A17)) -> 0 | U17: =IF($A17="",0,SUMIFS(GL_Input!$W:$W,GL_Input!$N:$N,$A17)) -> 0 | V17: =ROUND(U17*N(G17),2) -> 0 | W17: =IF($A17="",0,COUNTIFS(GL_Input!$N:$N,$A17)) -> 0 | X17: e.g. interest on loans to EU group companies. Not in VIES and gives no right to deduct - affects the pro-rata.
A18: EXS | B18: Exempt supplies (domestic) | C18: Output | D18: 0 | E18: ANY | F18: N | G18: 1 | L18: Y | T18: =IF($A18="",0,SUMIFS(GL_Input!$U:$U,GL_Input!$N:$N,$A18)) -> 0 | U18: =IF($A18="",0,SUMIFS(GL_Input!$W:$W,GL_Input!$N:$N,$A18)) -> 0 | V18: =ROUND(U18*N(G18),2) -> 0 | W18: =IF($A18="",0,COUNTIFS(GL_Input!$N:$N,$A18)) -> 0 | X18: Exempt supplies (e.g. financial services, insurance, letting of immovable property, medical, education). No right to deduct related input VAT.
A19: DRCS | B19: Domestic reverse-charge sales (customer accounts for VAT) | C19: Output | D19: 0 | E19: CY | F19: N | G19: 1 | L19: Y | T19: =IF($A19="",0,SUMIFS(GL_Input!$U:$U,GL_Input!$N:$N,$A19)) -> 0 | U19: =IF($A19="",0,SUMIFS(GL_Input!$W:$W,GL_Input!$N:$N,$A19)) -> 0 | V19: =ROUND(U19*N(G19),2) -> 0 | W19: =IF($A19="",0,COUNTIFS(GL_Input!$N:$N,$A19)) -> 0 | X19: Supplies where the Cyprus customer accounts for the VAT (construction services, scrap metals, mobile phones / laptops / consoles, precious metals, etc. - s.11B/11C). Invoice without VAT, marked 'reverse charge'.
A20: P19 | B20: Domestic purchases 19% - fully recoverable | C20: Input | D20: 0.19 | E20: CY | F20: N | G20: 1 | K20: Y | M20: Y | T20: =IF($A20="",0,SUMIFS(GL_Input!$U:$U,GL_Input!$N:$N,$A20)) -> 2000 | U20: =IF($A20="",0,SUMIFS(GL_Input!$W:$W,GL_Input!$N:$N,$A20)) -> 380 | V20: =ROUND(U20*N(G20),2) -> 380 | W20: =IF($A20="",0,COUNTIFS(GL_Input!$N:$N,$A20)) -> 1 | X20: Purchases from Cyprus suppliers with a valid VAT invoice, used for taxable (or outside-scope-with-right) supplies. Includes capital assets.
A21: P9 | B21: Domestic purchases 9% - fully recoverable | C21: Input | D21: 0.09 | E21: CY | F21: N | G21: 1 | K21: Y | M21: Y | T21: =IF($A21="",0,SUMIFS(GL_Input!$U:$U,GL_Input!$N:$N,$A21)) -> 0 | U21: =IF($A21="",0,SUMIFS(GL_Input!$W:$W,GL_Input!$N:$N,$A21)) -> 0 | V21: =ROUND(U21*N(G21),2) -> 0 | W21: =IF($A21="",0,COUNTIFS(GL_Input!$N:$N,$A21)) -> 0 | X21: As P19 at 9%.
A22: P5 | B22: Domestic purchases 5% - fully recoverable | C22: Input | D22: 0.05 | E22: CY | F22: N | G22: 1 | K22: Y | M22: Y | T22: =IF($A22="",0,SUMIFS(GL_Input!$U:$U,GL_Input!$N:$N,$A22)) -> 0 | U22: =IF($A22="",0,SUMIFS(GL_Input!$W:$W,GL_Input!$N:$N,$A22)) -> 0 | V22: =ROUND(U22*N(G22),2) -> 0 | W22: =IF($A22="",0,COUNTIFS(GL_Input!$N:$N,$A22)) -> 0 | X22: As P19 at 5%.
A23: P3 | B23: Domestic purchases 3% - fully recoverable | C23: Input | D23: 0.03 | E23: CY | F23: N | G23: 1 | K23: Y | M23: Y | T23: =IF($A23="",0,SUMIFS(GL_Input!$U:$U,GL_Input!$N:$N,$A23)) -> 0 | U23: =IF($A23="",0,SUMIFS(GL_Input!$W:$W,GL_Input!$N:$N,$A23)) -> 0 | V23: =ROUND(U23*N(G23),2) -> 0 | W23: =IF($A23="",0,COUNTIFS(GL_Input!$N:$N,$A23)) -> 0 | X23: As P19 at 3%.
A24: PM19 | B24: Domestic purchases 19% - mixed use (pro-rata applies) | C24: Input | D24: 0.19 | E24: CY | F24: N | G24: =Settings!$C$10 -> 1 | K24: Y | M24: Y | T24: =IF($A24="",0,SUMIFS(GL_Input!$U:$U,GL_Input!$N:$N,$A24)) -> 0 | U24: =IF($A24="",0,SUMIFS(GL_Input!$W:$W,GL_Input!$N:$N,$A24)) -> 0 | V24: =ROUND(U24*N(G24),2) -> 0 | W24: =IF($A24="",0,COUNTIFS(GL_Input!$N:$N,$A24)) -> 0 | X24: Overheads used for both taxable and exempt activities. Recovery = pro-rata % in Settings.
A25: PB19 | B25: Domestic purchases 19% - VAT not recoverable (blocked) | C25: Input | D25: 0.19 | E25: ANY | F25: N | G25: 0 | M25: Y | T25: =IF($A25="",0,SUMIFS(GL_Input!$U:$U,GL_Input!$N:$N,$A25)) -> 300 | U25: =IF($A25="",0,SUMIFS(GL_Input!$W:$W,GL_Input!$N:$N,$A25)) -> 57 | V25: =ROUND(U25*N(G25),2) -> 0 | W25: =IF($A25="",0,COUNTIFS(GL_Input!$N:$N,$A25)) -> 1 | X25: Business entertainment, private use, saloon cars (subject to exceptions), costs for exempt supplies. Value in Box 7, no Box 4 claim.
A26: PZ | B26: Purchases with no VAT (zero-rated, exempt, non-registered supplier) | C26: Input | D26: 0 | E26: ANY | F26: N | G26: 1 | M26: Y | T26: =IF($A26="",0,SUMIFS(GL_Input!$U:$U,GL_Input!$N:$N,$A26)) -> 0 | U26: =IF($A26="",0,SUMIFS(GL_Input!$W:$W,GL_Input!$N:$N,$A26)) -> 0 | V26: =ROUND(U26*N(G26),2) -> 0 | W26: =IF($A26="",0,COUNTIFS(GL_Input!$N:$N,$A26)) -> 0 | X26: e.g. insurance, bank charges, rent without VAT, purchases from non-registered suppliers.
A27: AEG19 | B27: Acquisitions of goods from EU suppliers - 19% | C27: Input | D27: 0.19 | E27: EU | F27: N | G27: 1 | J27: Y | K27: Y | M27: Y | R27: Y | T27: =IF($A27="",0,SUMIFS(GL_Input!$U:$U,GL_Input!$N:$N,$A27)) -> 5000 | U27: =IF($A27="",0,SUMIFS(GL_Input!$W:$W,GL_Input!$N:$N,$A27)) -> 950 | V27: =ROUND(U27*N(G27),2) -> 950 | W27: =IF($A27="",0,COUNTIFS(GL_Input!$N:$N,$A27)) -> 1 | X27: Goods received from a VAT-registered EU supplier invoicing without VAT. Self-account VAT in Box 2, recover in Box 4.
A28: AEG9 | B28: Acquisitions of goods from EU suppliers - 9% | C28: Input | D28: 0.09 | E28: EU | F28: N | G28: 1 | J28: Y | K28: Y | M28: Y | R28: Y | T28: =IF($A28="",0,SUMIFS(GL_Input!$U:$U,GL_Input!$N:$N,$A28)) -> 0 | U28: =IF($A28="",0,SUMIFS(GL_Input!$W:$W,GL_Input!$N:$N,$A28)) -> 0 | V28: =ROUND(U28*N(G28),2) -> 0 | W28: =IF($A28="",0,COUNTIFS(GL_Input!$N:$N,$A28)) -> 0 | X28: As AEG19 at 9%.
A29: AEG5 | B29: Acquisitions of goods from EU suppliers - 5% | C29: Input | D29: 0.05 | E29: EU | F29: N | G29: 1 | J29: Y | K29: Y | M29: Y | R29: Y | T29: =IF($A29="",0,SUMIFS(GL_Input!$U:$U,GL_Input!$N:$N,$A29)) -> 0 | U29: =IF($A29="",0,SUMIFS(GL_Input!$W:$W,GL_Input!$N:$N,$A29)) -> 0 | V29: =ROUND(U29*N(G29),2) -> 0 | W29: =IF($A29="",0,COUNTIFS(GL_Input!$N:$N,$A29)) -> 0 | X29: As AEG19 at 5%.
A30: AEG0 | B30: Acquisitions of goods from EU suppliers - zero-rated goods | C30: Input | D30: 0 | E30: EU | F30: N | G30: 1 | M30: Y | R30: Y | T30: =IF($A30="",0,SUMIFS(GL_Input!$U:$U,GL_Input!$N:$N,$A30)) -> 0 | U30: =IF($A30="",0,SUMIFS(GL_Input!$W:$W,GL_Input!$N:$N,$A30)) -> 0 | V30: =ROUND(U30*N(G30),2) -> 0 | W30: =IF($A30="",0,COUNTIFS(GL_Input!$N:$N,$A30)) -> 0 | X30: Zero-rated goods acquired from the EU (value only).
A31: AES19 | B31: Services received from EU suppliers - reverse charge 19% | C31: Input | D31: 0.19 | E31: EU | F31: N | G31: 1 | I31: Y | K31: Y | L31: Y | M31: Y | S31: Y | T31: =IF($A31="",0,SUMIFS(GL_Input!$U:$U,GL_Input!$N:$N,$A31)) -> 15000 | U31: =IF($A31="",0,SUMIFS(GL_Input!$W:$W,GL_Input!$N:$N,$A31)) -> 2850 | V31: =ROUND(U31*N(G31),2) -> 2850 | W31: =IF($A31="",0,COUNTIFS(GL_Input!$N:$N,$A31)) -> 1 | X31: B2B services from EU suppliers (including inter-company recharges, management fees, licences, IT from EU group companies). VAT in Box 1 and Box 4; value in Boxes 6, 7 and 11B.
A32: AESM | B32: Services received from EU suppliers - reverse charge, mixed use | C32: Input | D32: 0.19 | E32: EU | F32: N | G32: =Settings!$C$10 -> 1 | I32: Y | K32: Y | L32: Y | M32: Y | S32: Y | T32: =IF($A32="",0,SUMIFS(GL_Input!$U:$U,GL_Input!$N:$N,$A32)) -> 0 | U32: =IF($A32="",0,SUMIFS(GL_Input!$W:$W,GL_Input!$N:$N,$A32)) -> 0 | V32: =ROUND(U32*N(G32),2) -> 0 | W32: =IF($A32="",0,COUNTIFS(GL_Input!$N:$N,$A32)) -> 0 | X32: As AES19 but input recovery limited to the pro-rata % in Settings.
A33: A3S19 | B33: Services received from non-EU suppliers - reverse charge 19% | C33: Input | D33: 0.19 | E33: 3RD | F33: N | G33: 1 | I33: Y | K33: Y | L33: Y | M33: Y | T33: =IF($A33="",0,SUMIFS(GL_Input!$U:$U,GL_Input!$N:$N,$A33)) -> 1030.13 | U33: =IF($A33="",0,SUMIFS(GL_Input!$W:$W,GL_Input!$N:$N,$A33)) -> 195.72 | V33: =ROUND(U33*N(G33),2) -> 195.72 | W33: =IF($A33="",0,COUNTIFS(GL_Input!$N:$N,$A33)) -> 1 | X33: B2B services from third-country suppliers (e.g. US software, UK consultancy, inter-company charges from non-EU group companies). Not in Box 11B.
A34: A3SM | B34: Services received from non-EU suppliers - reverse charge, mixed use | C34: Input | D34: 0.19 | E34: 3RD | F34: N | G34: =Settings!$C$10 -> 1 | I34: Y | K34: Y | L34: Y | M34: Y | T34: =IF($A34="",0,SUMIFS(GL_Input!$U:$U,GL_Input!$N:$N,$A34)) -> 0 | U34: =IF($A34="",0,SUMIFS(GL_Input!$W:$W,GL_Input!$N:$N,$A34)) -> 0 | V34: =ROUND(U34*N(G34),2) -> 0 | W34: =IF($A34="",0,COUNTIFS(GL_Input!$N:$N,$A34)) -> 0 | X34: As A3S19 but input recovery limited to the pro-rata % in Settings.
A35: DRCP | B35: Domestic reverse-charge purchases 19% (we account for the VAT) | C35: Input | D35: 0.19 | E35: CY | F35: N | G35: 1 | I35: Y | K35: Y | M35: Y | T35: =IF($A35="",0,SUMIFS(GL_Input!$U:$U,GL_Input!$N:$N,$A35)) -> 0 | U35: =IF($A35="",0,SUMIFS(GL_Input!$W:$W,GL_Input!$N:$N,$A35)) -> 0 | V35: =ROUND(U35*N(G35),2) -> 0 | W35: =IF($A35="",0,COUNTIFS(GL_Input!$N:$N,$A35)) -> 0 | X35: Purchases under s.11B/11C (construction, scrap, phones/laptops, etc.) invoiced without VAT by a Cyprus supplier.
A36: IMP | B36: Imports of goods from third countries (value) | C36: Input | D36: 0 | E36: 3RD | F36: N | G36: 1 | M36: Y | T36: =IF($A36="",0,SUMIFS(GL_Input!$U:$U,GL_Input!$N:$N,$A36)) -> 3433.77 | U36: =IF($A36="",0,SUMIFS(GL_Input!$W:$W,GL_Input!$N:$N,$A36)) -> 0 | V36: =ROUND(U36*N(G36),2) -> 0 | W36: =IF($A36="",0,COUNTIFS(GL_Input!$N:$N,$A36)) -> 1 | X36: Value of imported goods. The import VAT paid to Customs is posted separately with code IVAT.
A37: IVAT | B37: Import VAT paid to / deferred with Customs (line is the VAT) | C37: Input | D37: 0 | E37: ANY | F37: Y | G37: 1 | K37: Y | T37: =IF($A37="",0,SUMIFS(GL_Input!$U:$U,GL_Input!$N:$N,$A37)) -> 700 | U37: =IF($A37="",0,SUMIFS(GL_Input!$W:$W,GL_Input!$N:$N,$A37)) -> 700 | V37: =ROUND(U37*N(G37),2) -> 700 | W37: =IF($A37="",0,COUNTIFS(GL_Input!$N:$N,$A37)) -> 1 | X37: Map the 'Import VAT' account here. The GL line amount itself is the VAT claimed in Box 4 (needs the customs import declaration).
A38: FOR | B38: Foreign VAT incurred abroad (not on the Cyprus return) | C38: None | D38: 0 | E38: ANY | F38: N | G38: 0 | T38: =IF($A38="",0,SUMIFS(GL_Input!$U:$U,GL_Input!$N:$N,$A38)) -> 0 | U38: =IF($A38="",0,SUMIFS(GL_Input!$W:$W,GL_Input!$N:$N,$A38)) -> 0 | V38: =ROUND(U38*N(G38),2) -> 0 | W38: =IF($A38="",0,COUNTIFS(GL_Input!$N:$N,$A38)) -> 0 | X38: e.g. hotels or fuel abroad. Reclaim through the EU VAT refund procedure (Directive 2008/9) or the foreign country's procedure.
A39: NR | B39: Not reportable on the VAT return | C39: None | D39: 0 | E39: ANY | F39: N | G39: 0 | T39: =IF($A39="",0,SUMIFS(GL_Input!$U:$U,GL_Input!$N:$N,$A39)) -> 0 | U39: =IF($A39="",0,SUMIFS(GL_Input!$W:$W,GL_Input!$N:$N,$A39)) -> 0 | V39: =ROUND(U39*N(G39),2) -> 0 | W39: =IF($A39="",0,COUNTIFS(GL_Input!$N:$N,$A39)) -> 4 | X39: Salaries, social insurance, depreciation, dividends, bank transfers, loans principal, balance-sheet movements, VAT control accounts, corporation tax.
T40: =IF($A40="",0,SUMIFS(GL_Input!$U:$U,GL_Input!$N:$N,$A40)) -> 0 | U40: =IF($A40="",0,SUMIFS(GL_Input!$W:$W,GL_Input!$N:$N,$A40)) -> 0 | V40: =ROUND(U40*N(G40),2) -> 0 | W40: =IF($A40="",0,COUNTIFS(GL_Input!$N:$N,$A40)) -> 0
T41: =IF($A41="",0,SUMIFS(GL_Input!$U:$U,GL_Input!$N:$N,$A41)) -> 0 | U41: =IF($A41="",0,SUMIFS(GL_Input!$W:$W,GL_Input!$N:$N,$A41)) -> 0 | V41: =ROUND(U41*N(G41),2) -> 0 | W41: =IF($A41="",0,COUNTIFS(GL_Input!$N:$N,$A41)) -> 0
T42: =IF($A42="",0,SUMIFS(GL_Input!$U:$U,GL_Input!$N:$N,$A42)) -> 0 | U42: =IF($A42="",0,SUMIFS(GL_Input!$W:$W,GL_Input!$N:$N,$A42)) -> 0 | V42: =ROUND(U42*N(G42),2) -> 0 | W42: =IF($A42="",0,COUNTIFS(GL_Input!$N:$N,$A42)) -> 0
T43: =IF($A43="",0,SUMIFS(GL_Input!$U:$U,GL_Input!$N:$N,$A43)) -> 0 | U43: =IF($A43="",0,SUMIFS(GL_Input!$W:$W,GL_Input!$N:$N,$A43)) -> 0 | V43: =ROUND(U43*N(G43),2) -> 0 | W43: =IF($A43="",0,COUNTIFS(GL_Input!$N:$N,$A43)) -> 0
T44: =IF($A44="",0,SUMIFS(GL_Input!$U:$U,GL_Input!$N:$N,$A44)) -> 0 | U44: =IF($A44="",0,SUMIFS(GL_Input!$W:$W,GL_Input!$N:$N,$A44)) -> 0 | V44: =ROUND(U44*N(G44),2) -> 0 | W44: =IF($A44="",0,COUNTIFS(GL_Input!$N:$N,$A44)) -> 0
T45: =IF($A45="",0,SUMIFS(GL_Input!$U:$U,GL_Input!$N:$N,$A45)) -> 0 | U45: =IF($A45="",0,SUMIFS(GL_Input!$W:$W,GL_Input!$N:$N,$A45)) -> 0 | V45: =ROUND(U45*N(G45),2) -> 0 | W45: =IF($A45="",0,COUNTIFS(GL_Input!$N:$N,$A45)) -> 0
T46: =IF($A46="",0,SUMIFS(GL_Input!$U:$U,GL_Input!$N:$N,$A46)) -> 0 | U46: =IF($A46="",0,SUMIFS(GL_Input!$W:$W,GL_Input!$N:$N,$A46)) -> 0 | V46: =ROUND(U46*N(G46),2) -> 0 | W46: =IF($A46="",0,COUNTIFS(GL_Input!$N:$N,$A46)) -> 0
T47: =IF($A47="",0,SUMIFS(GL_Input!$U:$U,GL_Input!$N:$N,$A47)) -> 0 | U47: =IF($A47="",0,SUMIFS(GL_Input!$W:$W,GL_Input!$N:$N,$A47)) -> 0 | V47: =ROUND(U47*N(G47),2) -> 0 | W47: =IF($A47="",0,COUNTIFS(GL_Input!$N:$N,$A47)) -> 0
T48: =IF($A48="",0,SUMIFS(GL_Input!$U:$U,GL_Input!$N:$N,$A48)) -> 0 | U48: =IF($A48="",0,SUMIFS(GL_Input!$W:$W,GL_Input!$N:$N,$A48)) -> 0 | V48: =ROUND(U48*N(G48),2) -> 0 | W48: =IF($A48="",0,COUNTIFS(GL_Input!$N:$N,$A48)) -> 0
T49: =IF($A49="",0,SUMIFS(GL_Input!$U:$U,GL_Input!$N:$N,$A49)) -> 0 | U49: =IF($A49="",0,SUMIFS(GL_Input!$W:$W,GL_Input!$N:$N,$A49)) -> 0 | V49: =ROUND(U49*N(G49),2) -> 0 | W49: =IF($A49="",0,COUNTIFS(GL_Input!$N:$N,$A49)) -> 0
T50: =IF($A50="",0,SUMIFS(GL_Input!$U:$U,GL_Input!$N:$N,$A50)) -> 0 | U50: =IF($A50="",0,SUMIFS(GL_Input!$W:$W,GL_Input!$N:$N,$A50)) -> 0 | V50: =ROUND(U50*N(G50),2) -> 0 | W50: =IF($A50="",0,COUNTIFS(GL_Input!$N:$N,$A50)) -> 0
T51: =IF($A51="",0,SUMIFS(GL_Input!$U:$U,GL_Input!$N:$N,$A51)) -> 0 | U51: =IF($A51="",0,SUMIFS(GL_Input!$W:$W,GL_Input!$N:$N,$A51)) -> 0 | V51: =ROUND(U51*N(G51),2) -> 0 | W51: =IF($A51="",0,COUNTIFS(GL_Input!$N:$N,$A51)) -> 0
... T80: =IF($A80="",0,SUMIFS(GL_Input!$U:$U,GL_Input!$N:$N,$A80)) -> 0 | U80: =IF($A80="",0,SUMIFS(GL_Input!$W:$W,GL_Input!$N:$N,$A80)) -> 0 | V80: =ROUND(U80*N(G80),2) -> 0 | W80: =IF($A80="",0,COUNTIFS(GL_Input!$N:$N,$A80)) -> 0
B81: TOTAL | T81: =SUM(T5:T80) -> 106518.49 | U81: =SUM(U5:U80) -> 7032.72 | V81: =SUM(V5:V80) -> 6975.72 | W81: =SUM(W5:W80) -> 16

Sheet FX_Rates
A1: FX_Rates - quarterly average euro reference rates (units of currency per 1 EUR)
A2: Average of the ECB daily reference rates in FX_Daily (the same rates the Central Bank of Cyprus publishes). Column C overrides the average.
A4: Currency | B4: Quarter average (FX_Daily) | C4: Manual override | D4: Rate used | E4: No. of daily rates | F4: First date | G4: Last date | H4: Source / date retrieved
A5: USD | B5: =IFERROR(ROUND(AVERAGE(FX_Daily!$B$5:$B$2000),4),"") -> 1.1649 | D5: =IF(C5<>"",C5,B5) -> 1.1649 | E5: =COUNT(FX_Daily!$B$5:$B$2000) -> 3 | F5: =IF(E5=0,"",MIN(FX_Daily!$A$5:$A$2000)) -> 46204 | G5: =IF(E5=0,"",MAX(FX_Daily!$A$5:$A$2000)) -> 46266 | H5: EXAMPLE - run the fx command to download the real rates
A6: GBP | B6: =IFERROR(ROUND(AVERAGE(FX_Daily!$C$5:$C$2000),4),"") -> 0.865 | D6: =IF(C6<>"",C6,B6) -> 0.865 | E6: =COUNT(FX_Daily!$C$5:$C$2000) -> 3 | F6: =IF(E6=0,"",MIN(FX_Daily!$A$5:$A$2000)) -> 46204 | G6: =IF(E6=0,"",MAX(FX_Daily!$A$5:$A$2000)) -> 46266 | H6: EXAMPLE - run the fx command to download the real rates

Sheet FX_Daily
A1: FX_Daily - ECB euro foreign exchange reference rates (units per 1 EUR)
A2: Written by the fx command. Business days only (no rates on weekends / TARGET holidays).
A4: Date | B4: USD | C4: GBP
A5: 46204 | B5: 1.1702 | C5: 0.8601
A6: 46237 | B6: 1.1655 | C6: 0.8662
A7: 46266 | B7: 1.159 | C7: 0.8687

Sheet VAT_Return
A1: VAT 4 - Cyprus VAT return
A2: Transfer the amounts in column C to the VAT 4 return on the Tax For All (TFA) portal. Amounts in EUR.
A3: Company | B3: =Settings!$C$4 -> Example Holdings Ltd
A4: VAT number | B4: =Settings!$C$5 -> 10000000X
A5: Period from | B5: =Settings!$C$8 -> 46204
A6: Period to | B6: =Settings!$C$9 -> 46295
A7: Return and payment due by | B7: =Settings!$C$13 -> 46336
A9: Box | B9: Description (VAT 4) | C9: Amount EUR | D9: What this box must include | E9: Fed by VAT codes
A10: 1 | B10: VAT due in this period on sales and other outputs | C10: =SUMIFS(VAT_Codes!$U$5:$U$80,VAT_Codes!$I$5:$I$80,"Y") -> 4945.72 | D10: Output VAT on domestic taxable supplies (19%, 9%, 5%, 3%) PLUS the VAT you self-account under the reverse charge on services received from abroad (EU and non-EU) and on domestic reverse-charge purchases. Credit notes issued reduce this box. | E10: S19, S9, S5, S3, AES19, AESM, A3S19, A3SM, DRCP
A11: 2 | B11: VAT due in this period on acquisitions from other EU Member States | C11: =SUMIFS(VAT_Codes!$U$5:$U$80,VAT_Codes!$J$5:$J$80,"Y") -> 950 | D11: VAT self-accounted on goods (and related services) acquired from VAT-registered suppliers in other EU member states. | E11: AEG19, AEG9, AEG5
A12: 3 | B12: Total VAT due (sum of Boxes 1 and 2) | C12: =C10+C11 -> 5895.72 | D12: Calculated: Box 1 + Box 2. | E12: Box 1 + Box 2
A13: 4 | B13: VAT reclaimed in this period on purchases and other inputs (including acquisitions from the EU) | C13: =SUMIFS(VAT_Codes!$V$5:$V$80,VAT_Codes!$K$5:$K$80,"Y") -> 5075.72 | D13: Deductible input VAT on domestic purchases and capital goods, import VAT paid to Customs, and the reverse-charge VAT of Boxes 1 and 2 to the extent it is deductible. Exclude blocked VAT (entertainment, private use, saloon cars, VAT on exempt activities) and foreign VAT. Mixed-use costs at the pro-rata %. | E13: P19, P9, P5, P3, PM19 (pro-rata), AEG*, AES19, AESM (pro-rata), A3S19, A3SM (pro-rata), DRCP, IVAT
A14: 5 | B14: Net VAT to be paid or reclaimed (difference between Boxes 3 and 4) | C14: =C12-C13 -> 820 | D14: Calculated: Box 3 - Box 4. Positive = payable by the due date; negative = credit carried forward / refund claim. | E14: Box 3 - Box 4
A15: 6 | B15: Total value of sales and other outputs excluding any VAT | C15: =SUMIFS(VAT_Codes!$T$5:$T$80,VAT_Codes!$L$5:$L$80,"Y") -> 95084.72 | D15: All outputs excluding VAT: domestic taxable, zero-rated, exempt, exports, EU supplies, outside-scope supplies, domestic reverse-charge sales. Must include the values in Boxes 8A, 8B, 9, 10 and 11B, and the value of services received from outside the EU under the reverse charge. | E15: S*, Z0, EXPG, EUG, EUS, TRI, OS3, OSS, FIN3, FINEU, EXS, DRCS, AES*, A3S*
A16: 7 | B16: Total value of purchases and other inputs excluding any VAT | C16: =SUMIFS(VAT_Codes!$T$5:$T$80,VAT_Codes!$M$5:$M$80,"Y") -> 26763.9 | D16: All purchases and expenses (including capital goods) excluding VAT: domestic, imports, EU acquisitions of goods (11A), services received from abroad (11B and non-EU). Exclude salaries, depreciation, dividends, loans and other non-supplies. | E16: P*, PM19, PB19, PZ, AEG*, AES*, A3S*, DRCP, IMP
A17: 8A | B17: Total value of supplies of goods to other EU Member States | C17: =SUMIFS(VAT_Codes!$T$5:$T$80,VAT_Codes!$N$5:$N$80,"Y") -> 8000 | D17: Intra-community supplies of goods to VAT-registered customers in other member states (0%). Must agree with the goods lines of the VIES statements for the quarter. | E17: EUG
A18: 8B | B18: Total value of services supplied to other EU Member States (general rule) | C18: =SUMIFS(VAT_Codes!$T$5:$T$80,VAT_Codes!$O$5:$O$80,"Y") -> 25000 | D18: B2B services to EU taxable persons where the customer accounts for the VAT (reverse charge). Must agree with the services lines of the VIES statements. | E18: EUS
A19: 9 | B19: Total value of outputs at zero rate (other than those in Boxes 8A and 8B) | C19: =SUMIFS(VAT_Codes!$T$5:$T$80,VAT_Codes!$P$5:$P$80,"Y") -> 10301.31 | D19: Exports of goods outside the EU and other zero-rated supplies. | E19: EXPG, Z0
A20: 10 | B20: Total value of out-of-scope sales with the right to deduct input VAT | C20: =SUMIFS(VAT_Codes!$T$5:$T$80,VAT_Codes!$Q$5:$Q$80,"Y") -> 25753.28 | D20: Services to non-EU customers whose place of supply is outside Cyprus, financial/insurance services to non-EU recipients, triangular transactions, OSS sales. | E20: OS3, FIN3, TRI, OSS
A21: 11A | B21: Total value of acquisitions of goods and related services from other EU Member States | C21: =SUMIFS(VAT_Codes!$T$5:$T$80,VAT_Codes!$R$5:$R$80,"Y") -> 5000 | D21: Value (excluding VAT) of goods acquired from EU suppliers. Also included in Box 7. | E21: AEG19, AEG9, AEG5, AEG0
A22: 11B | B22: Total value of services received from other EU Member States (reverse charge) | C22: =SUMIFS(VAT_Codes!$T$5:$T$80,VAT_Codes!$S$5:$S$80,"Y") -> 15000 | D22: Value (excluding VAT) of B2B services received from EU suppliers. Also included in Boxes 6 and 7. | E22: AES19, AESM
B24: Result | C24: =IF(C14>0,"VAT PAYABLE",IF(C14<0,"VAT CREDIT","NIL")) -> VAT PAYABLE | D24: Payable: pay through TFA / JCC by the due date. Credit: carried forward, or refund claim where conditions are met.
B25: Exceptions outstanding (see Checks) | C25: =Checks!C23 -> 1 | D25: Must be 0 before filing.
A27: Sign-off
B28: Prepared by / date
B29: Reviewed by / date
B30: Submitted on TFA (date / ref.)
B31: Paid (date / amount)

Sheet IC_Analysis
A1: IC_Analysis - inter-company vs third-party, Cyprus / EU / third countries (return value EUR, excl. VAT)
A2: Use it to confirm every inter-company flow has the right treatment: EU group = EUS / AES19, non-EU group = OS3 / A3S19.
A4: Code | B4: Description | C4: Nature | D4: Inter-company - CY | E4: Inter-company - EU | F4: Inter-company - 3RD | G4: Third party - CY | H4: Third party - EU | I4: Third party - 3RD | J4: No country | K4: Total | L4: Agrees to VAT_Codes
A5: =IF(VAT_Codes!A5="","",VAT_Codes!A5) -> S19 | B5: =IF(VAT_Codes!B5="","",VAT_Codes!B5) -> Domestic sales - standard rate 19% | C5: =IF(VAT_Codes!C5="","",VAT_Codes!C5) -> Output | D5: =IF($A5="",0,SUMIFS(GL_Input!$U:$U,GL_Input!$N:$N,$A5,GL_Input!$Q:$Q,"Y",GL_Input!$P:$P,"CY")) -> 0 | E5: =IF($A5="",0,SUMIFS(GL_Input!$U:$U,GL_Input!$N:$N,$A5,GL_Input!$Q:$Q,"Y",GL_Input!$P:$P,"EU")) -> 0 | F5: =IF($A5="",0,SUMIFS(GL_Input!$U:$U,GL_Input!$N:$N,$A5,GL_Input!$Q:$Q,"Y",GL_Input!$P:$P,"3RD")) -> 0 | G5: =IF($A5="",0,SUMIFS(GL_Input!$U:$U,GL_Input!$N:$N,$A5,GL_Input!$Q:$Q,"N",GL_Input!$P:$P,"CY")) -> 10000 | H5: =IF($A5="",0,SUMIFS(GL_Input!$U:$U,GL_Input!$N:$N,$A5,GL_Input!$Q:$Q,"N",GL_Input!$P:$P,"EU")) -> 0 | I5: =IF($A5="",0,SUMIFS(GL_Input!$U:$U,GL_Input!$N:$N,$A5,GL_Input!$Q:$Q,"N",GL_Input!$P:$P,"3RD")) -> 0 | J5: =IF($A5="",0,SUMIFS(GL_Input!$U:$U,GL_Input!$N:$N,$A5,GL_Input!$P:$P,"")) -> 0 | K5: =SUM(D5:J5) -> 10000 | L5: =IF(ROUND(K5-VAT_Codes!T5,2)=0,"OK","CHECK") -> OK
A6: =IF(VAT_Codes!A6="","",VAT_Codes!A6) -> S9 | B6: =IF(VAT_Codes!B6="","",VAT_Codes!B6) -> Domestic sales - reduced rate 9% | C6: =IF(VAT_Codes!C6="","",VAT_Codes!C6) -> Output | D6: =IF($A6="",0,SUMIFS(GL_Input!$U:$U,GL_Input!$N:$N,$A6,GL_Input!$Q:$Q,"Y",GL_Input!$P:$P,"CY")) -> 0 | E6: =IF($A6="",0,SUMIFS(GL_Input!$U:$U,GL_Input!$N:$N,$A6,GL_Input!$Q:$Q,"Y",GL_Input!$P:$P,"EU")) -> 0 | F6: =IF($A6="",0,SUMIFS(GL_Input!$U:$U,GL_Input!$N:$N,$A6,GL_Input!$Q:$Q,"Y",GL_Input!$P:$P,"3RD")) -> 0 | G6: =IF($A6="",0,SUMIFS(GL_Input!$U:$U,GL_Input!$N:$N,$A6,GL_Input!$Q:$Q,"N",GL_Input!$P:$P,"CY")) -> 0 | H6: =IF($A6="",0,SUMIFS(GL_Input!$U:$U,GL_Input!$N:$N,$A6,GL_Input!$Q:$Q,"N",GL_Input!$P:$P,"EU")) -> 0 | I6: =IF($A6="",0,SUMIFS(GL_Input!$U:$U,GL_Input!$N:$N,$A6,GL_Input!$Q:$Q,"N",GL_Input!$P:$P,"3RD")) -> 0 | J6: =IF($A6="",0,SUMIFS(GL_Input!$U:$U,GL_Input!$N:$N,$A6,GL_Input!$P:$P,"")) -> 0 | K6: =SUM(D6:J6) -> 0 | L6: =IF(ROUND(K6-VAT_Codes!T6,2)=0,"OK","CHECK") -> OK
A7: =IF(VAT_Codes!A7="","",VAT_Codes!A7) -> S5 | B7: =IF(VAT_Codes!B7="","",VAT_Codes!B7) -> Domestic sales - reduced rate 5% | C7: =IF(VAT_Codes!C7="","",VAT_Codes!C7) -> Output | D7: =IF($A7="",0,SUMIFS(GL_Input!$U:$U,GL_Input!$N:$N,$A7,GL_Input!$Q:$Q,"Y",GL_Input!$P:$P,"CY")) -> 0 | E7: =IF($A7="",0,SUMIFS(GL_Input!$U:$U,GL_Input!$N:$N,$A7,GL_Input!$Q:$Q,"Y",GL_Input!$P:$P,"EU")) -> 0 | F7: =IF($A7="",0,SUMIFS(GL_Input!$U:$U,GL_Input!$N:$N,$A7,GL_Input!$Q:$Q,"Y",GL_Input!$P:$P,"3RD")) -> 0 | G7: =IF($A7="",0,SUMIFS(GL_Input!$U:$U,GL_Input!$N:$N,$A7,GL_Input!$Q:$Q,"N",GL_Input!$P:$P,"CY")) -> 0 | H7: =IF($A7="",0,SUMIFS(GL_Input!$U:$U,GL_Input!$N:$N,$A7,GL_Input!$Q:$Q,"N",GL_Input!$P:$P,"EU")) -> 0 | I7: =IF($A7="",0,SUMIFS(GL_Input!$U:$U,GL_Input!$N:$N,$A7,GL_Input!$Q:$Q,"N",GL_Input!$P:$P,"3RD")) -> 0 | J7: =IF($A7="",0,SUMIFS(GL_Input!$U:$U,GL_Input!$N:$N,$A7,GL_Input!$P:$P,"")) -> 0 | K7: =SUM(D7:J7) -> 0 | L7: =IF(ROUND(K7-VAT_Codes!T7,2)=0,"OK","CHECK") -> OK
A8: =IF(VAT_Codes!A8="","",VAT_Codes!A8) -> S3 | B8: =IF(VAT_Codes!B8="","",VAT_Codes!B8) -> Domestic sales - super-reduced rate 3% | C8: =IF(VAT_Codes!C8="","",VAT_Codes!C8) -> Output | D8: =IF($A8="",0,SUMIFS(GL_Input!$U:$U,GL_Input!$N:$N,$A8,GL_Input!$Q:$Q,"Y",GL_Input!$P:$P,"CY")) -> 0 | E8: =IF($A8="",0,SUMIFS(GL_Input!$U:$U,GL_Input!$N:$N,$A8,GL_Input!$Q:$Q,"Y",GL_Input!$P:$P,"EU")) -> 0 | F8: =IF($A8="",0,SUMIFS(GL_Input!$U:$U,GL_Input!$N:$N,$A8,GL_Input!$Q:$Q,"Y",GL_Input!$P:$P,"3RD")) -> 0 | G8: =IF($A8="",0,SUMIFS(GL_Input!$U:$U,GL_Input!$N:$N,$A8,GL_Input!$Q:$Q,"N",GL_Input!$P:$P,"CY")) -> 0 | H8: =IF($A8="",0,SUMIFS(GL_Input!$U:$U,GL_Input!$N:$N,$A8,GL_Input!$Q:$Q,"N",GL_Input!$P:$P,"EU")) -> 0 | I8: =IF($A8="",0,SUMIFS(GL_Input!$U:$U,GL_Input!$N:$N,$A8,GL_Input!$Q:$Q,"N",GL_Input!$P:$P,"3RD")) -> 0 | J8: =IF($A8="",0,SUMIFS(GL_Input!$U:$U,GL_Input!$N:$N,$A8,GL_Input!$P:$P,"")) -> 0 | K8: =SUM(D8:J8) -> 0 | L8: =IF(ROUND(K8-VAT_Codes!T8,2)=0,"OK","CHECK") -> OK
A9: =IF(VAT_Codes!A9="","",VAT_Codes!A9) -> Z0 | B9: =IF(VAT_Codes!B9="","",VAT_Codes!B9) -> Domestic zero-rated supplies (not exports) | C9: =IF(VAT_Codes!C9="","",VAT_Codes!C9) -> Output | D9: =IF($A9="",0,SUMIFS(GL_Input!$U:$U,GL_Input!$N:$N,$A9,GL_Input!$Q:$Q,"Y",GL_Input!$P:$P,"CY")) -> 0 | E9: =IF($A9="",0,SUMIFS(GL_Input!$U:$U,GL_Input!$N:$N,$A9,GL_Input!$Q:$Q,"Y",GL_Input!$P:$P,"EU")) -> 0 | F9: =IF($A9="",0,SUMIFS(GL_Input!$U:$U,GL_Input!$N:$N,$A9,GL_Input!$Q:$Q,"Y",GL_Input!$P:$P,"3RD")) -> 0 | G9: =IF($A9="",0,SUMIFS(GL_Input!$U:$U,GL_Input!$N:$N,$A9,GL_Input!$Q:$Q,"N",GL_Input!$P:$P,"CY")) -> 0 | H9: =IF($A9="",0,SUMIFS(GL_Input!$U:$U,GL_Input!$N:$N,$A9,GL_Input!$Q:$Q,"N",GL_Input!$P:$P,"EU")) -> 0 | I9: =IF($A9="",0,SUMIFS(GL_Input!$U:$U,GL_Input!$N:$N,$A9,GL_Input!$Q:$Q,"N",GL_Input!$P:$P,"3RD")) -> 0 | J9: =IF($A9="",0,SUMIFS(GL_Input!$U:$U,GL_Input!$N:$N,$A9,GL_Input!$P:$P,"")) -> 0 | K9: =SUM(D9:J9) -> 0 | L9: =IF(ROUND(K9-VAT_Codes!T9,2)=0,"OK","CHECK") -> OK
A10: =IF(VAT_Codes!A10="","",VAT_Codes!A10) -> EXPG | B10: =IF(VAT_Codes!B10="","",VAT_Codes!B10) -> Exports of goods to third countries | C10: =IF(VAT_Codes!C10="","",VAT_Codes!C10) -> Output | D10: =IF($A10="",0,SUMIFS(GL_Input!$U:$U,GL_Input!$N:$N,$A10,GL_Input!$Q:$Q,"Y",GL_Input!$P:$P,"CY")) -> 0 | E10: =IF($A10="",0,SUMIFS(GL_Input!$U:$U,GL_Input!$N:$N,$A10,GL_Input!$Q:$Q,"Y",GL_Input!$P:$P,"EU")) -> 0 | F10: =IF($A10="",0,SUMIFS(GL_Input!$U:$U,GL_Input!$N:$N,$A10,GL_Input!$Q:$Q,"Y",GL_Input!$P:$P,"3RD")) -> 0 | G10: =IF($A10="",0,SUMIFS(GL_Input!$U:$U,GL_Input!$N:$N,$A10,GL_Input!$Q:$Q,"N",GL_Input!$P:$P,"CY")) -> 0 | H10: =IF($A10="",0,SUMIFS(GL_Input!$U:$U,GL_Input!$N:$N,$A10,GL_Input!$Q:$Q,"N",GL_Input!$P:$P,"EU")) -> 0 | I10: =IF($A10="",0,SUMIFS(GL_Input!$U:$U,GL_Input!$N:$N,$A10,GL_Input!$Q:$Q,"N",GL_Input!$P:$P,"3RD")) -> 10301.31 | J10: =IF($A10="",0,SUMIFS(GL_Input!$U:$U,GL_Input!$N:$N,$A10,GL_Input!$P:$P,"")) -> 0 | K10: =SUM(D10:J10) -> 10301.31 | L10: =IF(ROUND(K10-VAT_Codes!T10,2)=0,"OK","CHECK") -> OK
A11: =IF(VAT_Codes!A11="","",VAT_Codes!A11) -> EUG | B11: =IF(VAT_Codes!B11="","",VAT_Codes!B11) -> Intra-EU supplies of goods (B2B) | C11: =IF(VAT_Codes!C11="","",VAT_Codes!C11) -> Output | D11: =IF($A11="",0,SUMIFS(GL_Input!$U:$U,GL_Input!$N:$N,$A11,GL_Input!$Q:$Q,"Y",GL_Input!$P:$P,"CY")) -> 0 | E11: =IF($A11="",0,SUMIFS(GL_Input!$U:$U,GL_Input!$N:$N,$A11,GL_Input!$Q:$Q,"Y",GL_Input!$P:$P,"EU")) -> 0 | F11: =IF($A11="",0,SUMIFS(GL_Input!$U:$U,GL_Input!$N:$N,$A11,GL_Input!$Q:$Q,"Y",GL_Input!$P:$P,"3RD")) -> 0 | G11: =IF($A11="",0,SUMIFS(GL_Input!$U:$U,GL_Input!$N:$N,$A11,GL_Input!$Q:$Q,"N",GL_Input!$P:$P,"CY")) -> 0 | H11: =IF($A11="",0,SUMIFS(GL_Input!$U:$U,GL_Input!$N:$N,$A11,GL_Input!$Q:$Q,"N",GL_Input!$P:$P,"EU")) -> 8000 | I11: =IF($A11="",0,SUMIFS(GL_Input!$U:$U,GL_Input!$N:$N,$A11,GL_Input!$Q:$Q,"N",GL_Input!$P:$P,"3RD")) -> 0 | J11: =IF($A11="",0,SUMIFS(GL_Input!$U:$U,GL_Input!$N:$N,$A11,GL_Input!$P:$P,"")) -> 0 | K11: =SUM(D11:J11) -> 8000 | L11: =IF(ROUND(K11-VAT_Codes!T11,2)=0,"OK","CHECK") -> OK
A12: =IF(VAT_Codes!A12="","",VAT_Codes!A12) -> EUS | B12: =IF(VAT_Codes!B12="","",VAT_Codes!B12) -> Services to EU taxable persons (general rule - reverse charge by customer) | C12: =IF(VAT_Codes!C12="","",VAT_Codes!C12) -> Output | D12: =IF($A12="",0,SUMIFS(GL_Input!$U:$U,GL_Input!$N:$N,$A12,GL_Input!$Q:$Q,"Y",GL_Input!$P:$P,"CY")) -> 0 | E12: =IF($A12="",0,SUMIFS(GL_Input!$U:$U,GL_Input!$N:$N,$A12,GL_Input!$Q:$Q,"Y",GL_Input!$P:$P,"EU")) -> 25000 | F12: =IF($A12="",0,SUMIFS(GL_Input!$U:$U,GL_Input!$N:$N,$A12,GL_Input!$Q:$Q,"Y",GL_Input!$P:$P,"3RD")) -> 0 | G12: =IF($A12="",0,SUMIFS(GL_Input!$U:$U,GL_Input!$N:$N,$A12,GL_Input!$Q:$Q,"N",GL_Input!$P:$P,"CY")) -> 0 | H12: =IF($A12="",0,SUMIFS(GL_Input!$U:$U,GL_Input!$N:$N,$A12,GL_Input!$Q:$Q,"N",GL_Input!$P:$P,"EU")) -> 0 | I12: =IF($A12="",0,SUMIFS(GL_Input!$U:$U,GL_Input!$N:$N,$A12,GL_Input!$Q:$Q,"N",GL_Input!$P:$P,"3RD")) -> 0 | J12: =IF($A12="",0,SUMIFS(GL_Input!$U:$U,GL_Input!$N:$N,$A12,GL_Input!$P:$P,"")) -> 0 | K12: =SUM(D12:J12) -> 25000 | L12: =IF(ROUND(K12-VAT_Codes!T12,2)=0,"OK","CHECK") -> OK
A13: =IF(VAT_Codes!A13="","",VAT_Codes!A13) -> TRI | B13: =IF(VAT_Codes!B13="","",VAT_Codes!B13) -> Triangular transactions (Cyprus as intermediary) | C13: =IF(VAT_Codes!C13="","",VAT_Codes!C13) -> Output | D13: =IF($A13="",0,SUMIFS(GL_Input!$U:$U,GL_Input!$N:$N,$A13,GL_Input!$Q:$Q,"Y",GL_Input!$P:$P,"CY")) -> 0 | E13: =IF($A13="",0,SUMIFS(GL_Input!$U:$U,GL_Input!$N:$N,$A13,GL_Input!$Q:$Q,"Y",GL_Input!$P:$P,"EU")) -> 0 | F13: =IF($A13="",0,SUMIFS(GL_Input!$U:$U,GL_Input!$N:$N,$A13,GL_Input!$Q:$Q,"Y",GL_Input!$P:$P,"3RD")) -> 0 | G13: =IF($A13="",0,SUMIFS(GL_Input!$U:$U,GL_Input!$N:$N,$A13,GL_Input!$Q:$Q,"N",GL_Input!$P:$P,"CY")) -> 0 | H13: =IF($A13="",0,SUMIFS(GL_Input!$U:$U,GL_Input!$N:$N,$A13,GL_Input!$Q:$Q,"N",GL_Input!$P:$P,"EU")) -> 0 | I13: =IF($A13="",0,SUMIFS(GL_Input!$U:$U,GL_Input!$N:$N,$A13,GL_Input!$Q:$Q,"N",GL_Input!$P:$P,"3RD")) -> 0 | J13: =IF($A13="",0,SUMIFS(GL_Input!$U:$U,GL_Input!$N:$N,$A13,GL_Input!$P:$P,"")) -> 0 | K13: =SUM(D13:J13) -> 0 | L13: =IF(ROUND(K13-VAT_Codes!T13,2)=0,"OK","CHECK") -> OK
A14: =IF(VAT_Codes!A14="","",VAT_Codes!A14) -> OS3 | B14: =IF(VAT_Codes!B14="","",VAT_Codes!B14) -> Services to customers outside the EU (outside scope, with right to deduct) | C14: =IF(VAT_Codes!C14="","",VAT_Codes!C14) -> Output | D14: =IF($A14="",0,SUMIFS(GL_Input!$U:$U,GL_Input!$N:$N,$A14,GL_Input!$Q:$Q,"Y",GL_Input!$P:$P,"CY")) -> 0 | E14: =IF($A14="",0,SUMIFS(GL_Input!$U:$U,GL_Input!$N:$N,$A14,GL_Input!$Q:$Q,"Y",GL_Input!$P:$P,"EU")) -> 0 | F14: =IF($A14="",0,SUMIFS(GL_Input!$U:$U,GL_Input!$N:$N,$A14,GL_Input!$Q:$Q,"Y",GL_Input!$P:$P,"3RD")) -> 25753.28 | G14: =IF($A14="",0,SUMIFS(GL_Input!$U:$U,GL_Input!$N:$N,$A14,GL_Input!$Q:$Q,"N",GL_Input!$P:$P,"CY")) -> 0 | H14: =IF($A14="",0,SUMIFS(GL_Input!$U:$U,GL_Input!$N:$N,$A14,GL_Input!$Q:$Q,"N",GL_Input!$P:$P,"EU")) -> 0 | I14: =IF($A14="",0,SUMIFS(GL_Input!$U:$U,GL_Input!$N:$N,$A14,GL_Input!$Q:$Q,"N",GL_Input!$P:$P,"3RD")) -> 0 | J14: =IF($A14="",0,SUMIFS(GL_Input!$U:$U,GL_Input!$N:$N,$A14,GL_Input!$P:$P,"")) -> 0 | K14: =SUM(D14:J14) -> 25753.28 | L14: =IF(ROUND(K14-VAT_Codes!T14,2)=0,"OK","CHECK") -> OK
A15: =IF(VAT_Codes!A15="","",VAT_Codes!A15) -> OSS | B15: =IF(VAT_Codes!B15="","",VAT_Codes!B15) -> Distance sales / B2C services declared through OSS | C15: =IF(VAT_Codes!C15="","",VAT_Codes!C15) -> Output | D15: =IF($A15="",0,SUMIFS(GL_Input!$U:$U,GL_Input!$N:$N,$A15,GL_Input!$Q:$Q,"Y",GL_Input!$P:$P,"CY")) -> 0 | E15: =IF($A15="",0,SUMIFS(GL_Input!$U:$U,GL_Input!$N:$N,$A15,GL_Input!$Q:$Q,"Y",GL_Input!$P:$P,"EU")) -> 0 | F15: =IF($A15="",0,SUMIFS(GL_Input!$U:$U,GL_Input!$N:$N,$A15,GL_Input!$Q:$Q,"Y",GL_Input!$P:$P,"3RD")) -> 0 | G15: =IF($A15="",0,SUMIFS(GL_Input!$U:$U,GL_Input!$N:$N,$A15,GL_Input!$Q:$Q,"N",GL_Input!$P:$P,"CY")) -> 0 | H15: =IF($A15="",0,SUMIFS(GL_Input!$U:$U,GL_Input!$N:$N,$A15,GL_Input!$Q:$Q,"N",GL_Input!$P:$P,"EU")) -> 0 | I15: =IF($A15="",0,SUMIFS(GL_Input!$U:$U,GL_Input!$N:$N,$A15,GL_Input!$Q:$Q,"N",GL_Input!$P:$P,"3RD")) -> 0 | J15: =IF($A15="",0,SUMIFS(GL_Input!$U:$U,GL_Input!$N:$N,$A15,GL_Input!$P:$P,"")) -> 0 | K15: =SUM(D15:J15) -> 0 | L15: =IF(ROUND(K15-VAT_Codes!T15,2)=0,"OK","CHECK") -> OK
A16: =IF(VAT_Codes!A16="","",VAT_Codes!A16) -> FIN3 | B16: =IF(VAT_Codes!B16="","",VAT_Codes!B16) -> Financial / insurance services to recipients outside the EU | C16: =IF(VAT_Codes!C16="","",VAT_Codes!C16) -> Output | D16: =IF($A16="",0,SUMIFS(GL_Input!$U:$U,GL_Input!$N:$N,$A16,GL_Input!$Q:$Q,"Y",GL_Input!$P:$P,"CY")) -> 0 | E16: =IF($A16="",0,SUMIFS(GL_Input!$U:$U,GL_Input!$N:$N,$A16,GL_Input!$Q:$Q,"Y",GL_Input!$P:$P,"EU")) -> 0 | F16: =IF($A16="",0,SUMIFS(GL_Input!$U:$U,GL_Input!$N:$N,$A16,GL_Input!$Q:$Q,"Y",GL_Input!$P:$P,"3RD")) -> 0 | G16: =IF($A16="",0,SUMIFS(GL_Input!$U:$U,GL_Input!$N:$N,$A16,GL_Input!$Q:$Q,"N",GL_Input!$P:$P,"CY")) -> 0 | H16: =IF($A16="",0,SUMIFS(GL_Input!$U:$U,GL_Input!$N:$N,$A16,GL_Input!$Q:$Q,"N",GL_Input!$P:$P,"EU")) -> 0 | I16: =IF($A16="",0,SUMIFS(GL_Input!$U:$U,GL_Input!$N:$N,$A16,GL_Input!$Q:$Q,"N",GL_Input!$P:$P,"3RD")) -> 0 | J16: =IF($A16="",0,SUMIFS(GL_Input!$U:$U,GL_Input!$N:$N,$A16,GL_Input!$P:$P,"")) -> 0 | K16: =SUM(D16:J16) -> 0 | L16: =IF(ROUND(K16-VAT_Codes!T16,2)=0,"OK","CHECK") -> OK
... A80: =IF(VAT_Codes!A80="","",VAT_Codes!A80) | B80: =IF(VAT_Codes!B80="","",VAT_Codes!B80) | C80: =IF(VAT_Codes!C80="","",VAT_Codes!C80) | D80: =IF($A80="",0,SUMIFS(GL_Input!$U:$U,GL_Input!$N:$N,$A80,GL_Input!$Q:$Q,"Y",GL_Input!$P:$P,"CY")) -> 0 | E80: =IF($A80="",0,SUMIFS(GL_Input!$U:$U,GL_Input!$N:$N,$A80,GL_Input!$Q:$Q,"Y",GL_Input!$P:$P,"EU")) -> 0 | F80: =IF($A80="",0,SUMIFS(GL_Input!$U:$U,GL_Input!$N:$N,$A80,GL_Input!$Q:$Q,"Y",GL_Input!$P:$P,"3RD")) -> 0 | G80: =IF($A80="",0,SUMIFS(GL_Input!$U:$U,GL_Input!$N:$N,$A80,GL_Input!$Q:$Q,"N",GL_Input!$P:$P,"CY")) -> 0 | H80: =IF($A80="",0,SUMIFS(GL_Input!$U:$U,GL_Input!$N:$N,$A80,GL_Input!$Q:$Q,"N",GL_Input!$P:$P,"EU")) -> 0 | I80: =IF($A80="",0,SUMIFS(GL_Input!$U:$U,GL_Input!$N:$N,$A80,GL_Input!$Q:$Q,"N",GL_Input!$P:$P,"3RD")) -> 0 | J80: =IF($A80="",0,SUMIFS(GL_Input!$U:$U,GL_Input!$N:$N,$A80,GL_Input!$P:$P,"")) -> 0 | K80: =SUM(D80:J80) -> 0 | L80: =IF(ROUND(K80-VAT_Codes!T80,2)=0,"OK","CHECK") -> OK
B81: TOTAL | D81: =SUM(D5:D80) -> 0 | E81: =SUM(E5:E80) -> 40000 | F81: =SUM(F5:F80) -> 25753.28 | G81: =SUM(G5:G80) -> 12300 | H81: =SUM(H5:H80) -> 13000 | I81: =SUM(I5:I80) -> 14765.21 | J81: =SUM(J5:J80) -> 700 | K81: =SUM(K5:K80) -> 106518.49
B83: Summary by nature
B84: Total outputs | C84: Output | D84: =SUMIFS(D$5:D$80,$C$5:$C$80,$C84) -> 0 | E84: =SUMIFS(E$5:E$80,$C$5:$C$80,$C84) -> 25000 | F84: =SUMIFS(F$5:F$80,$C$5:$C$80,$C84) -> 25753.28 | G84: =SUMIFS(G$5:G$80,$C$5:$C$80,$C84) -> 10000 | H84: =SUMIFS(H$5:H$80,$C$5:$C$80,$C84) -> 8000 | I84: =SUMIFS(I$5:I$80,$C$5:$C$80,$C84) -> 10301.31 | J84: =SUMIFS(J$5:J$80,$C$5:$C$80,$C84) -> 0 | K84: =SUMIFS(K$5:K$80,$C$5:$C$80,$C84) -> 79054.59
B85: Total inputs | C85: Input | D85: =SUMIFS(D$5:D$80,$C$5:$C$80,$C85) -> 0 | E85: =SUMIFS(E$5:E$80,$C$5:$C$80,$C85) -> 15000 | F85: =SUMIFS(F$5:F$80,$C$5:$C$80,$C85) -> 0 | G85: =SUMIFS(G$5:G$80,$C$5:$C$80,$C85) -> 2300 | H85: =SUMIFS(H$5:H$80,$C$5:$C$80,$C85) -> 5000 | I85: =SUMIFS(I$5:I$80,$C$5:$C$80,$C85) -> 4463.9 | J85: =SUMIFS(J$5:J$80,$C$5:$C$80,$C85) -> 700 | K85: =SUMIFS(K$5:K$80,$C$5:$C$80,$C85) -> 27463.9

Sheet VIES
A1: VIES - recapitulative statement amounts per EU customer (EUR)
A2: Filed monthly by the 15th of the following month. Rows follow the Counterparties list; filter Total <> 0.
A4: Counterparty | B4: Name | C4: Country | D4: VAT number | E4: IC | F4: Goods M1 | G4: Goods M2 | H4: Goods M3 | I4: Triang. M1 | J4: Triang. M2 | K4: Triang. M3 | L4: Services M1 | M4: Services M2 | N4: Services M3 | O4: Total | P4: VAT no. check
A5: =IF(Counterparties!A5="","",Counterparties!A5) -> C-CY01 | B5: =IF(Counterparties!B5="","",Counterparties!B5) -> Limassol Trading Ltd | C5: =IF(Counterparties!C5="","",Counterparties!C5) -> CY | D5: =IF(Counterparties!D5="","",Counterparties!D5) -> CY10111111A | E5: =IF(Counterparties!E5="","",Counterparties!E5) -> N | F5: =IF($A5="",0,SUMIFS(GL_Input!$U:$U,GL_Input!$F:$F,$A5,GL_Input!$X:$X,"G",GL_Input!$Y:$Y,1)) -> 0 | G5: =IF($A5="",0,SUMIFS(GL_Input!$U:$U,GL_Input!$F:$F,$A5,GL_Input!$X:$X,"G",GL_Input!$Y:$Y,2)) -> 0 | H5: =IF($A5="",0,SUMIFS(GL_Input!$U:$U,GL_Input!$F:$F,$A5,GL_Input!$X:$X,"G",GL_Input!$Y:$Y,3)) -> 0 | I5: =IF($A5="",0,SUMIFS(GL_Input!$U:$U,GL_Input!$F:$F,$A5,GL_Input!$X:$X,"T",GL_Input!$Y:$Y,1)) -> 0 | J5: =IF($A5="",0,SUMIFS(GL_Input!$U:$U,GL_Input!$F:$F,$A5,GL_Input!$X:$X,"T",GL_Input!$Y:$Y,2)) -> 0 | K5: =IF($A5="",0,SUMIFS(GL_Input!$U:$U,GL_Input!$F:$F,$A5,GL_Input!$X:$X,"T",GL_Input!$Y:$Y,3)) -> 0 | L5: =IF($A5="",0,SUMIFS(GL_Input!$U:$U,GL_Input!$F:$F,$A5,GL_Input!$X:$X,"S",GL_Input!$Y:$Y,1)) -> 0 | M5: =IF($A5="",0,SUMIFS(GL_Input!$U:$U,GL_Input!$F:$F,$A5,GL_Input!$X:$X,"S",GL_Input!$Y:$Y,2)) -> 0 | N5: =IF($A5="",0,SUMIFS(GL_Input!$U:$U,GL_Input!$F:$F,$A5,GL_Input!$X:$X,"S",GL_Input!$Y:$Y,3)) -> 0 | O5: =SUM(F5:N5) -> 0 | P5: =IF(O5=0,"",IF($D5="","MISSING VAT NO.",IF(OR($C5="",$C5="CY",Counterparties!G5<>"EU"),"NOT AN EU CUSTOMER","OK")))
A6: =IF(Counterparties!A6="","",Counterparties!A6) -> IC-DE01 | B6: =IF(Counterparties!B6="","",Counterparties!B6) -> Example GmbH (group) | C6: =IF(Counterparties!C6="","",Counterparties!C6) -> DE | D6: =IF(Counterparties!D6="","",Counterparties!D6) -> DE123456789 | E6: =IF(Counterparties!E6="","",Counterparties!E6) -> Y | F6: =IF($A6="",0,SUMIFS(GL_Input!$U:$U,GL_Input!$F:$F,$A6,GL_Input!$X:$X,"G",GL_Input!$Y:$Y,1)) -> 0 | G6: =IF($A6="",0,SUMIFS(GL_Input!$U:$U,GL_Input!$F:$F,$A6,GL_Input!$X:$X,"G",GL_Input!$Y:$Y,2)) -> 0 | H6: =IF($A6="",0,SUMIFS(GL_Input!$U:$U,GL_Input!$F:$F,$A6,GL_Input!$X:$X,"G",GL_Input!$Y:$Y,3)) -> 0 | I6: =IF($A6="",0,SUMIFS(GL_Input!$U:$U,GL_Input!$F:$F,$A6,GL_Input!$X:$X,"T",GL_Input!$Y:$Y,1)) -> 0 | J6: =IF($A6="",0,SUMIFS(GL_Input!$U:$U,GL_Input!$F:$F,$A6,GL_Input!$X:$X,"T",GL_Input!$Y:$Y,2)) -> 0 | K6: =IF($A6="",0,SUMIFS(GL_Input!$U:$U,GL_Input!$F:$F,$A6,GL_Input!$X:$X,"T",GL_Input!$Y:$Y,3)) -> 0 | L6: =IF($A6="",0,SUMIFS(GL_Input!$U:$U,GL_Input!$F:$F,$A6,GL_Input!$X:$X,"S",GL_Input!$Y:$Y,1)) -> 25000 | M6: =IF($A6="",0,SUMIFS(GL_Input!$U:$U,GL_Input!$F:$F,$A6,GL_Input!$X:$X,"S",GL_Input!$Y:$Y,2)) -> 0 | N6: =IF($A6="",0,SUMIFS(GL_Input!$U:$U,GL_Input!$F:$F,$A6,GL_Input!$X:$X,"S",GL_Input!$Y:$Y,3)) -> 0 | O6: =SUM(F6:N6) -> 25000 | P6: =IF(O6=0,"",IF($D6="","MISSING VAT NO.",IF(OR($C6="",$C6="CY",Counterparties!G6<>"EU"),"NOT AN EU CUSTOMER","OK"))) -> OK
A7: =IF(Counterparties!A7="","",Counterparties!A7) -> IC-AE01 | B7: =IF(Counterparties!B7="","",Counterparties!B7) -> Example FZE Dubai (group) | C7: =IF(Counterparties!C7="","",Counterparties!C7) -> AE | D7: =IF(Counterparties!D7="","",Counterparties!D7) | E7: =IF(Counterparties!E7="","",Counterparties!E7) -> Y | F7: =IF($A7="",0,SUMIFS(GL_Input!$U:$U,GL_Input!$F:$F,$A7,GL_Input!$X:$X,"G",GL_Input!$Y:$Y,1)) -> 0 | G7: =IF($A7="",0,SUMIFS(GL_Input!$U:$U,GL_Input!$F:$F,$A7,GL_Input!$X:$X,"G",GL_Input!$Y:$Y,2)) -> 0 | H7: =IF($A7="",0,SUMIFS(GL_Input!$U:$U,GL_Input!$F:$F,$A7,GL_Input!$X:$X,"G",GL_Input!$Y:$Y,3)) -> 0 | I7: =IF($A7="",0,SUMIFS(GL_Input!$U:$U,GL_Input!$F:$F,$A7,GL_Input!$X:$X,"T",GL_Input!$Y:$Y,1)) -> 0 | J7: =IF($A7="",0,SUMIFS(GL_Input!$U:$U,GL_Input!$F:$F,$A7,GL_Input!$X:$X,"T",GL_Input!$Y:$Y,2)) -> 0 | K7: =IF($A7="",0,SUMIFS(GL_Input!$U:$U,GL_Input!$F:$F,$A7,GL_Input!$X:$X,"T",GL_Input!$Y:$Y,3)) -> 0 | L7: =IF($A7="",0,SUMIFS(GL_Input!$U:$U,GL_Input!$F:$F,$A7,GL_Input!$X:$X,"S",GL_Input!$Y:$Y,1)) -> 0 | M7: =IF($A7="",0,SUMIFS(GL_Input!$U:$U,GL_Input!$F:$F,$A7,GL_Input!$X:$X,"S",GL_Input!$Y:$Y,2)) -> 0 | N7: =IF($A7="",0,SUMIFS(GL_Input!$U:$U,GL_Input!$F:$F,$A7,GL_Input!$X:$X,"S",GL_Input!$Y:$Y,3)) -> 0 | O7: =SUM(F7:N7) -> 0 | P7: =IF(O7=0,"",IF($D7="","MISSING VAT NO.",IF(OR($C7="",$C7="CY",Counterparties!G7<>"EU"),"NOT AN EU CUSTOMER","OK")))
A8: =IF(Counterparties!A8="","",Counterparties!A8) -> C-IT01 | B8: =IF(Counterparties!B8="","",Counterparties!B8) -> Milano Srl | C8: =IF(Counterparties!C8="","",Counterparties!C8) -> IT | D8: =IF(Counterparties!D8="","",Counterparties!D8) -> IT01234567890 | E8: =IF(Counterparties!E8="","",Counterparties!E8) -> N | F8: =IF($A8="",0,SUMIFS(GL_Input!$U:$U,GL_Input!$F:$F,$A8,GL_Input!$X:$X,"G",GL_Input!$Y:$Y,1)) -> 0 | G8: =IF($A8="",0,SUMIFS(GL_Input!$U:$U,GL_Input!$F:$F,$A8,GL_Input!$X:$X,"G",GL_Input!$Y:$Y,2)) -> 8000 | H8: =IF($A8="",0,SUMIFS(GL_Input!$U:$U,GL_Input!$F:$F,$A8,GL_Input!$X:$X,"G",GL_Input!$Y:$Y,3)) -> 0 | I8: =IF($A8="",0,SUMIFS(GL_Input!$U:$U,GL_Input!$F:$F,$A8,GL_Input!$X:$X,"T",GL_Input!$Y:$Y,1)) -> 0 | J8: =IF($A8="",0,SUMIFS(GL_Input!$U:$U,GL_Input!$F:$F,$A8,GL_Input!$X:$X,"T",GL_Input!$Y:$Y,2)) -> 0 | K8: =IF($A8="",0,SUMIFS(GL_Input!$U:$U,GL_Input!$F:$F,$A8,GL_Input!$X:$X,"T",GL_Input!$Y:$Y,3)) -> 0 | L8: =IF($A8="",0,SUMIFS(GL_Input!$U:$U,GL_Input!$F:$F,$A8,GL_Input!$X:$X,"S",GL_Input!$Y:$Y,1)) -> 0 | M8: =IF($A8="",0,SUMIFS(GL_Input!$U:$U,GL_Input!$F:$F,$A8,GL_Input!$X:$X,"S",GL_Input!$Y:$Y,2)) -> 0 | N8: =IF($A8="",0,SUMIFS(GL_Input!$U:$U,GL_Input!$F:$F,$A8,GL_Input!$X:$X,"S",GL_Input!$Y:$Y,3)) -> 0 | O8: =SUM(F8:N8) -> 8000 | P8: =IF(O8=0,"",IF($D8="","MISSING VAT NO.",IF(OR($C8="",$C8="CY",Counterparties!G8<>"EU"),"NOT AN EU CUSTOMER","OK"))) -> OK
A9: =IF(Counterparties!A9="","",Counterparties!A9) -> C-US01 | B9: =IF(Counterparties!B9="","",Counterparties!B9) -> Boston Inc | C9: =IF(Counterparties!C9="","",Counterparties!C9) -> US | D9: =IF(Counterparties!D9="","",Counterparties!D9) | E9: =IF(Counterparties!E9="","",Counterparties!E9) -> N | F9: =IF($A9="",0,SUMIFS(GL_Input!$U:$U,GL_Input!$F:$F,$A9,GL_Input!$X:$X,"G",GL_Input!$Y:$Y,1)) -> 0 | G9: =IF($A9="",0,SUMIFS(GL_Input!$U:$U,GL_Input!$F:$F,$A9,GL_Input!$X:$X,"G",GL_Input!$Y:$Y,2)) -> 0 | H9: =IF($A9="",0,SUMIFS(GL_Input!$U:$U,GL_Input!$F:$F,$A9,GL_Input!$X:$X,"G",GL_Input!$Y:$Y,3)) -> 0 | I9: =IF($A9="",0,SUMIFS(GL_Input!$U:$U,GL_Input!$F:$F,$A9,GL_Input!$X:$X,"T",GL_Input!$Y:$Y,1)) -> 0 | J9: =IF($A9="",0,SUMIFS(GL_Input!$U:$U,GL_Input!$F:$F,$A9,GL_Input!$X:$X,"T",GL_Input!$Y:$Y,2)) -> 0 | K9: =IF($A9="",0,SUMIFS(GL_Input!$U:$U,GL_Input!$F:$F,$A9,GL_Input!$X:$X,"T",GL_Input!$Y:$Y,3)) -> 0 | L9: =IF($A9="",0,SUMIFS(GL_Input!$U:$U,GL_Input!$F:$F,$A9,GL_Input!$X:$X,"S",GL_Input!$Y:$Y,1)) -> 0 | M9: =IF($A9="",0,SUMIFS(GL_Input!$U:$U,GL_Input!$F:$F,$A9,GL_Input!$X:$X,"S",GL_Input!$Y:$Y,2)) -> 0 | N9: =IF($A9="",0,SUMIFS(GL_Input!$U:$U,GL_Input!$F:$F,$A9,GL_Input!$X:$X,"S",GL_Input!$Y:$Y,3)) -> 0 | O9: =SUM(F9:N9) -> 0 | P9: =IF(O9=0,"",IF($D9="","MISSING VAT NO.",IF(OR($C9="",$C9="CY",Counterparties!G9<>"EU"),"NOT AN EU CUSTOMER","OK")))
A10: =IF(Counterparties!A10="","",Counterparties!A10) -> S-CY01 | B10: =IF(Counterparties!B10="","",Counterparties!B10) -> Nicosia Audit Ltd | C10: =IF(Counterparties!C10="","",Counterparties!C10) -> CY | D10: =IF(Counterparties!D10="","",Counterparties!D10) -> CY10222222B | E10: =IF(Counterparties!E10="","",Counterparties!E10) -> N | F10: =IF($A10="",0,SUMIFS(GL_Input!$U:$U,GL_Input!$F:$F,$A10,GL_Input!$X:$X,"G",GL_Input!$Y:$Y,1)) -> 0 | G10: =IF($A10="",0,SUMIFS(GL_Input!$U:$U,GL_Input!$F:$F,$A10,GL_Input!$X:$X,"G",GL_Input!$Y:$Y,2)) -> 0 | H10: =IF($A10="",0,SUMIFS(GL_Input!$U:$U,GL_Input!$F:$F,$A10,GL_Input!$X:$X,"G",GL_Input!$Y:$Y,3)) -> 0 | I10: =IF($A10="",0,SUMIFS(GL_Input!$U:$U,GL_Input!$F:$F,$A10,GL_Input!$X:$X,"T",GL_Input!$Y:$Y,1)) -> 0 | J10: =IF($A10="",0,SUMIFS(GL_Input!$U:$U,GL_Input!$F:$F,$A10,GL_Input!$X:$X,"T",GL_Input!$Y:$Y,2)) -> 0 | K10: =IF($A10="",0,SUMIFS(GL_Input!$U:$U,GL_Input!$F:$F,$A10,GL_Input!$X:$X,"T",GL_Input!$Y:$Y,3)) -> 0 | L10: =IF($A10="",0,SUMIFS(GL_Input!$U:$U,GL_Input!$F:$F,$A10,GL_Input!$X:$X,"S",GL_Input!$Y:$Y,1)) -> 0 | M10: =IF($A10="",0,SUMIFS(GL_Input!$U:$U,GL_Input!$F:$F,$A10,GL_Input!$X:$X,"S",GL_Input!$Y:$Y,2)) -> 0 | N10: =IF($A10="",0,SUMIFS(GL_Input!$U:$U,GL_Input!$F:$F,$A10,GL_Input!$X:$X,"S",GL_Input!$Y:$Y,3)) -> 0 | O10: =SUM(F10:N10) -> 0 | P10: =IF(O10=0,"",IF($D10="","MISSING VAT NO.",IF(OR($C10="",$C10="CY",Counterparties!G10<>"EU"),"NOT AN EU CUSTOMER","OK")))
A11: =IF(Counterparties!A11="","",Counterparties!A11) -> IC-NL01 | B11: =IF(Counterparties!B11="","",Counterparties!B11) -> Example BV (parent) | C11: =IF(Counterparties!C11="","",Counterparties!C11) -> NL | D11: =IF(Counterparties!D11="","",Counterparties!D11) -> NL123456789B01 | E11: =IF(Counterparties!E11="","",Counterparties!E11) -> Y | F11: =IF($A11="",0,SUMIFS(GL_Input!$U:$U,GL_Input!$F:$F,$A11,GL_Input!$X:$X,"G",GL_Input!$Y:$Y,1)) -> 0 | G11: =IF($A11="",0,SUMIFS(GL_Input!$U:$U,GL_Input!$F:$F,$A11,GL_Input!$X:$X,"G",GL_Input!$Y:$Y,2)) -> 0 | H11: =IF($A11="",0,SUMIFS(GL_Input!$U:$U,GL_Input!$F:$F,$A11,GL_Input!$X:$X,"G",GL_Input!$Y:$Y,3)) -> 0 | I11: =IF($A11="",0,SUMIFS(GL_Input!$U:$U,GL_Input!$F:$F,$A11,GL_Input!$X:$X,"T",GL_Input!$Y:$Y,1)) -> 0 | J11: =IF($A11="",0,SUMIFS(GL_Input!$U:$U,GL_Input!$F:$F,$A11,GL_Input!$X:$X,"T",GL_Input!$Y:$Y,2)) -> 0 | K11: =IF($A11="",0,SUMIFS(GL_Input!$U:$U,GL_Input!$F:$F,$A11,GL_Input!$X:$X,"T",GL_Input!$Y:$Y,3)) -> 0 | L11: =IF($A11="",0,SUMIFS(GL_Input!$U:$U,GL_Input!$F:$F,$A11,GL_Input!$X:$X,"S",GL_Input!$Y:$Y,1)) -> 0 | M11: =IF($A11="",0,SUMIFS(GL_Input!$U:$U,GL_Input!$F:$F,$A11,GL_Input!$X:$X,"S",GL_Input!$Y:$Y,2)) -> 0 | N11: =IF($A11="",0,SUMIFS(GL_Input!$U:$U,GL_Input!$F:$F,$A11,GL_Input!$X:$X,"S",GL_Input!$Y:$Y,3)) -> 0 | O11: =SUM(F11:N11) -> 0 | P11: =IF(O11=0,"",IF($D11="","MISSING VAT NO.",IF(OR($C11="",$C11="CY",Counterparties!G11<>"EU"),"NOT AN EU CUSTOMER","OK")))
A12: =IF(Counterparties!A12="","",Counterparties!A12) -> S-US01 | B12: =IF(Counterparties!B12="","",Counterparties!B12) -> Cloudsoft Inc | C12: =IF(Counterparties!C12="","",Counterparties!C12) -> US | D12: =IF(Counterparties!D12="","",Counterparties!D12) | E12: =IF(Counterparties!E12="","",Counterparties!E12) -> N | F12: =IF($A12="",0,SUMIFS(GL_Input!$U:$U,GL_Input!$F:$F,$A12,GL_Input!$X:$X,"G",GL_Input!$Y:$Y,1)) -> 0 | G12: =IF($A12="",0,SUMIFS(GL_Input!$U:$U,GL_Input!$F:$F,$A12,GL_Input!$X:$X,"G",GL_Input!$Y:$Y,2)) -> 0 | H12: =IF($A12="",0,SUMIFS(GL_Input!$U:$U,GL_Input!$F:$F,$A12,GL_Input!$X:$X,"G",GL_Input!$Y:$Y,3)) -> 0 | I12: =IF($A12="",0,SUMIFS(GL_Input!$U:$U,GL_Input!$F:$F,$A12,GL_Input!$X:$X,"T",GL_Input!$Y:$Y,1)) -> 0 | J12: =IF($A12="",0,SUMIFS(GL_Input!$U:$U,GL_Input!$F:$F,$A12,GL_Input!$X:$X,"T",GL_Input!$Y:$Y,2)) -> 0 | K12: =IF($A12="",0,SUMIFS(GL_Input!$U:$U,GL_Input!$F:$F,$A12,GL_Input!$X:$X,"T",GL_Input!$Y:$Y,3)) -> 0 | L12: =IF($A12="",0,SUMIFS(GL_Input!$U:$U,GL_Input!$F:$F,$A12,GL_Input!$X:$X,"S",GL_Input!$Y:$Y,1)) -> 0 | M12: =IF($A12="",0,SUMIFS(GL_Input!$U:$U,GL_Input!$F:$F,$A12,GL_Input!$X:$X,"S",GL_Input!$Y:$Y,2)) -> 0 | N12: =IF($A12="",0,SUMIFS(GL_Input!$U:$U,GL_Input!$F:$F,$A12,GL_Input!$X:$X,"S",GL_Input!$Y:$Y,3)) -> 0 | O12: =SUM(F12:N12) -> 0 | P12: =IF(O12=0,"",IF($D12="","MISSING VAT NO.",IF(OR($C12="",$C12="CY",Counterparties!G12<>"EU"),"NOT AN EU CUSTOMER","OK")))
A13: =IF(Counterparties!A13="","",Counterparties!A13) -> S-DE01 | B13: =IF(Counterparties!B13="","",Counterparties!B13) -> Hamburg Supplies GmbH | C13: =IF(Counterparties!C13="","",Counterparties!C13) -> DE | D13: =IF(Counterparties!D13="","",Counterparties!D13) -> DE987654321 | E13: =IF(Counterparties!E13="","",Counterparties!E13) -> N | F13: =IF($A13="",0,SUMIFS(GL_Input!$U:$U,GL_Input!$F:$F,$A13,GL_Input!$X:$X,"G",GL_Input!$Y:$Y,1)) -> 0 | G13: =IF($A13="",0,SUMIFS(GL_Input!$U:$U,GL_Input!$F:$F,$A13,GL_Input!$X:$X,"G",GL_Input!$Y:$Y,2)) -> 0 | H13: =IF($A13="",0,SUMIFS(GL_Input!$U:$U,GL_Input!$F:$F,$A13,GL_Input!$X:$X,"G",GL_Input!$Y:$Y,3)) -> 0 | I13: =IF($A13="",0,SUMIFS(GL_Input!$U:$U,GL_Input!$F:$F,$A13,GL_Input!$X:$X,"T",GL_Input!$Y:$Y,1)) -> 0 | J13: =IF($A13="",0,SUMIFS(GL_Input!$U:$U,GL_Input!$F:$F,$A13,GL_Input!$X:$X,"T",GL_Input!$Y:$Y,2)) -> 0 | K13: =IF($A13="",0,SUMIFS(GL_Input!$U:$U,GL_Input!$F:$F,$A13,GL_Input!$X:$X,"T",GL_Input!$Y:$Y,3)) -> 0 | L13: =IF($A13="",0,SUMIFS(GL_Input!$U:$U,GL_Input!$F:$F,$A13,GL_Input!$X:$X,"S",GL_Input!$Y:$Y,1)) -> 0 | M13: =IF($A13="",0,SUMIFS(GL_Input!$U:$U,GL_Input!$F:$F,$A13,GL_Input!$X:$X,"S",GL_Input!$Y:$Y,2)) -> 0 | N13: =IF($A13="",0,SUMIFS(GL_Input!$U:$U,GL_Input!$F:$F,$A13,GL_Input!$X:$X,"S",GL_Input!$Y:$Y,3)) -> 0 | O13: =SUM(F13:N13) -> 0 | P13: =IF(O13=0,"",IF($D13="","MISSING VAT NO.",IF(OR($C13="",$C13="CY",Counterparties!G13<>"EU"),"NOT AN EU CUSTOMER","OK")))
A14: =IF(Counterparties!A14="","",Counterparties!A14) -> S-CN01 | B14: =IF(Counterparties!B14="","",Counterparties!B14) -> Shenzhen Mfg Co | C14: =IF(Counterparties!C14="","",Counterparties!C14) -> CN | D14: =IF(Counterparties!D14="","",Counterparties!D14) | E14: =IF(Counterparties!E14="","",Counterparties!E14) -> N | F14: =IF($A14="",0,SUMIFS(GL_Input!$U:$U,GL_Input!$F:$F,$A14,GL_Input!$X:$X,"G",GL_Input!$Y:$Y,1)) -> 0 | G14: =IF($A14="",0,SUMIFS(GL_Input!$U:$U,GL_Input!$F:$F,$A14,GL_Input!$X:$X,"G",GL_Input!$Y:$Y,2)) -> 0 | H14: =IF($A14="",0,SUMIFS(GL_Input!$U:$U,GL_Input!$F:$F,$A14,GL_Input!$X:$X,"G",GL_Input!$Y:$Y,3)) -> 0 | I14: =IF($A14="",0,SUMIFS(GL_Input!$U:$U,GL_Input!$F:$F,$A14,GL_Input!$X:$X,"T",GL_Input!$Y:$Y,1)) -> 0 | J14: =IF($A14="",0,SUMIFS(GL_Input!$U:$U,GL_Input!$F:$F,$A14,GL_Input!$X:$X,"T",GL_Input!$Y:$Y,2)) -> 0 | K14: =IF($A14="",0,SUMIFS(GL_Input!$U:$U,GL_Input!$F:$F,$A14,GL_Input!$X:$X,"T",GL_Input!$Y:$Y,3)) -> 0 | L14: =IF($A14="",0,SUMIFS(GL_Input!$U:$U,GL_Input!$F:$F,$A14,GL_Input!$X:$X,"S",GL_Input!$Y:$Y,1)) -> 0 | M14: =IF($A14="",0,SUMIFS(GL_Input!$U:$U,GL_Input!$F:$F,$A14,GL_Input!$X:$X,"S",GL_Input!$Y:$Y,2)) -> 0 | N14: =IF($A14="",0,SUMIFS(GL_Input!$U:$U,GL_Input!$F:$F,$A14,GL_Input!$X:$X,"S",GL_Input!$Y:$Y,3)) -> 0 | O14: =SUM(F14:N14) -> 0 | P14: =IF(O14=0,"",IF($D14="","MISSING VAT NO.",IF(OR($C14="",$C14="CY",Counterparties!G14<>"EU"),"NOT AN EU CUSTOMER","OK")))
A15: =IF(Counterparties!A15="","",Counterparties!A15) -> S-CY02 | B15: =IF(Counterparties!B15="","",Counterparties!B15) -> Paphos Restaurant Ltd | C15: =IF(Counterparties!C15="","",Counterparties!C15) -> CY | D15: =IF(Counterparties!D15="","",Counterparties!D15) -> CY10333333C | E15: =IF(Counterparties!E15="","",Counterparties!E15) -> N | F15: =IF($A15="",0,SUMIFS(GL_Input!$U:$U,GL_Input!$F:$F,$A15,GL_Input!$X:$X,"G",GL_Input!$Y:$Y,1)) -> 0 | G15: =IF($A15="",0,SUMIFS(GL_Input!$U:$U,GL_Input!$F:$F,$A15,GL_Input!$X:$X,"G",GL_Input!$Y:$Y,2)) -> 0 | H15: =IF($A15="",0,SUMIFS(GL_Input!$U:$U,GL_Input!$F:$F,$A15,GL_Input!$X:$X,"G",GL_Input!$Y:$Y,3)) -> 0 | I15: =IF($A15="",0,SUMIFS(GL_Input!$U:$U,GL_Input!$F:$F,$A15,GL_Input!$X:$X,"T",GL_Input!$Y:$Y,1)) -> 0 | J15: =IF($A15="",0,SUMIFS(GL_Input!$U:$U,GL_Input!$F:$F,$A15,GL_Input!$X:$X,"T",GL_Input!$Y:$Y,2)) -> 0 | K15: =IF($A15="",0,SUMIFS(GL_Input!$U:$U,GL_Input!$F:$F,$A15,GL_Input!$X:$X,"T",GL_Input!$Y:$Y,3)) -> 0 | L15: =IF($A15="",0,SUMIFS(GL_Input!$U:$U,GL_Input!$F:$F,$A15,GL_Input!$X:$X,"S",GL_Input!$Y:$Y,1)) -> 0 | M15: =IF($A15="",0,SUMIFS(GL_Input!$U:$U,GL_Input!$F:$F,$A15,GL_Input!$X:$X,"S",GL_Input!$Y:$Y,2)) -> 0 | N15: =IF($A15="",0,SUMIFS(GL_Input!$U:$U,GL_Input!$F:$F,$A15,GL_Input!$X:$X,"S",GL_Input!$Y:$Y,3)) -> 0 | O15: =SUM(F15:N15) -> 0 | P15: =IF(O15=0,"",IF($D15="","MISSING VAT NO.",IF(OR($C15="",$C15="CY",Counterparties!G15<>"EU"),"NOT AN EU CUSTOMER","OK")))
A16: =IF(Counterparties!A16="","",Counterparties!A16) | B16: =IF(Counterparties!B16="","",Counterparties!B16) | C16: =IF(Counterparties!C16="","",Counterparties!C16) | D16: =IF(Counterparties!D16="","",Counterparties!D16) | E16: =IF(Counterparties!E16="","",Counterparties!E16) | F16: =IF($A16="",0,SUMIFS(GL_Input!$U:$U,GL_Input!$F:$F,$A16,GL_Input!$X:$X,"G",GL_Input!$Y:$Y,1)) -> 0 | G16: =IF($A16="",0,SUMIFS(GL_Input!$U:$U,GL_Input!$F:$F,$A16,GL_Input!$X:$X,"G",GL_Input!$Y:$Y,2)) -> 0 | H16: =IF($A16="",0,SUMIFS(GL_Input!$U:$U,GL_Input!$F:$F,$A16,GL_Input!$X:$X,"G",GL_Input!$Y:$Y,3)) -> 0 | I16: =IF($A16="",0,SUMIFS(GL_Input!$U:$U,GL_Input!$F:$F,$A16,GL_Input!$X:$X,"T",GL_Input!$Y:$Y,1)) -> 0 | J16: =IF($A16="",0,SUMIFS(GL_Input!$U:$U,GL_Input!$F:$F,$A16,GL_Input!$X:$X,"T",GL_Input!$Y:$Y,2)) -> 0 | K16: =IF($A16="",0,SUMIFS(GL_Input!$U:$U,GL_Input!$F:$F,$A16,GL_Input!$X:$X,"T",GL_Input!$Y:$Y,3)) -> 0 | L16: =IF($A16="",0,SUMIFS(GL_Input!$U:$U,GL_Input!$F:$F,$A16,GL_Input!$X:$X,"S",GL_Input!$Y:$Y,1)) -> 0 | M16: =IF($A16="",0,SUMIFS(GL_Input!$U:$U,GL_Input!$F:$F,$A16,GL_Input!$X:$X,"S",GL_Input!$Y:$Y,2)) -> 0 | N16: =IF($A16="",0,SUMIFS(GL_Input!$U:$U,GL_Input!$F:$F,$A16,GL_Input!$X:$X,"S",GL_Input!$Y:$Y,3)) -> 0 | O16: =SUM(F16:N16) -> 0 | P16: =IF(O16=0,"",IF($D16="","MISSING VAT NO.",IF(OR($C16="",$C16="CY",Counterparties!G16<>"EU"),"NOT AN EU CUSTOMER","OK")))
... A304: =IF(Counterparties!A304="","",Counterparties!A304) | B304: =IF(Counterparties!B304="","",Counterparties!B304) | C304: =IF(Counterparties!C304="","",Counterparties!C304) | D304: =IF(Counterparties!D304="","",Counterparties!D304) | E304: =IF(Counterparties!E304="","",Counterparties!E304) | F304: =IF($A304="",0,SUMIFS(GL_Input!$U:$U,GL_Input!$F:$F,$A304,GL_Input!$X:$X,"G",GL_Input!$Y:$Y,1)) -> 0 | G304: =IF($A304="",0,SUMIFS(GL_Input!$U:$U,GL_Input!$F:$F,$A304,GL_Input!$X:$X,"G",GL_Input!$Y:$Y,2)) -> 0 | H304: =IF($A304="",0,SUMIFS(GL_Input!$U:$U,GL_Input!$F:$F,$A304,GL_Input!$X:$X,"G",GL_Input!$Y:$Y,3)) -> 0 | I304: =IF($A304="",0,SUMIFS(GL_Input!$U:$U,GL_Input!$F:$F,$A304,GL_Input!$X:$X,"T",GL_Input!$Y:$Y,1)) -> 0 | J304: =IF($A304="",0,SUMIFS(GL_Input!$U:$U,GL_Input!$F:$F,$A304,GL_Input!$X:$X,"T",GL_Input!$Y:$Y,2)) -> 0 | K304: =IF($A304="",0,SUMIFS(GL_Input!$U:$U,GL_Input!$F:$F,$A304,GL_Input!$X:$X,"T",GL_Input!$Y:$Y,3)) -> 0 | L304: =IF($A304="",0,SUMIFS(GL_Input!$U:$U,GL_Input!$F:$F,$A304,GL_Input!$X:$X,"S",GL_Input!$Y:$Y,1)) -> 0 | M304: =IF($A304="",0,SUMIFS(GL_Input!$U:$U,GL_Input!$F:$F,$A304,GL_Input!$X:$X,"S",GL_Input!$Y:$Y,2)) -> 0 | N304: =IF($A304="",0,SUMIFS(GL_Input!$U:$U,GL_Input!$F:$F,$A304,GL_Input!$X:$X,"S",GL_Input!$Y:$Y,3)) -> 0 | O304: =SUM(F304:N304) -> 0 | P304: =IF(O304=0,"",IF($D304="","MISSING VAT NO.",IF(OR($C304="",$C304="CY",Counterparties!G304<>"EU"),"NOT AN EU CUSTOMER","OK")))
B305: TOTAL | F305: =SUM(F5:F304) -> 0 | G305: =SUM(G5:G304) -> 8000 | H305: =SUM(H5:H304) -> 0 | I305: =SUM(I5:I304) -> 0 | J305: =SUM(J5:J304) -> 0 | K305: =SUM(K5:K304) -> 0 | L305: =SUM(L5:L304) -> 25000 | M305: =SUM(M5:M304) -> 0 | ... O305: =SUM(O5:O304) -> 33000

Sheet Reconciliation
A1: Reconciliation - VAT return vs GL VAT control accounts (EUR)
A2: VAT control account codes are set in Settings. GL movements are for the lines in GL_Input (the quarter).
B4: A. Output VAT
B5: Box 1 per return | C5: =VAT_Return!C10 -> 4945.72
B6: Less: reverse-charge VAT self-accounted in Box 1 (services from abroad, domestic reverse charge) | C6: =-SUMIFS(VAT_Codes!$U$5:$U$80,VAT_Codes!$I$5:$I$80,"Y",VAT_Codes!$C$5:$C$80,"Input") -> -3045.72
B7: Add: Box 2 (acquisitions of goods) if booked in the output VAT account | C7: =IF(Settings!$C$11="Y",VAT_Return!C11,0) -> 0 | D7: Only when reverse-charge VAT is posted in the GL (Settings C11 = Y).
B8: Add back reverse-charge VAT if booked in the GL VAT accounts | C8: =IF(Settings!$C$11="Y",SUMIFS(VAT_Codes!$U$5:$U$80,VAT_Codes!$I$5:$I$80,"Y",VAT_Codes!$C$5:$C$80,"Input"),0) -> 0
B9: Output VAT expected in the GL | C9: =SUM(C5:C8) -> 1900
B10: GL output VAT control accounts - net credit movement | C10: =-(SUMIFS(GL_Input!$S:$S,GL_Input!$C:$C,Settings!$C$18&"")*(Settings!$C$18<>"")+SUMIFS(GL_Input!$S:$S,GL_Input!$C:$C,Settings!$C$19&"")*(Settings!$C$19<>"")+SUMIFS(GL_Input!$S:$S,GL_Input!$C:$C,Settings!$C$20&"")*(Settings!$C$20<>"")+SUMIFS(GL_Input!$S:$S,GL_Input!$C:$C,Settings!$C$21&"")*(Settings!$C$21<>"")+SUMIFS(GL_Input!$S:$S,GL_Input!$C:$C,Settings!$C$22&"")*(Settings!$C$22<>"")) -> 1900 | D10: Credit movements shown positive.
B11: Difference | C11: =ROUND(C9-C10,2) -> 0
B12: Status | C12: =IF(ABS(C11)<=Settings!$C$12,"OK","INVESTIGATE") -> OK | D12: Typical causes: wrong account, VAT rate errors, invoices outside period, manual journals.
B13: B. Input VAT
B14: Box 4 per return | C14: =VAT_Return!C13 -> 5075.72
B15: Less: reclaimable reverse-charge VAT on services / domestic reverse charge | C15: =-SUMIFS(VAT_Codes!$V$5:$V$80,VAT_Codes!$K$5:$K$80,"Y",VAT_Codes!$I$5:$I$80,"Y") -> -3045.72
B16: Less: reclaimable VAT on EU acquisitions of goods (Box 2) | C16: =-SUMIFS(VAT_Codes!$V$5:$V$80,VAT_Codes!$K$5:$K$80,"Y",VAT_Codes!$J$5:$J$80,"Y") -> -950
B17: Less: import VAT (IVAT - separate account) | C17: =-SUMIFS(VAT_Codes!$V$5:$V$80,VAT_Codes!$F$5:$F$80,"Y") -> -700
B18: Add back reverse-charge VAT if booked in the GL VAT accounts | C18: =IF(Settings!$C$11="Y",SUMIFS(VAT_Codes!$V$5:$V$80,VAT_Codes!$K$5:$K$80,"Y",VAT_Codes!$I$5:$I$80,"Y")+SUMIFS(VAT_Codes!$V$5:$V$80,VAT_Codes!$K$5:$K$80,"Y",VAT_Codes!$J$5:$J$80,"Y"),0) -> 0
B19: Input VAT expected in the GL | C19: =SUM(C14:C18) -> 380
B20: GL input VAT control accounts - net debit movement | C20: =SUMIFS(GL_Input!$S:$S,GL_Input!$C:$C,Settings!$C$26&"")*(Settings!$C$26<>"")+SUMIFS(GL_Input!$S:$S,GL_Input!$C:$C,Settings!$C$27&"")*(Settings!$C$27<>"")+SUMIFS(GL_Input!$S:$S,GL_Input!$C:$C,Settings!$C$28&"")*(Settings!$C$28<>"")+SUMIFS(GL_Input!$S:$S,GL_Input!$C:$C,Settings!$C$29&"")*(Settings!$C$29<>"")+SUMIFS(GL_Input!$S:$S,GL_Input!$C:$C,Settings!$C$30&"")*(Settings!$C$30<>"") -> 380 | D20: Blocked / irrecoverable VAT should be expensed, not left in the input VAT account.
B21: Difference | C21: =ROUND(C19-C20,2) -> 0
B22: Status | C22: =IF(ABS(C21)<=Settings!$C$12,"OK","INVESTIGATE") -> OK
B23: C. Values
B24: Box 6 must be at least Boxes 8A + 8B + 9 + 10 + 11B | C24: =IF(VAT_Return!C15+0.005>=VAT_Return!C17+VAT_Return!C18+VAT_Return!C19+VAT_Return!C20+VAT_Return!C22,"OK","CHECK") -> OK
B25: Box 7 must be at least Boxes 11A + 11B | C25: =IF(VAT_Return!C16+0.005>=VAT_Return!C21+VAT_Return!C22,"OK","CHECK") -> OK
B26: Total sales per GL (all output codes) vs Box 6 | C26: =ROUND(SUMIFS(VAT_Codes!$T$5:$T$80,VAT_Codes!$C$5:$C$80,"Output")-(VAT_Return!C15-SUMIFS(VAT_Codes!$T$5:$T$80,VAT_Codes!$C$5:$C$80,"Input",VAT_Codes!$L$5:$L$80,"Y")),2) -> 0 | D26: Should be 0 (Box 6 also contains the reverse-charge services values).

Sheet Checks
A1: Checks - exception report
A2: Every line must be 0 / OK before the return is filed.
B4: Check | C4: Result | D4: What to do
B5: GL lines with no VAT code (map the account or override in column K) | C5: =COUNTIFS(GL_Input!$Z:$Z,"NO VAT CODE") -> 0 | D5: Filter GL_Input column Z.
B6: GL lines with a code not in VAT_Codes | C6: =COUNTIFS(GL_Input!$Z:$Z,"UNKNOWN VAT CODE") -> 0
B7: GL lines with a missing FX rate | C7: =COUNTIFS(GL_Input!$Z:$Z,"MISSING FX RATE") -> 0 | D7: Run the fx command or enter a manual override in FX_Rates.
B8: GL lines dated outside the VAT period | C8: =COUNTIFS(GL_Input!$Z:$Z,"OUTSIDE PERIOD") -> 0 | D8: Remove them or confirm the tax point is in this quarter.
B9: GL lines needing a counterparty country (EU / 3rd-country codes) | C9: =COUNTIFS(GL_Input!$Z:$Z,"MISSING COUNTERPARTY COUNTRY") -> 0 | D9: Add the counterparty code in GL column F and its country in Counterparties.
B10: GL lines where the code does not fit the counterparty's region | C10: =COUNTIFS(GL_Input!$Z:$Z,"REGION MISMATCH") -> 0 | D10: e.g. EUS on a US customer, A3S19 on a German supplier.
B11: Accounts in Account_Mapping without a VAT code | C11: =COUNTIFS(Account_Mapping!$A$5:$A$5000,"<>",Account_Mapping!$C$5:$C$5000,"") -> 0
B12: GL accounts missing from Account_Mapping | C12: =SUMPRODUCT((GL_Input!$C$5:$C$60000<>"")*ISNA(MATCH(GL_Input!$C$5:$C$60000&"",Account_Mapping!$A$5:$A$5000,0))) -> 0 | D12: Run import-gl again or add the accounts.
B13: Counterparties used in the GL without a country | C13: =COUNTIFS(Counterparties!$A$5:$A$5000,"<>",Counterparties!$C$5:$C$5000,"",Counterparties!$H$5:$H$5000,">0") -> 0
B14: EU customers in VIES without a VAT number / not in the EU | C14: =COUNTIFS(VIES!$P:$P,"MISSING VAT NO.")+COUNTIFS(VIES!$P:$P,"NOT AN EU CUSTOMER") -> 0
B15: VIES goods total less Box 8A | C15: =ROUND(SUMIFS(VIES!F:F,VIES!A:A,"<>")+SUMIFS(VIES!G:G,VIES!A:A,"<>")+SUMIFS(VIES!H:H,VIES!A:A,"<>")-VAT_Return!C17,2) -> 0 | D15: Should be 0.
B16: VIES services total less Box 8B | C16: =ROUND(SUMIFS(VIES!L:L,VIES!A:A,"<>")+SUMIFS(VIES!M:M,VIES!A:A,"<>")+SUMIFS(VIES!N:N,VIES!A:A,"<>")-VAT_Return!C18,2) -> 0 | D16: Should be 0.
B17: Output VAT reconciliation | C17: =Reconciliation!C12 -> OK
B18: Input VAT reconciliation | C18: =Reconciliation!C22 -> OK
B19: Box 6 / Box 7 completeness | C19: =IF(AND(Reconciliation!C24="OK",Reconciliation!C25="OK"),"OK","CHECK") -> OK
B20: Exchange rates still the EXAMPLE placeholders | C20: =COUNTIF(FX_Rates!$H:$H,"EXAMPLE*") -> 2 | D20: Run the fx command (or enter manual overrides and change the note).
B21: Inter-company analysis agrees to VAT_Codes | C21: =IF(COUNTIF(IC_Analysis!$L$5:$L$80,"CHECK")=0,"OK","CHECK") -> OK
B23: TOTAL OPEN EXCEPTIONS | C23: =COUNTIF(C5:C22,">0.004")+COUNTIF(C5:C22,"<-0.004")+COUNTIF(C5:C22,"INVESTIGATE")+COUNTIF(C5:C22,"CHECK") -> 1

Sheet Legal_Notes
A1: Legal_Notes - Cyprus VAT rules used in this working (as at October 2026)
A2: Summary for preparation purposes only. Check the current law and Tax Department announcements every quarter.
B4: Law
B5: Value Added Tax Law N.95(I)/2000 as amended, and the regulations / decisions issued under it; EU VAT Directive 2006/112/EC; Implementing Regulation 282/2011.
B7: VAT rates
B8: 19% standard rate - all supplies not covered by a reduced, zero or exempt schedule.
B9: 9% reduced rate - e.g. hotel accommodation, restaurant and catering services (excluding alcoholic drinks, beer, wine, soft drinks), certain passenger transport.
B10: 5% reduced rate - e.g. foodstuffs, water, pharmaceuticals, vaccines, books (where not 3%), qualifying first residence (with conditions amended from 1 September 2026), renovation of private homes over 3 years old.
B11: 3% super-reduced rate - e.g. books, newspapers and periodicals, and some other items introduced in 2023.
B12: 0% - exports, intra-EU supplies of goods, qualifying ships / aircraft supplies, and items temporarily zero-rated by decree (several temporary zero rates on basic goods run through 2026-2027 - check the current decree for each item).
B14: Filing and payment
B15: Quarterly VAT 4 return and payment due by the 10th day of the second month after the end of the quarter (e.g. Q3 Jul-Sep: 10 November). Filed electronically on the Tax For All (TFA) portal.
B16: VIES recapitulative statement: monthly, by the 15th day after the end of each month in which intra-EU supplies of goods or general-rule B2B services were made. Corrections within one month.
B17: Intrastat (Statistical Service) is separate and applies when intra-EU goods flows exceed the annual thresholds.
... B52: EU VIES VAT number validation: https://ec.europa.eu/taxation_customs/vies/

Sheet Lists
A1: Lists - EU member states (other than Cyprus)
A2: Any country code not listed here (and not CY) is treated as a third country.
A4: ISO code | B4: Member state
A5: AT | B5: Austria
A6: BE | B6: Belgium
A7: BG | B7: Bulgaria
A8: HR | B8: Croatia
A9: CZ | B9: Czechia
A10: DK | B10: Denmark
A11: EE | B11: Estonia
A12: FI | B12: Finland
A13: FR | B13: France
A14: DE | B14: Germany
A15: GR | B15: Greece
... A32: XI | B32: Northern Ireland (goods only)
A34: Note: the UK (GB) is a third country since 1.1.2021 (Northern Ireland - XI - stays in the EU VAT area for goods only).
